Workbook

Sheet Valuation Dashboard
D1: =+Timeline!A2 -> #VALUE!
S3: METODOLOGIAS DE VALUACION
S5: A. | T5: VALOR PRESENT DE FLUJO DE FONDOS
T6: Proyeccion Proforma: | Z6: 2026-2030
D7: VALUACION INDICATIVA DE LA EMPRESA | T7: Tasa de descuento: | AA7: =+Engine!Q219 -> 0.161485
T8: Pertetuidad aplicada (USD): | AA8: =+J17 -> 9731762.4 | AI8: Pond.
D9: COMPANY VALUATION (Pre Money) | U9: Valuacion Obtenida: | AD9: =+Engine!Q223 -> 7185460.4 | AG9: USD | AI9: 0.6
D10: =+AD21/1000000 -> 6.6935852 | L10: M USD | M10: TRUE
S11: B. | T11: MULTIPLO DE EBITDA | AB11: 18.83 | AD11: Benchmark
T12: EBITDA 2025 (USD) | AA12: =+R38*1000 -> 301024.34
T13: Multimplo Aplicable: | AB13: =+Engine!Q227 -> 13
E14: Methodologia: | J14: VAN Perpetuidad | U14: Valuacion Obtenida: | AD14: =+Engine!Q229 -> 6294468.4 | AG14: USD | AI14: 0.3
E15: Tasa de descuento:
S16: C. | T16: MULTIPLO DE VENTAS | AB16: 2.36 | AD16: Benchmark
A17: TRUE | E17: Valor Aplicado: | J17: =+Engine!$AT$214 -> 9731762.4 | N17: USD | T17: VENTAS 2025 (USD) | AA17: =+Engine!Q233 -> 1646561.4
T18: Multimplo Aplicable: | AB18: =+Engine!Q232 -> 3 | AN18: VENTAS | BM18: EBITDA
E19: Aplicacion Perpetuidad: | U19: Valuacion Obtenida: | AD19: =+Engine!Q234 -> 4939684.2 | AG19: USD | AI19: =100%-AI9-AI14 -> 0.1 | AN19: 2023 | AQ19: 2024 | AT19: =+AQ19+1 -> 2025 | AW19: =+AT19+1 -> 2026 | AZ19: =+AW19+1 -> 2027 | BC19: =+AZ19+1 -> 2028 | BF19: =+BC19+1 -> 2029 | BI19: =+BF19+1 -> 2030 | BM19: 2023 | BP19: 2024 | BS19: =+BP19+1 -> 2025 | BV19: =+BS19+1 -> 2026 | BY19: =+BV19+1 -> 2027 | CB19: =+BY19+1 -> 2028 | CE19: =+CB19+1 -> 2029 | CH19: =+CE19+1 -> 2030
E20: Tasa de descuento: | K20: =+Engine!$Q$219 -> 0.161485 | AN20: =+SUMIFS(Engine!$O$175:$V$175,Engine!$O$163:$V$163,AN19) -> 666807.44 | AQ20: =+SUMIFS(Engine!$O$175:$V$175,Engine!$O$163:$V$163,AQ19) -> 919497.15 | AT20: =+SUMIFS(Engine!$O$175:$V$175,Engine!$O$163:$V$163,AT19) -> 1312010 | AW20: =+SUMIFS(Engine!$O$175:$V$175,Engine!$O$163:$V$163,AW19) -> 2153259.9 | AZ20: =+SUMIFS(Engine!$O$175:$V$175,Engine!$O$163:$V$163,AZ19) -> 3174238.2 | BC20: =+SUMIFS(Engine!$O$175:$V$175,Engine!$O$163:$V$163,BC19) -> 3972505.2 | BF20: =+SUMIFS(Engine!$O$175:$V$175,Engine!$O$163:$V$163,BF19) -> 4486353.7 | BI20: =+SUMIFS(Engine!$O$175:$V$175,Engine!$O$163:$V$163,BI19) -> 4780585.2 | BM20: =+SUMIFS(Engine!$O$262:$V$262,Engine!$O$163:$V$163,BM19) -> 206741.02 | BP20: =+SUMIFS(Engine!$O$262:$V$262,Engine!$O$163:$V$163,BP19) -> 203147.84 | BS20: =+SUMIFS(Engine!$O$262:$V$262,Engine!$O$163:$V$163,BS19) -> 301024.34 | BV20: =+SUMIFS(Engine!$O$262:$V$262,Engine!$O$163:$V$163,BV19) -> 551914.83 | BY20: =+SUMIFS(Engine!$O$262:$V$262,Engine!$O$163:$V$163,BY19) -> 827997.79 | CB20: =+SUMIFS(Engine!$O$262:$V$262,Engine!$O$163:$V$163,CB19) -> 1048977.7 | CE20: =+SUMIFS(Engine!$O$262:$V$262,Engine!$O$163:$V$163,CE19) -> 1193133.2 | CH20: =+SUMIFS(Engine!$O$262:$V$262,Engine!$O$163:$V$163,CH19) -> 1276274.6
E21: Tasa de Crecimiento: | K21: =+Engine!AT200 -> 0.06968331 | T21: VALUACION PONDERADA | AD21: =+AD9*AI9+AD14*AI14+AD19*AI19 -> 6693585.2 | AG21: USD | AI21: =+AI9+AI14+AI19 -> 1 | AQ21: =+(AQ20-AN20)/AN20 -> 0.37895455 | AT21: =+(AT20-AQ20)/AQ20 -> 0.42687769 | AW21: =+(AW20-AT20)/AT20 -> 0.64119171 | AZ21: =+(AZ20-AW20)/AW20 -> 0.4741547 | BC21: =+(BC20-AZ20)/AZ20 -> 0.25148304 | BF21: =+(BF20-BC20)/BC20 -> 0.12935124 | BI21: =+(BI20-BF20)/BF20 -> 0.065583657 | BP21: =+(BP20-BM20)/BM20 -> -0.017380107 | BS21: =+(BS20-BP20)/BP20 -> 0.4817994 | BV21: =+(BV20-BS20)/BS20 -> 0.83345581 | BY21: =+(BY20-BV20)/BV20 -> 0.50022748 | CB21: =+(CB20-BY20)/BY20 -> 0.26688467 | CE21: =+(CE20-CB20)/CB20 -> 0.13742471 | CH21: =+(CH20-CE20)/CE20 -> 0.06968331
E22: Valor Perpetuidad: | J22: =+Engine!$AT$214/(1-K23) -> 9731762.4 | N22: USD
Q23: Directorio | W23: ANDESMAR INCL. | AC23: Ajuste Costos Andesmar | AI23: 0.015 | AY23: Atemperador
AN24: AJUSTE CURVA DE CRECIMIENTO | AY24: 1 | BB24: 1.5 | BE24: 2 | BH24: 2 | BK24: 2
AN25: % sobre ventas Acumuladas | AV25: 2025 | AY25: 2026 | BB25: =+AY25+1 -> 2027 | BE25: =+BB25+1 -> 2028 | BH25: =+BE25+1 -> 2029 | BK25: =+BH25+1 -> 2030
E26: PROYECCIONES FINANCIERAS | M26: 2023 | P26: =+M26+1 -> 2024 | S26: =+P26+1 -> 2025 | V26: =+S26+1 -> 2026 | Y26: =+V26+1 -> 2027 | AB26: =+Y26+1 -> 2028 | AE26: =+AB26+1 -> 2029 | AH26: =+AE26+1 -> 2030 | AN26: =+Engine!N142 -> TOLWEB SaaS | AS26: Q1 | AV26: =+Engine!W142 -> 2.4493832 | AY26: =+Engine!AA142 -> 1.1118614 | BB26: =+Engine!AE142 -> 0.74124092 | BE26: =+Engine!AI142 -> 0.37062046 | BH26: =+Engine!AM142 -> 0.18531023 | BK26: =+Engine!AQ142 -> 0.092655115
E27: Valores en Miles de Dolares | M27: Año -2 | P27: Año -1 | S27: Año 0 | V27: Año 1 | Y27: Año 2 | AB27: Año 3 | AE27: Año 4 | AH27: Año 5 | AS27: Q2 | AV27: =+Engine!X142 -> 2.2648922 | AY27: =+Engine!AB142 -> 1.1184093 | BB27: =+Engine!AF142 -> 0.74560622 | BE27: =+Engine!AJ142 -> 0.37280311 | BH27: =+Engine!AN142 -> 0.18640155 | BK27: =+Engine!AR142 -> 0.093200777
E28: Ingresos | AS28: Q3 | AV28: =+Engine!Y142 -> 1.4408391 | AY28: =+Engine!AC142 -> 0.88730174 | BB28: =+Engine!AG142 -> 0.59153449 | BE28: =+Engine!AK142 -> 0.29576725 | BH28: =+Engine!AO142 -> 0.14788362 | BK28: =+Engine!AS142 -> 0.073941812
E29: TOLWEB | M29: =+SUMIFS(Engine!$O$126:$AT$126,Engine!$O$121:$AT$121,M$26)/1000 -> 353.89966 | O29: =+SUMIFS(Engine!$O$126:$AT$126,Engine!$O$121:$AT$121,P26)/1000 -> 485.87652 | R29: =+SUMIFS(Engine!$O$126:$AT$126,Engine!$O$121:$AT$121,S$26)/1000 -> 923.88919 | U29: =+SUMIFS(Engine!$O$126:$AT$126,Engine!$O$121:$AT$121,V$26)/1000 -> 1698.887 | X29: =+SUMIFS(Engine!$O$126:$AT$126,Engine!$O$121:$AT$121,Y$26)/1000 -> 2663.1139 | AA29: =+SUMIFS(Engine!$O$126:$AT$126,Engine!$O$121:$AT$121,AB$26)/1000 -> 3427.4862 | AD29: =+SUMIFS(Engine!$O$126:$AT$126,Engine!$O$121:$AT$121,AE$26)/1000 -> 3922.7144 | AG29: =+SUMIFS(Engine!$O$126:$AT$126,Engine!$O$121:$AT$121,AH$26)/1000 -> 4207.1729 | AS29: Q4 | AV29: =+Engine!Z142 -> -0.088019356 | AY29: =+Engine!AD142 -> 0.62326699 | BB29: =+Engine!AH142 -> 0.41551132 | BE29: =+Engine!AL142 -> 0.20775566 | BH29: =+Engine!AP142 -> 0.10387783 | BK29: =+Engine!AT142 -> 0.051938916
E30: TOLPOS | M30: =+SUMIFS(Engine!$O$130:$AT$130,Engine!$O$121:$AT$121,M$26)/1000 -> 0 | P30: =+SUMIFS(Engine!$O$130:$AT$130,Engine!$O$121:$AT$121,P26)/1000 -> 0 | R30: =+SUMIFS(Engine!$O$130:$AT$130,Engine!$O$121:$AT$121,S$26)/1000 -> 0 | U30: =+SUMIFS(Engine!$O$130:$AT$130,Engine!$O$121:$AT$121,V$26)/1000 -> 0 | X30: =+SUMIFS(Engine!$O$130:$AT$130,Engine!$O$121:$AT$121,Y$26)/1000 -> 0 | AA30: =+SUMIFS(Engine!$O$130:$AT$130,Engine!$O$121:$AT$121,AB$26)/1000 -> 0 | AD30: =+SUMIFS(Engine!$O$130:$AT$130,Engine!$O$121:$AT$121,AE$26)/1000 -> 0 | AG30: =+SUMIFS(Engine!$O$130:$AT$130,Engine!$O$121:$AT$121,AH$26)/1000 -> 0 | AN30: =+Engine!N146 -> TOLPOS SaaS | AS30: Q1 | AV30: =+Engine!W146 -> 0.46023771 | AY30: =+Engine!AA146 -> 0.18519056 | BB30: =+Engine!AE146 -> 0.12346038 | BE30: =+Engine!AI146 -> 0.061730188 | BH30: =+Engine!AM146 -> 0.030865094 | BK30: =+Engine!AQ146 -> 0.015432547
E31: UNIBUS | M31: =+SUMIFS(Engine!$O$134:$AT$134,Engine!$O$121:$AT$121,M$26)/1000 -> 312.90778 | P31: =+SUMIFS(Engine!$O$134:$AT$134,Engine!$O$121:$AT$121,P26)/1000 -> 433.62063 | R31: =+SUMIFS(Engine!$O$134:$AT$134,Engine!$O$121:$AT$121,S$26)/1000 -> 388.12077 | U31: =+SUMIFS(Engine!$O$134:$AT$134,Engine!$O$121:$AT$121,V$26)/1000 -> 454.37289 | X31: =+SUMIFS(Engine!$O$134:$AT$134,Engine!$O$121:$AT$121,Y$26)/1000 -> 511.1243 | AA31: =+SUMIFS(Engine!$O$134:$AT$134,Engine!$O$121:$AT$121,AB$26)/1000 -> 545.01899 | AD31: =+SUMIFS(Engine!$O$134:$AT$134,Engine!$O$121:$AT$121,AE$26)/1000 -> 563.63926 | AG31: =+SUMIFS(Engine!$O$134:$AT$134,Engine!$O$121:$AT$121,AH$26)/1000 -> 573.41231 | AS31: Q2 | AV31: =+Engine!X146 -> 0.73696351 | AY31: =+Engine!AB146 -> 0.70994269 | BB31: =+Engine!AF146 -> 0.47329513 | BE31: =+Engine!AJ146 -> 0.23664756 | BH31: =+Engine!AN146 -> 0.11832378 | BK31: =+Engine!AR146 -> 0.059161891
E32: Total Ingresos | M32: =SUM(M29:N31) -> 666.80744 | P32: =SUM(P29:Q31) -> 433.62063 | R32: =SUM(R29:T31) -> 1312.01 | U32: =SUM(U29:W31) -> 2153.2599 | X32: =SUM(X29:Z31) -> 3174.2382 | AA32: =SUM(AA29:AC31) -> 3972.5052 | AD32: =SUM(AD29:AF31) -> 4486.3537 | AG32: =SUM(AG29:AI31) -> 4780.5852 | AS32: Q3 | AV32: =+Engine!Y146 -> -0.87235005 | AY32: =+Engine!AC146 -> -0.033005778 | BB32: =+Engine!AG146 -> -0.022003852 | BE32: =+Engine!AK146 -> -0.011001926 | BH32: =+Engine!AO146 -> -0.0055009629 | BK32: =+Engine!AS146 -> -0.0027504815
E33: Costos | AS33: Q4 | AV33: =+Engine!Z146 -> -1 | AY33: =+Engine!AD146 -> -0.2420286 | BB33: =+Engine!AH146 -> -0.1613524 | BE33: =+Engine!AL146 -> -0.080676199 | BH33: =+Engine!AP146 -> -0.0403381 | BK33: =+Engine!AT146 -> -0.02016905
E34: TOLWEB | F34: =+Engine!N187 -> OPERACIONES | M34: =+SUMIFS(Engine!$O$187:$AT$187,Engine!$O$121:$AT$121,M$26)/1000 -> 73.415951 | O34: =+SUMIFS(Engine!$O$187:$AT$187,Engine!$O$121:$AT$121,P$26)/1000 -> 112.8959 | R34: =+SUMIFS(Engine!$O$187:$AT$187,Engine!$O$121:$AT$121,S$26)/1000 -> 175.26955 | U34: =+SUMIFS(Engine!$O$187:$AT$187,Engine!$O$121:$AT$121,V$26)/1000 -> 262.85167 | X34: =+SUMIFS(Engine!$O$187:$AT$187,Engine!$O$121:$AT$121,Y$26)/1000 -> 391.18836 | AA34: =+SUMIFS(Engine!$O$187:$AT$187,Engine!$O$121:$AT$121,AB$26)/1000 -> 492.61621 | AD34: =+SUMIFS(Engine!$O$187:$AT$187,Engine!$O$121:$AT$121,AE$26)/1000 -> 558.32513 | AG34: =+SUMIFS(Engine!$O$187:$AT$187,Engine!$O$121:$AT$121,AH$26)/1000 -> 596.08389 | AN34: =+Engine!N150 -> Plataforma UNIBUS | AS34: Q1 | AV34: =+Engine!W150 -> -0.26276888 | AY34: =+Engine!AA150 -> 0.0070057875 | BB34: =+Engine!AE150 -> 0.004670525 | BE34: =+Engine!AI150 -> 0.0023352625 | BH34: =+Engine!AM150 -> 0.0011676313 | BK34: =+Engine!AQ150 -> 0.00058381563
E35: TOLPOS | F35: =+Engine!N188 -> INFRAESTRUCTURA | M35: =+SUMIFS(Engine!$O$188:$AT$188,Engine!$O$121:$AT$121,M$26)/1000 -> 119.1956 | O35: =+SUMIFS(Engine!$O$126:$AT$126,Engine!$O$121:$AT$121,P$26)/1000 -> 485.87652 | R35: =+SUMIFS(Engine!$O$188:$AT$188,Engine!$O$121:$AT$121,S$26)/1000 -> 281.70995 | U35: =+SUMIFS(Engine!$O$188:$AT$188,Engine!$O$121:$AT$121,V$26)/1000 -> 435.3959 | X35: =+SUMIFS(Engine!$O$188:$AT$188,Engine!$O$121:$AT$121,Y$26)/1000 -> 637.28051 | AA35: =+SUMIFS(Engine!$O$188:$AT$188,Engine!$O$121:$AT$121,AB$26)/1000 -> 793.601 | AD35: =+SUMIFS(Engine!$O$188:$AT$188,Engine!$O$121:$AT$121,AE$26)/1000 -> 893.66553 | AG35: =+SUMIFS(Engine!$O$188:$AT$188,Engine!$O$121:$AT$121,AH$26)/1000 -> 950.78943 | AS35: Q2 | AV35: =+Engine!X150 -> 0.26826886 | AY35: =+Engine!AB150 -> 0.35430475 | BB35: =+Engine!AF150 -> 0.23620317 | BE35: =+Engine!AJ150 -> 0.11810158 | BH35: =+Engine!AN150 -> 0.059050791 | BK35: =+Engine!AR150 -> 0.029525396
E36: UNIBUS | F36: =+Engine!N189 -> PERSONAL | M36: =+SUMIFS(Engine!$O$189:$AT$189,Engine!$O$121:$AT$121,M$26)/1000 -> 267.45487 | O36: =+SUMIFS(Engine!$O$126:$AT$126,Engine!$O$121:$AT$121,P$26)/1000 -> 485.87652 | R36: =+SUMIFS(Engine!$O$189:$AT$189,Engine!$O$121:$AT$121,S$26)/1000 -> 554.00612 | U36: =+SUMIFS(Engine!$O$189:$AT$189,Engine!$O$121:$AT$121,V$26)/1000 -> 903.09748 | X36: =+SUMIFS(Engine!$O$189:$AT$189,Engine!$O$121:$AT$121,Y$26)/1000 -> 1317.7715 | AA36: =+SUMIFS(Engine!$O$189:$AT$189,Engine!$O$121:$AT$121,AB$26)/1000 -> 1637.3103 | AD36: =+SUMIFS(Engine!$O$189:$AT$189,Engine!$O$121:$AT$121,AE$26)/1000 -> 1841.2299 | AG36: =+SUMIFS(Engine!$O$189:$AT$189,Engine!$O$121:$AT$121,AH$26)/1000 -> 1957.4372 | AS36: Q3 | AV36: =+Engine!Y150 -> -0.096218859 | AY36: =+Engine!AC150 -> 0.27909767 | BB36: =+Engine!AG150 -> 0.18606512 | BE36: =+Engine!AK150 -> 0.093032558 | BH36: =+Engine!AO150 -> 0.046516279 | BK36: =+Engine!AS150 -> 0.023258139
E37: Total Costos | M37: =SUM(M34:N36) -> 460.06642 | O37: =SUM(O34:Q36) -> 1084.6489 | R37: =SUM(R34:T36) -> 1010.9856 | U37: =SUM(U34:W36) -> 1601.345 | X37: =SUM(X34:Z36) -> 2346.2404 | AA37: =SUM(AA34:AC36) -> 2923.5275 | AD37: =SUM(AD34:AF36) -> 3293.2205 | AG37: =SUM(AG34:AI36) -> 3504.3106 | AS37: Q4 | AV37: =+Engine!Z150 -> -0.14440828 | AY37: =+Engine!AD150 -> 0.093910975 | BB37: =+Engine!AH150 -> 0.062607317 | BE37: =+Engine!AL150 -> 0.031303658 | BH37: =+Engine!AP150 -> 0.015651829 | BK37: =+Engine!AT150 -> 0.0078259146
E38: EBITDA | M38: =+M32-M37 -> 206.74102 | O38: =+P32-O37 -> -651.02831 | R38: =+R32-R37 -> 301.02434 | U38: =+U32-U37 -> 551.91483 | X38: =+X32-X37 -> 827.99779 | AA38: =+AA32-AA37 -> 1048.9777 | AD38: =+AD32-AD37 -> 1193.1332 | AG38: =+AG32-AG37 -> 1276.2746
E39: Depreciaciones/Amortizaciones | M39: 0 | O39: 0 | R39: 0 | U39: 0 | X39: 0 | AA39: 0 | AD39: 0 | AG39: 0
E40: Intereses Financieros | M40: 0 | O40: 0 | R40: 0 | U40: 0 | X40: 0 | AA40: 0 | AD40: 0 | AG40: 0
E41: Ganancia antes de Impuestos | M41: =+M38-M39-M40 -> 206.74102 | O41: =+O38-O39-O40 -> -651.02831 | R41: =+R38-R39-R40 -> 301.02434 | U41: =+U38-U39-U40 -> 551.91483 | X41: =+X38-X39-X40 -> 827.99779 | AA41: =+AA38-AA39-AA40 -> 1048.9777 | AD41: =+AD38-AD39-AD40 -> 1193.1332 | AG41: =+AG38-AG39-AG40 -> 1276.2746 | AN41: ESTADOS CONTABLES HISTORICOS | AW41: 2021 | AZ41: 2022 | BC41: 2023 | BF41: 2024
E42: Impuestos | I42: 0.35 | M42: =+M41*I42 -> 72.359356 | O42: =+MAX(0,O41*I42) -> 0 | R42: =+R41*$I$42 -> 105.35852 | U42: =+U41*$I$42 -> 193.17019 | X42: =+X41*$I$42 -> 289.79923 | AA42: =+AA41*$I$42 -> 367.1422 | AD42: =+AD41*$I$42 -> 417.59661 | AG42: =+AG41*$I$42 -> 446.69612 | AU42: TC-BoP | AW42: 160 | AZ42: 210 | BC42: 360 | BF42: 995
E43: Ganancia Neta | M43: =+M37-M41 -> 253.3254 | O43: =+P37-O41 -> 651.02831 | R43: =+R41-R42 -> 195.66582 | U43: =+U41-U42 -> 358.74464 | X43: =+X41-X42 -> 538.19856 | AA43: =+AA41-AA42 -> 681.83551 | AD43: =+AD41-AD42 -> 775.53655 | AG43: =+AG41-AG42 -> 829.57851 | AU43: TP-EoP | AW43: 208 | AZ43: 346 | BC43: 1015 | BF43: 1215
AO44: Activos
E45: CASHFLOWS | AO45: Activos Fijos | AW45: 18756.159 | AZ45: 19039.867 | BC45: 47833.705 | BF45: 47274.941
E46: =+E43 -> Ganancia Neta | M46: =+M43 -> 253.3254 | O46: =+O43 -> 651.02831 | R46: =+R43 -> 195.66582 | U46: =+U43 -> 358.74464 | X46: =+X43 -> 538.19856 | AA46: =+AA43 -> 681.83551 | AD46: =+AD43 -> 775.53655 | AG46: =+AG43 -> 829.57851 | AO46: Inventarios | AW46: 0 | AZ46: 0 | BC46: 0 | BF46: 0
E47: =+E39 -> Depreciaciones/Amortizaciones | M47: =+M39 -> 0 | O47: =+O39 -> 0 | R47: =+R39 -> 0 | U47: =+U39 -> 0 | X47: =+X39 -> 0 | AA47: =+AA39 -> 0 | AD47: =+AD39 -> 0 | AG47: =+AG39 -> 0 | AO47: Deudas comerciales | AW47: 303940.92 | AZ47: 315027.04 | BC47: 621773.28 | BF47: 316366.02
E48: Ganancia antes de Impuestos | M48: =+M46+M47 -> 253.3254 | O48: =+O47+O46 -> 651.02831 | R48: =+R47+R46 -> 195.66582 | U48: =+U47+U46 -> 358.74464 | X48: =+X47+X46 -> 538.19856 | AA48: =+AA47+AA46 -> 681.83551 | AD48: =+AD47+AD46 -> 775.53655 | AG48: =+AG47+AG46 -> 829.57851 | AO48: Otras Deudas | AW48: 25226.486 | AZ48: 23978.101 | BC48: 36063.301 | BF48: 21851.628
E49: Perpetuidad | M49: 0 | O49: 0 | R49: 0 | U49: 0 | X49: 0 | AA49: 0 | AD49: 0 | AG49: =+Engine!AT214/1000 -> 9731.7624 | AO49: Efectivo y bancos | AW49: 260148.51 | AZ49: 181973.47 | BC49: 129754.95 | BF49: 201461.4
E50: Ganancia Neta | M50: =+M48+M49 -> 253.3254 | O50: =+O48+O49 -> 651.02831 | R50: =+R48+R49 -> 195.66582 | U50: =+U48+U49 -> 358.74464 | X50: =+X48+X49 -> 538.19856 | AA50: =+AA48+AA49 -> 681.83551 | AD50: =+AD48+AD49 -> 775.53655 | AG50: =+AG48+AG49 -> 10561.341 | AO50: Total Activos | AW50: 608072.08 | AZ50: 540018.48 | BC50: 835425.24 | BF50: 586953.98
AO52: Pasivos
AO53: Pasivos a largo plazo | AW53: 0 | AZ53: 4793.6329 | BC53: 15001.671 | BF53: 6714.3975
AO54: Acreedores | AW54: 173052.11 | AZ54: 88407.592 | BC54: 91134.033 | BF54: 123865.46
AO55: Otros acreedores | AW55: 5306.4183 | AZ55: 11288.185 | BC55: 702103.24 | BF55: 315231.91
AO56: Sobregiro bancario | AW56: 0 | AZ56: 0 | BC56: 0 | BF56: 0
AO57: Total Pasivos | AW57: 178358.52 | AZ57: 104489.41 | BC57: 808238.94 | BF57: 445811.76
AO58: Patrimonio Neto | AW58: =+AW50-AW57 -> 429713.55 | AZ58: =+AZ50-AZ57 -> 435529.07 | BC58: =+BC50-BC57 -> 27186.3 | BF58: =+BF50-BF57 -> 141142.22
AO60: Ingresos | AW60: 2153104.1 | AZ60: 1389991.3 | BC60: 1988179.8 | BF60: 1406869.2 | CM60: 50
AO61: EBITDA | AW61: 174594.68 | AZ61: 111109.63 | BC61: 57171.3 | BF61: 64243.428 | CM61: 50
AO62: EBIT | AW62: 117274.51 | AZ62: 79919.113 | BC62: 45425.251 | BF62: 54762.429 | CM62: 50
AO63: Resultado Neto | AW63: 117274.51 | AZ63: 79919.113 | BC63: 45425.251 | BF63: 54762.429
CM64: 50
AO65: Indice de Liquidez | AW65: =+(AW46+AW47+AW48+AW49)/(AW54+AW55+AW56) -> 3.3041085 | AX65: =+(AX40+AX41+AX42+AX43)/(AX48+AX49+AX50) -> #DIV/0! | AY65: =+(AY40+AY41+AY42+AY43)/(AY48+AY49+AY50) -> #DIV/0! | AZ65: =+(AZ46+AZ47+AZ48+AZ49)/(AZ54+AZ55+AZ56) -> 5.2256838 | BA65: =+(BA40+BA41+BA42+BA43)/(BA48+BA49+BA50) -> #DIV/0! | BB65: =+(BB40+BB41+BB42+BB43)/(BB48+BB49+BB50) -> #DIV/0! | BC65: =+(BC46+BC47+BC48+BC49)/(BC54+BC55+BC56) -> 0.99288267 | BD65: =+(BD40+BD41+BD42+BD43)/(BD48+BD49+BD50) -> #DIV/0! | BE65: =+(BE40+BE41+BE42+BE43)/(BE48+BE49+BE50) -> #DIV/0! | BF65: =+(BF46+BF47+BF48+BF49)/(BF54+BF55+BF56) -> 1.2290646 | BG65: =+(BG40+BG41+BG42+BG43)/(BG48+BG49+BG50) -> #DIV/0! | BH65: =+(BH40+BH41+BH42+BH43)/(BH48+BH49+BH50) -> #DIV/0!
AO66: Indice de Endeudamiento | AW66: =+AW57/AW50 -> 0.29331806 | AZ66: =+AZ57/AZ50 -> 0.19349229 | BC66: =+BC57/BC50 -> 0.96745813 | BF66: =+BF57/BF50 -> 0.75953444 | CM66: 50
AO67: Margen Neto | AW67: =+AW63/AW60 -> 0.054467645 | AZ67: =+AZ63/AZ60 -> 0.057496123 | BC67: =+BC63/BC60 -> 0.022847658 | BF67: =+BF63/BF60 -> 0.038925033 | CM67: 50
AO68: Retorno Sobre Activos (ROA) | AW68: =+AW63/AW50 -> 0.19286284 | AZ68: =+AZ63/AZ50 -> 0.14799329 | BC68: =+BC63/BC50 -> 0.054373808 | BF68: =+BF63/BF50 -> 0.093299357 | CM68: 50
AO69: Rotacion de Activos | AW69: =+AW60/AW50 -> 3.5408699 | AZ69: =+AZ60/AZ50 -> 2.5739699 | BC69: =+BC60/BC50 -> 2.3798417 | BF69: =+BF60/BF50 -> 2.3968986 | CM69: 50

Sheet Sheet1
F4: V A L U A C I O N
J7: Agosto 2025
G8: =+'Valuation Dashboard'!D1 -> #VALUE!
G17: =+'Valuation Dashboard'!D10*1000000 -> 6693585.2
G21: Plataforma integral para la comercialización y distribución de servicios de autobuses interurbanos y otras modalidades de movilidad. Modelo de Negocio Dual (B2C: UNIBUS; B2B: TOLWEB, TOLPOS, TOL API)

Sheet Timeline
A2: #VALUE! | I2: Year | J2: 2023 | K2: =+YEAR(K4) -> 2023 | L2: =+YEAR(L4) -> 2023 | M2: =+YEAR(M4) -> 2023 | N2: =+YEAR(N4) -> 2023 | O2: =+YEAR(O4) -> 2023 | P2: =+YEAR(P4) -> 2023 | Q2: =+YEAR(Q4) -> 2023 | R2: =+YEAR(R4) -> 2023 | ... DA2: =+YEAR(DA4) -> 2030
D3: PROYECCIONES FINANCIERAS | H3: Powered by: | I3: Project month | J3: =+ROUND(+(J4-$E$9)/30,0) -> -30 | K3: =+ROUND(+(K4-$E$9)/30,0) -> -29 | L3: =+ROUND(+(L4-$E$9)/30,0) -> -28 | M3: =+ROUND(+(M4-$E$9)/30,0) -> -27 | N3: =+ROUND(+(N4-$E$9)/30,0) -> -26 | O3: =+ROUND(+(O4-$E$9)/30,0) -> -25 | P3: =+ROUND(+(P4-$E$9)/30,0) -> -24 | Q3: =+ROUND(+(Q4-$E$9)/30,0) -> -23 | ... DA3: =+ROUND(+(DA4-$E$9)/30,0) -> 66
H4: #VALUE! | I4: Start | J4: 44927 | K4: =+J5+1 -> 44958 | L4: =+K5+1 -> 44986 | M4: =+L5+1 -> 45017 | N4: =+M5+1 -> 45047 | O4: =+N5+1 -> 45078 | P4: =+O5+1 -> 45108 | Q4: =+P5+1 -> 45139 | R4: =+Q5+1 -> 45170 | ... DA4: =+CZ5+1 -> 47818
I5: End | J5: =+EOMONTH(J4,0) -> 44957 | K5: =+EOMONTH(K4,0) -> 44985 | L5: =+EOMONTH(L4,0) -> 45016 | M5: =+EOMONTH(M4,0) -> 45046 | N5: =+EOMONTH(N4,0) -> 45077 | O5: =+EOMONTH(O4,0) -> 45107 | P5: =+EOMONTH(P4,0) -> 45138 | Q5: =+EOMONTH(Q4,0) -> 45169 | ... DA5: =+EOMONTH(DA4,0) -> 47848
J6: Q1 | K6: Q1 | L6: Q1 | M6: Q2 | N6: Q2 | O6: Q2 | P6: Q3 | Q6: Q3 | R6: Q3 | S6: Q4 | T6: Q4 | U6: Q4 | V6: Q1 | W6: Q1 | X6: Q1 | Y6: Q2 | Z6: Q2 | AA6: Q2 | AB6: Q3 | AC6: Q3 | AD6: Q3 | AE6: Q4 | AF6: Q4 | AG6: Q4 | AH6: Q1 | AI6: Q1 | AJ6: Q1 | AK6: Q2 | AL6: Q2 | AM6: Q2 | AN6: Q3 | AO6: Q3 | AP6: Q3 | AQ6: Q4 | AR6: Q4 | AS6: Q4 | AT6: Q1 | AU6: Q1 | AV6: Q1 | AW6: Q2 | AX6: Q2 | AY6: Q2 | AZ6: Q3 | BA6: Q3 | BB6: Q3 | BC6: Q4 | BD6: Q4 | BE6: Q4 | BF6: Q1 | BG6: Q1 | BH6: Q1 | BI6: Q2 | BJ6: Q2 | BK6: Q2 | BL6: Q3 | BM6: Q3 | BN6: Q3 | BO6: Q4 | BP6: Q4 | BQ6: Q4 | BR6: Q1 | BS6: Q1 | BT6: Q1 | BU6: Q2 | BV6: Q2 | BW6: Q2 | BX6: Q3 | BY6: Q3 | BZ6: Q3 | CA6: Q4 | CB6: Q4 | CC6: Q4 | CD6: Q1 | CE6: Q1 | CF6: Q1 | CG6: Q2 | CH6: Q2 | CI6: Q2 | CJ6: Q3 | CK6: Q3 | CL6: Q3 | CM6: Q4 | CN6: Q4 | CO6: Q4 | CP6: Q1 | CQ6: Q1 | CR6: Q1 | CS6: Q2 | CT6: Q2 | CU6: Q2 | CV6: Q3 | CW6: Q3 | CX6: Q3 | CY6: Q4 | CZ6: Q4 | DA6: Q4
I7: Inflation % | J7: =+SUMIFS('Curva Dolar Blue'!$S:$S,'Curva Dolar Blue'!$Q:$Q,Timeline!J4) -> 0.06 | K7: =+SUMIFS('Curva Dolar Blue'!$S:$S,'Curva Dolar Blue'!$Q:$Q,Timeline!K4) -> 0.066 | L7: =+SUMIFS('Curva Dolar Blue'!$S:$S,'Curva Dolar Blue'!$Q:$Q,Timeline!L4) -> 0.077 | M7: =+SUMIFS('Curva Dolar Blue'!$S:$S,'Curva Dolar Blue'!$Q:$Q,Timeline!M4) -> 0.084 | N7: =+SUMIFS('Curva Dolar Blue'!$S:$S,'Curva Dolar Blue'!$Q:$Q,Timeline!N4) -> 0.078 | O7: =+SUMIFS('Curva Dolar Blue'!$S:$S,'Curva Dolar Blue'!$Q:$Q,Timeline!O4) -> 0.06 | P7: =+SUMIFS('Curva Dolar Blue'!$S:$S,'Curva Dolar Blue'!$Q:$Q,Timeline!P4) -> 0.063 | Q7: =+SUMIFS('Curva Dolar Blue'!$S:$S,'Curva Dolar Blue'!$Q:$Q,Timeline!Q4) -> 0.124 | ... AL7: =+SUMIFS('Curva Dolar Blue'!$S:$S,'Curva Dolar Blue'!$Q:$Q,Timeline!AL4) -> 0 | AM7: =+AL7 -> 0 | AN7: =+AM7 -> 0 | AO7: =+AN7 -> 0 | AP7: =+AO7 -> 0 | AQ7: =+AP7 -> 0 | AR7: =+AQ7 -> 0 | AS7: =+AR7 -> 0 | AT7: =+AS7 -> 0 | ... DA7: =+CZ7 -> 0
I8: Cum Factor | J8: =+IF(J4<$E$9,1,I8*(1+J7)) -> 1 | K8: =+IF(K4<$E$9,1,J8*(1+K7)) -> 1 | L8: =+IF(L4<$E$9,1,K8*(1+L7)) -> 1 | M8: =+IF(M4<$E$9,1,L8*(1+M7)) -> 1 | N8: =+IF(N4<$E$9,1,M8*(1+N7)) -> 1 | O8: =+IF(O4<$E$9,1,N8*(1+O7)) -> 1 | P8: =+IF(P4<$E$9,1,O8*(1+P7)) -> 1 | Q8: =+IF(Q4<$E$9,1,P8*(1+Q7)) -> 1 | ... DA8: =+IF(DA4<$E$9,1,CZ8*(1+DA7)) -> 1
D9: Fecha de Inicio | E9: 45839 | G9: (mes 0) | I9: Dolar Oficial | J9: =+SUMIFS('Curva Dolar Blue'!$L:$L,'Curva Dolar Blue'!$K:$K,Timeline!J5) -> 186.875 | K9: =+SUMIFS('Curva Dolar Blue'!$L:$L,'Curva Dolar Blue'!$K:$K,Timeline!K5) -> 197.1533 | L9: =+SUMIFS('Curva Dolar Blue'!$L:$L,'Curva Dolar Blue'!$K:$K,Timeline!L5) -> 208.9883 | M9: =+SUMIFS('Curva Dolar Blue'!$L:$L,'Curva Dolar Blue'!$K:$K,Timeline!M5) -> 222.575 | N9: =+SUMIFS('Curva Dolar Blue'!$L:$L,'Curva Dolar Blue'!$K:$K,Timeline!N5) -> 239.325 | O9: =+SUMIFS('Curva Dolar Blue'!$L:$L,'Curva Dolar Blue'!$K:$K,Timeline!O5) -> 256.675 | P9: =+SUMIFS('Curva Dolar Blue'!$L:$L,'Curva Dolar Blue'!$K:$K,Timeline!P5) -> 275.2833 | Q9: =+SUMIFS('Curva Dolar Blue'!$L:$L,'Curva Dolar Blue'!$K:$K,Timeline!Q5) -> 350.0167 | ... AS9: =+SUMIFS('Curva Dolar Blue'!$L:$L,'Curva Dolar Blue'!$K:$K,Timeline!AS5) -> 1443 | AT9: =+AS9 -> 1443 | AU9: =+AT9 -> 1443 | AV9: =+AU9 -> 1443 | AW9: =+AV9 -> 1443 | AX9: =+AW9 -> 1443 | AY9: =+AX9 -> 1443 | AZ9: =+AY9 -> 1443 | BA9: =+AZ9 -> 1443 | ... DA9: =+CZ9 -> 1443 | DB9: TOTAL
I10: Dolar Blue | J10: =+SUMIFS('Curva Dolar Blue'!$G:$G,'Curva Dolar Blue'!$F:$F,Timeline!J5) -> 382 | K10: =+SUMIFS('Curva Dolar Blue'!$G:$G,'Curva Dolar Blue'!$F:$F,Timeline!K5) -> 375 | L10: =+SUMIFS('Curva Dolar Blue'!$G:$G,'Curva Dolar Blue'!$F:$F,Timeline!L5) -> 393 | M10: =+SUMIFS('Curva Dolar Blue'!$G:$G,'Curva Dolar Blue'!$F:$F,Timeline!M5) -> 468 | N10: =+SUMIFS('Curva Dolar Blue'!$G:$G,'Curva Dolar Blue'!$F:$F,Timeline!N5) -> 490 | O10: =+SUMIFS('Curva Dolar Blue'!$G:$G,'Curva Dolar Blue'!$F:$F,Timeline!O5) -> 493 | P10: =+SUMIFS('Curva Dolar Blue'!$G:$G,'Curva Dolar Blue'!$F:$F,Timeline!P5) -> 550 | Q10: =+SUMIFS('Curva Dolar Blue'!$G:$G,'Curva Dolar Blue'!$F:$F,Timeline!Q5) -> 730 | ... DA10: =+SUMIFS('Curva Dolar Blue'!$G:$G,'Curva Dolar Blue'!$F:$F,Timeline!DA5) -> 0
A13: 1 | C13: VENTAS HISTORICAS | D13: en AR$ | E13: HISTORICO
C15: VENTAS HISTORICAS | D15: TOTALES EN PESOS | G15: Total 2023 - 2025
B17: 1 | C17: TOLWEB SaaS | G17: =SUM(J17:AS17) -> 2.6626288e+09 | H17: =+G17/$G$20 -> 0.65491543 | I17: AR$ | J17: 30394935 | K17: 19249470 | L17: 14315810 | M17: 12755003 | N17: 11614809 | O17: 11414492 | P17: 18124702 | Q17: 15396306 | R17: 21226326 | S17: 27009622 | T17: 39017414 | U17: 66360955 | V17: 54349483 | W17: 44146828 | X17: 41638298 | Y17: 23415888 | Z17: 26737566 | AA17: 37916152 | AB17: 52642707 | AC17: 35840535 | AD17: 50733844 | AE17: 68042942 | AF17: 1.1329965e+08 | AG17: 2.0246708e+08 | AH17: 2.5547975e+08 | AI17: 1.8277755e+08 | AJ17: 1.1781852e+08 | AK17: 1.0630974e+08 | AL17: 70247179 | AM17: 1.04402e+08 | AN17: 1.4282822e+08 | AO17: 1.1552043e+08 | AP17: 1.0060633e+08 | AQ17: 98731153 | AR17: 1.3596149e+08 | AS17: 1.9383565e+08
B18: 2 | C18: TOLPOS SaaS | G18: =SUM(J18:AS18) -> 1.8423755e+08 | H18: =+G18/$G$20 -> 0.045316122 | I18: AR$ | J18: 3497853.2 | K18: 2215231.6 | L18: 1647465.3 | M18: 1467847.5 | N18: 1336633.8 | O18: 1313581.3 | P18: 2085793.2 | Q18: 1771809 | R18: 2442728.5 | S18: 3108271 | T18: 4490129.3 | U18: 7636827.7 | V18: 6695806.4 | W18: 5978176.3 | X18: 6179658.8 | Y18: 5096852.2 | Z18: 5824580.8 | AA18: 6438583 | AB18: 8121611.4 | AC18: 6723016.3 | AD18: 6906396.7 | AE18: 7547652.2 | AF18: 9540187.1 | AG18: 11404994 | AH18: 12139961 | AI18: 10742831 | AJ18: 9151657.9 | AK18: 9482688.2 | AL18: 8088755.3 | AM18: 12239633 | AN18: 1292904 | AO18: 864342.59 | AP18: 763085.58 | AQ18: 0 | AR18: 0 | AS18: 0
B19: 3 | C19: Plataforma UNIBUS | G19: =SUM(J19:AS19) -> 1.2187407e+09 | H19: =+G19/$G$20 -> 0.29976844 | I19: AR$ | J19: 20667399 | K19: 13088907 | L19: 9734205.7 | M19: 8672916.4 | N19: 7897628.2 | O19: 7761420 | P19: 12324108 | Q19: 10468902 | R19: 14433094 | S19: 18365515 | T19: 26530357 | U19: 45122924 | V19: 72482803 | W19: 47199724 | X19: 39174621 | Y19: 28058736 | Z19: 25939260 | AA19: 33462032 | AB19: 35223556 | AC19: 36027855 | AD19: 45636218 | AE19: 51090895 | AF19: 49055097 | AG19: 47451919 | AH19: 53444844 | AI19: 43608163 | AJ19: 36880265 | AK19: 33702854 | AL19: 42665459 | AM19: 33359007 | AN19: 34387046 | AO19: 34292670 | AP19: 44531767 | AQ19: 48857775 | AR19: 52740461 | AS19: 54400307
C20: Totales | G20: =SUM(J20:AS20) -> 4.0656071e+09 | H20: =+G20/$G$20 -> 1 | I20: AR$ | J20: =SUM(J17:J19) -> 54560186 | K20: =SUM(K17:K19) -> 34553608 | L20: =SUM(L17:L19) -> 25697481 | M20: =SUM(M17:M19) -> 22895767 | N20: =SUM(N17:N19) -> 20849071 | O20: =SUM(O17:O19) -> 20489493 | P20: =SUM(P17:P19) -> 32534603 | Q20: =SUM(Q17:Q19) -> 27637017 | ... AS20: =SUM(AS17:AS19) -> 2.4823596e+08
C22: Andesmar Total | G22: =SUM(J22:AS22) -> 8.9839184e+08 | H22: =G22/G20 -> 0.2209736 | I22: AR$ | J22: =J43+J38+J33 -> 12295217 | K22: =K43+K38+K33 -> 7786705.6 | L22: =L43+L38+L33 -> 5790964.5 | M22: =M43+M38+M33 -> 5159594.2 | N22: =N43+N38+N33 -> 4698368.4 | O22: =O43+O38+O33 -> 4617337 | P22: =P43+P38+P33 -> 7331719.8 | Q22: =Q43+Q38+Q33 -> 6228041.8 | ... AG22: =AG43+AG38+AG33 -> 62247678 | AH22: 79333353 | AI22: 58585727 | AJ22: 44719359 | AK22: 41324837 | AL22: 33460086 | AM22: 59055936 | AN22: 68275150 | AO22: 53387115 | AP22: 37662894 | AQ22: 2650382.3 | AR22: 0 | AS22: 0
C24: Totales SIN Andesmar | G24: =SUM(J24:AS24) -> 3.1672152e+09 | H24: =+G24/$G$20 -> 0.7790264 | I24: AR$ | J24: =+J20-J22 -> 42264969 | K24: =+K20-K22 -> 26766902 | L24: =+L20-L22 -> 19906516 | M24: =+M20-M22 -> 17736173 | N24: =+N20-N22 -> 16150703 | O24: =+O20-O22 -> 15872156 | P24: =+P20-P22 -> 25202883 | Q24: =+Q20-Q22 -> 21408975 | ... AS24: =+AS20-AS22 -> 2.4823596e+08
C26: Incidencia Andesmar | G26: =+G22/G20 -> 0.2209736 | I26: % | J26: =+J22/J20 -> 0.22535145 | K26: =+K22/K20 -> 0.22535145 | L26: =+L22/L20 -> 0.22535145 | M26: =+M22/M20 -> 0.22535145 | N26: =+N22/N20 -> 0.22535145 | O26: =+O22/O20 -> 0.22535145 | P26: =+P22/P20 -> 0.22535145 | Q26: =+Q22/Q20 -> 0.22535145 | ... AS26: =+AS22/AS20 -> 0
C30: VENTAS HISTORICAS | D30: DETALLE POR UNIDADES
B32: 1 | C32: TOLWEB SaaS | E32: =+H17 -> 0.65491543 | G32: =SUM(J32:AS32) -> 2.6626288e+09 | H32: 1 | I32: AR$ | J32: =J17 -> 30394935 | K32: =K17 -> 19249470 | L32: =L17 -> 14315810 | M32: =M17 -> 12755003 | N32: =N17 -> 11614809 | O32: =O17 -> 11414492 | P32: =P17 -> 18124702 | Q32: =Q17 -> 15396306 | ... AS32: =AS17 -> 1.9383565e+08
C33: Andesmar - TOLWEB | G33: =SUM(J33:AS33) -> 6.4084161e+08 | H33: =G33/$G$32 -> 0.24068004 | I33: AR$ | J33: =J281 -> 7020043.7 | K33: =K281 -> 4445876.2 | L33: =L281 -> 3306393.3 | M33: =M281 -> 2945907.9 | N33: =N281 -> 2682567.7 | O33: =O281 -> 2636302.2 | P33: =P281 -> 4186098.8 | Q33: =Q281 -> 3555945.8 | ... AG33: =AG281 -> 46761994 | AH33: 67193392 | AI33: 47842896 | AJ33: 35567701 | AK33: 31842149 | AL33: 25371330 | AM33: 45385390 | AN33: 60970618 | AO33: 47354855 | AP33: 36899808 | AQ33: 2650382.3
C34: TOLWEB SaaS sin Andesmar | G34: =SUM(J34:AS34) -> 2.0217872e+09 | H34: =H32-H33 -> 0.75931996 | I34: AR$ | J34: =J32-J33 -> 23374891 | K34: =K32-K33 -> 14803593 | L34: =L32-L33 -> 11009416 | M34: =M32-M33 -> 9809095 | N34: =N32-N33 -> 8932241.6 | O34: =O32-O33 -> 8778189.8 | P34: =P32-P33 -> 13938603 | Q34: =Q32-Q33 -> 11840360 | ... AS34: =AS32-AS33 -> 1.9383565e+08
C35: Incidencia Andesmar | G35: =+G33/G32 -> 0.24068004 | I35: % | J35: =+J33/J32 -> 0.23096097 | K35: =+K33/K32 -> 0.23096097 | L35: =+L33/L32 -> 0.23096097 | M35: =+M33/M32 -> 0.23096097 | N35: =+N33/N32 -> 0.23096097 | O35: =+O33/O32 -> 0.23096097 | P35: =+P33/P32 -> 0.23096097 | Q35: =+Q33/Q32 -> 0.23096097 | ... AS35: =+AS33/AS32 -> 0
B37: 2 | C37: TOLPOS SaaS | E37: =+H18 -> 0.045316122 | G37: =SUM(J37:AS37) -> 1.8423755e+08 | H37: 1 | I37: AR$ | J37: =J18 -> 3497853.2 | K37: =K18 -> 2215231.6 | L37: =L18 -> 1647465.3 | M37: =M18 -> 1467847.5 | N37: =N18 -> 1336633.8 | O37: =O18 -> 1313581.3 | P37: =P18 -> 2085793.2 | Q37: =Q18 -> 1771809 | ... AS37: =AS18 -> 0
C38: Andesmar - TOLPOS | G38: =SUM(J38:AS38) -> 1.8423755e+08 | H38: =G38/G37 -> 1 | I38: AR$ | J38: =J403 -> 3497853.2 | K38: =K403 -> 2215231.6 | L38: =L403 -> 1647465.3 | M38: =M403 -> 1467847.5 | N38: =N403 -> 1336633.8 | O38: =O403 -> 1313581.3 | P38: =P403 -> 2085793.2 | Q38: =Q403 -> 1771809 | ... AG38: =AG403 -> 11404994 | AH38: 12139961 | AI38: 10742831 | AJ38: 9151657.9 | AK38: 9482688.2 | AL38: 8088755.3 | AM38: 12239633 | AN38: 1292904 | AO38: 864342.59 | AP38: 763085.58
C39: TOLPOS SaaS sin Andesmar | G39: =SUM(J39:AS39) -> 0 | H39: =H37-H38 -> 0 | I39: AR$ | J39: =J37-J38 -> 0 | K39: =K37-K38 -> 0 | L39: =L37-L38 -> 0 | M39: =M37-M38 -> 0 | N39: =N37-N38 -> 0 | O39: =O37-O38 -> 0 | P39: =P37-P38 -> 0 | Q39: =Q37-Q38 -> 0 | ... AS39: =AS37-AS38 -> 0
C40: Incidencia Andesmar | G40: =+G38/G37 -> 1 | I40: % | J40: =+J38/J37 -> 1 | K40: =+K38/K37 -> 1 | L40: =+L38/L37 -> 1 | M40: =+M38/M37 -> 1 | N40: =+N38/N37 -> 1 | O40: =+O38/O37 -> 1 | P40: =+P38/P37 -> 1 | Q40: =+Q38/Q37 -> 1 | ... AP40: =+AP38/AP37 -> 1
B42: 3 | C42: Plataforma UNIBUS | E42: =+H19 -> 0.29976844 | G42: =SUM(J42:AS42) -> 1.2187407e+09 | H42: 1 | I42: AR$ | J42: =J19 -> 20667399 | K42: =K19 -> 13088907 | L42: =L19 -> 9734205.7 | M42: =M19 -> 8672916.4 | N42: =N19 -> 7897628.2 | O42: =O19 -> 7761420 | P42: =P19 -> 12324108 | Q42: =Q19 -> 10468902 | ... AS42: =AS19 -> 54400307
C43: Andesmar - UNIBUS | G43: =SUM(J43:AS43) -> 1.8178694e+08 | H43: =G43/G42 -> 0.14915966 | I43: AR$ | J43: =J149 -> 1777320.1 | K43: =K149 -> 1125597.8 | L43: =L149 -> 837105.83 | M43: =M149 -> 745838.86 | N43: =N149 -> 679166.93 | O43: =O149 -> 667453.53 | P43: =P149 -> 1059827.8 | Q43: =Q149 -> 900287.01 | ... AG43: =AG149 -> 4080690.2 | AH43: 18283190 | AI43: 16620067 | AJ43: 14397423 | AK43: 14206990 | AL43: 7070575.1 | AM43: 1430912.8 | AN43: 6011628.9 | AO43: 5167917.3 | AP43: 6051290.8 | AQ43: 9774406.6 | AR43: 9031788.9 | AS43: 13038527
C44: Plataforma UNIBUS sin Andesmar | G44: =SUM(J44:AS44) -> 1.0369538e+09 | H44: =H42-H43 -> 0.85084034 | I44: AR$ | J44: =J42-J43 -> 18890078 | K44: =K42-K43 -> 11963309 | L44: =L42-L43 -> 8897099.9 | M44: =M42-M43 -> 7927077.6 | N44: =N42-N43 -> 7218461.3 | O44: =O42-O43 -> 7093966.5 | P44: =P42-P43 -> 11264280 | Q44: =Q42-Q43 -> 9568615.1 | ... AS44: =AS42-AS43 -> 41361780
C45: Incidencia Andesmar | G45: =+G43/G42 -> 0.14915966 | I45: % | J45: =+J43/J42 -> 0.085996316 | K45: =+K43/K42 -> 0.085996316 | L45: =+L43/L42 -> 0.085996316 | M45: =+M43/M42 -> 0.085996316 | N45: =+N43/N42 -> 0.085996316 | O45: =+O43/O42 -> 0.085996316 | P45: =+P43/P42 -> 0.085996316 | Q45: =+Q43/Q42 -> 0.085996316 | ... AS45: =+AS43/AS42 -> 0.23967745
C49: RATIOS DE CRECIMIENTO
B51: 1 | C51: =+C17 -> TOLWEB SaaS | D51: Crecimiento Mensual | I51: % Mes | J51: 0 | K51: =+K17/J17-1 -> -0.36668824 | L51: =+L17/K17-1 -> -0.25630109 | M51: =+M17/L17-1 -> -0.10902679 | N51: =+N17/M17-1 -> -0.089391871 | O51: =+O17/N17-1 -> -0.017246717 | P51: =+P17/O17-1 -> 0.58786761 | Q51: =+Q17/P17-1 -> -0.15053467 | R51: =+R17/Q17-1 -> 0.37866357 | ... AS51: =+AS17/AR17-1 -> 0.4256658
D52: Crecimiento Annual | I52: % Año | J52: 0 | K52: =+J52 -> 0 | L52: =+K52 -> 0 | M52: =+L52 -> 0 | N52: =+M52 -> 0 | O52: =+N52 -> 0 | P52: =+O52 -> 0 | Q52: =+P52 -> 0 | R52: =+Q52 -> 0 | ... U52: =+T52 -> 0 | V52: =SUM(V17:AG17)/SUM(J17:U17) -> 2.6186259 | W52: =SUM(W17:AH17)/SUM(K17:V17) -> 3.0638863 | X52: =SUM(X17:AI17)/SUM(L17:W17) -> 3.2495942 | Y52: =SUM(Y17:AJ17)/SUM(M17:X17) -> 3.21487 | Z52: =SUM(Z17:AK17)/SUM(N17:Y17) -> 3.3449704 | AA52: =SUM(AA17:AL17)/SUM(O17:Z17) -> 3.3267737 | AB52: =SUM(AB17:AM17)/SUM(P17:AA17) -> 3.2745774 | AC52: =SUM(AC17:AN17)/SUM(Q17:AB17) -> 3.2237917 | ... AS52: =SUM(AS17:BD17)/SUM(AG17:AR17) -> 0.11868825
B55: 2 | C55: =+C37 -> TOLPOS SaaS | D55: Crecimiento Mensual | I55: % Mes | J55: 0 | K55: =+K18/J18-1 -> -0.36668824 | L55: =+L18/K18-1 -> -0.25630109 | M55: =+M18/L18-1 -> -0.10902679 | N55: =+N18/M18-1 -> -0.089391871 | O55: =+O18/N18-1 -> -0.017246717 | P55: =+P18/O18-1 -> 0.58786761 | Q55: =+Q18/P18-1 -> -0.15053467 | R55: =+R18/Q18-1 -> 0.37866357 | ... AQ55: =+AQ18/AP18-1 -> -1
D56: Crecimiento Annual | I56: % Año | J56: 0 | K56: =+J56 -> 0 | L56: =+K56 -> 0 | M56: =+L56 -> 0 | N56: =+M56 -> 0 | O56: =+N56 -> 0 | P56: =+O56 -> 0 | Q56: =+P56 -> 0 | R56: =+Q56 -> 0 | ... U56: =+T56 -> 0 | V56: =SUM(V18:AG18)/SUM(J18:U18) -> 2.6188001 | W56: =SUM(W18:AH18)/SUM(K18:V18) -> 2.5378702 | X56: =SUM(X18:AI18)/SUM(L18:W18) -> 2.4181653 | Y56: =SUM(Y18:AJ18)/SUM(M18:X18) -> 2.2386981 | Z56: =SUM(Z18:AK18)/SUM(N18:Y18) -> 2.161035 | AA56: =SUM(AA18:AL18)/SUM(O18:Z18) -> 2.019761 | AB56: =SUM(AB18:AM18)/SUM(P18:AA18) -> 1.9409681 | AC56: =SUM(AC18:AN18)/SUM(Q18:AB18) -> 1.650241 | ... AS56: =SUM(AS18:BD18)/SUM(AG18:AR18) -> 0
B59: 3 | C59: =+C42 -> Plataforma UNIBUS | D59: Crecimiento Mensual | I59: % Mes | J59: 0 | K59: =+K19/J19-1 -> -0.36668824 | L59: =+L19/K19-1 -> -0.25630109 | M59: =+M19/L19-1 -> -0.10902679 | N59: =+N19/M19-1 -> -0.089391871 | O59: =+O19/N19-1 -> -0.017246717 | P59: =+P19/O19-1 -> 0.58786761 | Q59: =+Q19/P19-1 -> -0.15053467 | R59: =+R19/Q19-1 -> 0.37866357 | ... AS59: =+AS19/AR19-1 -> 0.031471977
D60: Crecimiento Annual | I60: % Año | J60: 0 | K60: =+J60 -> 0 | L60: =+K60 -> 0 | M60: =+L60 -> 0 | N60: =+M60 -> 0 | O60: =+N60 -> 0 | P60: =+O60 -> 0 | Q60: =+P60 -> 0 | R60: =+Q60 -> 0 | ... U60: =+T60 -> 0 | V60: =SUM(V19:AG19)/SUM(J19:U19) -> 2.6185964 | W60: =SUM(W19:AH19)/SUM(K19:V19) -> 1.9918957 | X60: =SUM(X19:AI19)/SUM(L19:W19) -> 1.7373108 | Y60: =SUM(Y19:AJ19)/SUM(M19:X19) -> 1.5651598 | Z60: =SUM(Z19:AK19)/SUM(N19:Y19) -> 1.4902771 | AA60: =SUM(AA19:AL19)/SUM(O19:Z19) -> 1.4610677 | AB60: =SUM(AB19:AM19)/SUM(P19:AA19) -> 1.3602723 | AC60: =SUM(AC19:AN19)/SUM(Q19:AB19) -> 1.2795936 | ... AS60: =SUM(AS19:BD19)/SUM(AG19:AR19) -> 0.10752702
B63: T | C63: TOTAL | D63: Crecimiento Mensual | I63: % Mes | J63: 0 | K63: =+K20/J20-1 -> -0.36668824 | L63: =+L20/K20-1 -> -0.25630109 | M63: =+M20/L20-1 -> -0.10902679 | N63: =+N20/M20-1 -> -0.089391871 | O63: =+O20/N20-1 -> -0.017246717 | P63: =+P20/O20-1 -> 0.58786761 | Q63: =+Q20/P20-1 -> -0.15053467 | R63: =+R20/Q20-1 -> 0.37866357 | ... AS63: =+AS20/AR20-1 -> 0.31549225
D64: Crecimiento Annual | I64: % Año | J64: 0 | K64: =+J64 -> 0 | L64: =+K64 -> 0 | M64: =+L64 -> 0 | N64: =+M64 -> 0 | O64: =+N64 -> 0 | P64: =+O64 -> 0 | Q64: =+P64 -> 0 | R64: =+Q64 -> 0 | ... U64: =+T64 -> 0 | V64: =SUM(V20:AG20)/SUM(J20:U20) -> 2.6186259 | W64: =SUM(W20:AH20)/SUM(K20:V20) -> 2.586213 | X64: =SUM(X20:AI20)/SUM(L20:W20) -> 2.5518965 | Y64: =SUM(Y20:AJ20)/SUM(M20:X20) -> 2.4410868 | Z64: =SUM(Z20:AK20)/SUM(N20:Y20) -> 2.4553463 | AA64: =SUM(AA20:AL20)/SUM(O20:Z20) -> 2.417403 | AB64: =SUM(AB20:AM20)/SUM(P20:AA20) -> 2.3389772 | AC64: =SUM(AC20:AN20)/SUM(Q20:AB20) -> 2.2665729 | ... AS64: =SUM(AS20:BD20)/SUM(AG20:AR20) -> 0.11205814
A69: 2 | C69: VENTAS HISTORICAS | D69: en USD | E69: HISTORICO
C71: VENTAS HISTORICAS | D71: TOTALES EN PESOS | G71: Total 2023 - 2025
B73: 1 | C73: TOLWEB SaaS | G73: =SUM(J73:AS73) -> 2330387.9 | H73: =+G73/$G$76 -> 0.63962268 | I73: USD Blue | J73: =+J17/J$10 -> 79567.891 | K73: =+K17/K$10 -> 51331.919 | L73: =+L17/L$10 -> 36426.997 | M73: =+M17/M$10 -> 27254.28 | N73: =+N17/N$10 -> 23703.692 | O73: =+O17/O$10 -> 23153.128 | P73: =+P17/P$10 -> 32954.004 | Q73: =+Q17/Q$10 -> 21090.83 | ... AS73: =+AS17/AS$10 -> 133220.38
B74: 2 | C74: TOLPOS SaaS | G74: =SUM(J74:AS74) -> 178342.01 | H74: =+G74/$G$76 -> 0.048949616 | I74: USD Blue | J74: =+J18/J$10 -> 9156.6837 | K74: =+K18/K$10 -> 5907.2842 | L74: =+L18/L$10 -> 4192.0237 | M74: =+M18/M$10 -> 3136.4262 | N74: =+N18/N$10 -> 2727.8241 | O74: =+O18/O$10 -> 2664.4651 | P74: =+P18/P$10 -> 3792.3512 | Q74: =+Q18/Q$10 -> 2427.1356 | ... AS74: =+AS18/AS$10 -> 0
B75: 3 | C75: Plataforma UNIBUS | G75: =SUM(J75:AS75) -> 1134649.2 | H75: =+G75/$G$76 -> 0.3114277 | I75: USD Blue | J75: =+J19/J$10 -> 54103.138 | K75: =+K19/K$10 -> 34903.751 | L75: =+L19/L$10 -> 24768.971 | M75: =+M19/M$10 -> 18531.873 | N75: =+N19/N$10 -> 16117.609 | O75: =+O19/O$10 -> 15743.246 | P75: =+P19/P$10 -> 22407.468 | Q75: =+Q19/Q$10 -> 14340.962 | ... AS75: =+AS19/AS$10 -> 37388.527
C76: Totales | G76: =SUM(J76:AS76) -> 3643379.1 | H76: =+G76/$G$76 -> 1 | I76: USD Blue | J76: =SUM(J73:J75) -> 142827.71 | K76: =SUM(K73:K75) -> 92142.954 | L76: =SUM(L73:L75) -> 65387.992 | M76: =SUM(M73:M75) -> 48922.578 | N76: =SUM(N73:N75) -> 42549.125 | O76: =SUM(O73:O75) -> 41560.838 | P76: =SUM(P73:P75) -> 59153.823 | Q76: =SUM(Q73:Q75) -> 37858.927 | ... AS76: =SUM(AS73:AS75) -> 170608.91
C78: Andesmar Total | G78: =SUM(J78:AS78) -> 818786.35 | H78: =G78/G76 -> 0.22473268 | I78: USD Blue | J78: =+J22/J$10 -> 32186.432 | K78: =+K22/K$10 -> 20764.548 | L78: =+L22/L$10 -> 14735.279 | M78: =+M22/M$10 -> 11024.774 | N78: =+N22/N$10 -> 9588.5069 | O78: =+O22/O$10 -> 9365.7951 | P78: =+P22/P$10 -> 13330.4 | Q78: =+Q22/Q$10 -> 8531.5641 | ... AS78: =+AS22/AS$10 -> 0
C80: Totales SIN Andesmar | G80: =SUM(J80:AS80) -> 2824592.7 | H80: =+G80/$G$20 -> 0.000694753 | I80: USD Blue | J80: =+J76-J78 -> 110641.28 | K80: =+K76-K78 -> 71378.406 | L80: =+L76-L78 -> 50652.713 | M80: =+M76-M78 -> 37897.805 | N80: =+N76-N78 -> 32960.618 | O80: =+O76-O78 -> 32195.043 | P80: =+P76-P78 -> 45823.423 | Q80: =+Q76-Q78 -> 29327.363 | ... AS80: =+AS76-AS78 -> 170608.91
C82: Incidencia Andesmar | G82: =+G78/G76 -> 0.22473268 | I82: % | J82: =+J78/J76 -> 0.22535145 | K82: =+K78/K76 -> 0.22535145 | L82: =+L78/L76 -> 0.22535145 | M82: =+M78/M76 -> 0.22535145 | N82: =+N78/N76 -> 0.22535145 | O82: =+O78/O76 -> 0.22535145 | P82: =+P78/P76 -> 0.22535145 | Q82: =+Q78/Q76 -> 0.22535145 | ... AS82: =+AS78/AS76 -> 0
C86: VENTAS HISTORICAS | D86: DETALLE POR UNIDADES
B88: 1 | C88: TOLWEB SaaS | G88: =SUM(J88:AS88) -> 2330387.9 | H88: 1 | I88: USD Blue | J88: =+J32/J$10 -> 79567.891 | K88: =+K32/K$10 -> 51331.919 | L88: =+L32/L$10 -> 36426.997 | M88: =+M32/M$10 -> 27254.28 | N88: =+N32/N$10 -> 23703.692 | O88: =+O32/O$10 -> 23153.128 | P88: =+P32/P$10 -> 32954.004 | Q88: =+Q32/Q$10 -> 21090.83 | ... AS88: =+AS32/AS$10 -> 133220.38
C89: Andesmar - TOLWEB | G89: =SUM(J89:AS89) -> 566722.53 | H89: =G89/$G$32 -> 0.00021284323 | I89: USD Blue | J89: =+J33/J$10 -> 18377.078 | K89: =+K33/K$10 -> 11855.67 | L89: =+L33/L$10 -> 8413.2146 | M89: =+M33/M$10 -> 6294.6749 | N89: =+N33/N$10 -> 5474.6279 | O89: =+O33/O$10 -> 5347.4689 | P89: =+P33/P$10 -> 7611.0888 | Q89: =+Q33/Q$10 -> 4871.1587 | ... AS89: =+AS33/AS$10 -> 0
C90: TOLWEB SaaS sin Andesmar | G90: =SUM(J90:AS90) -> 1763665.4 | H90: =H88-H89 -> 0.99978716 | I90: USD Blue | J90: =J88-J89 -> 61190.814 | K90: =K88-K89 -> 39476.249 | L90: =L88-L89 -> 28013.782 | M90: =M88-M89 -> 20959.605 | N90: =N88-N89 -> 18229.065 | O90: =O88-O89 -> 17805.659 | P90: =P88-P89 -> 25342.915 | Q90: =Q88-Q89 -> 16219.672 | ... AS90: =AS88-AS89 -> 133220.38
C91: Incidencia Andesmar | G91: =+G89/G88 -> 0.24318807 | I91: % | J91: =+J89/J88 -> 0.23096097 | K91: =+K89/K88 -> 0.23096097 | L91: =+L89/L88 -> 0.23096097 | M91: =+M89/M88 -> 0.23096097 | N91: =+N89/N88 -> 0.23096097 | O91: =+O89/O88 -> 0.23096097 | P91: =+P89/P88 -> 0.23096097 | Q91: =+Q89/Q88 -> 0.23096097 | ... AS91: =+AS89/AS88 -> 0
B93: 2 | C93: TOLPOS SaaS | G93: =SUM(J93:AS93) -> 178342.01 | H93: 1 | I93: USD Blue | J93: =+J37/J$10 -> 9156.6837 | K93: =+K37/K$10 -> 5907.2842 | L93: =+L37/L$10 -> 4192.0237 | M93: =+M37/M$10 -> 3136.4262 | N93: =+N37/N$10 -> 2727.8241 | O93: =+O37/O$10 -> 2664.4651 | P93: =+P37/P$10 -> 3792.3512 | Q93: =+Q37/Q$10 -> 2427.1356 | ... AS93: =+AS37/AS$10 -> 0
C94: Andesmar - TOLPOS | G94: =SUM(J94:AS94) -> 178342.01 | H94: =G94/G93 -> 1 | I94: USD Blue | J94: =+J38/J$10 -> 9156.6837 | K94: =+K38/K$10 -> 5907.2842 | L94: =+L38/L$10 -> 4192.0237 | M94: =+M38/M$10 -> 3136.4262 | N94: =+N38/N$10 -> 2727.8241 | O94: =+O38/O$10 -> 2664.4651 | P94: =+P38/P$10 -> 3792.3512 | Q94: =+Q38/Q$10 -> 2427.1356 | ... AS94: =+AS38/AS$10 -> 0
C95: TOLPOS SaaS sin Andesmar | G95: =SUM(J95:AS95) -> 0 | H95: =H93-H94 -> 0 | I95: USD Blue | J95: =J93-J94 -> 0 | K95: =K93-K94 -> 0 | L95: =L93-L94 -> 0 | M95: =M93-M94 -> 0 | N95: =N93-N94 -> 0 | O95: =O93-O94 -> 0 | P95: =P93-P94 -> 0 | Q95: =Q93-Q94 -> 0 | ... AS95: =AS93-AS94 -> 0
C96: Incidencia Andesmar | G96: =+G94/G93 -> 1 | I96: % | J96: =+J94/J93 -> 1 | K96: =+K94/K93 -> 1 | L96: =+L94/L93 -> 1 | M96: =+M94/M93 -> 1 | N96: =+N94/N93 -> 1 | O96: =+O94/O93 -> 1 | P96: =+P94/P93 -> 1 | Q96: =+Q94/Q93 -> 1 | ... AP96: =+AP94/AP93 -> 1 | AQ96: 0 | AR96: 0 | AS96: 0
B98: 3 | C98: Plataforma UNIBUS | G98: =SUM(J98:AS98) -> 1134649.2 | H98: 1 | I98: USD Blue | J98: =+J42/J$10 -> 54103.138 | K98: =+K42/K$10 -> 34903.751 | L98: =+L42/L$10 -> 24768.971 | M98: =+M42/M$10 -> 18531.873 | N98: =+N42/N$10 -> 16117.609 | O98: =+O42/O$10 -> 15743.246 | P98: =+P42/P$10 -> 22407.468 | Q98: =+Q42/Q$10 -> 14340.962 | ... AS98: =+AS42/AS$10 -> 37388.527
C99: Andesmar - UNIBUS | G99: =SUM(J99:AS99) -> 157098.42 | H99: =G99/G98 -> 0.1384555 | I99: USD Blue | J99: =+J43/J$10 -> 4652.6705 | K99: =+K43/K$10 -> 3001.594 | L99: =+L43/L$10 -> 2130.0403 | M99: =+M43/M$10 -> 1593.6728 | N99: =+N43/N$10 -> 1386.055 | O99: =+O43/O$10 -> 1353.8611 | P99: =+P43/P$10 -> 1926.9597 | Q99: =+Q43/Q$10 -> 1233.2699 | ... AS99: =+AS43/AS$10 -> 8961.187
C100: Plataforma UNIBUS sin Andesmar | G100: =SUM(J100:AS100) -> 977550.76 | H100: =H98-H99 -> 0.8615445 | I100: USD Blue | J100: =J98-J99 -> 49450.467 | K100: =K98-K99 -> 31902.157 | L100: =L98-L99 -> 22638.931 | M100: =M98-M99 -> 16938.2 | N100: =N98-N99 -> 14731.554 | O100: =O98-O99 -> 14389.384 | P100: =P98-P99 -> 20480.508 | Q100: =Q98-Q99 -> 13107.692 | ... AS100: =AS98-AS99 -> 28427.34
C101: Incidencia Andesmar | G101: =+G99/G98 -> 0.1384555 | I101: % | J101: =+J99/J98 -> 0.085996316 | K101: =+K99/K98 -> 0.085996316 | L101: =+L99/L98 -> 0.085996316 | M101: =+M99/M98 -> 0.085996316 | N101: =+N99/N98 -> 0.085996316 | O101: =+O99/O98 -> 0.085996316 | P101: =+P99/P98 -> 0.085996316 | Q101: =+Q99/Q98 -> 0.085996316 | ... AS101: =+AS99/AS98 -> 0.23967745
C105: RATIOS DE CRECIMIENTO
B107: 1 | C107: =+C73 -> TOLWEB SaaS | D107: Crecimiento Mensual | I107: % Mes | J107: 0 | K107: =+K73/J73-1 -> -0.35486642 | L107: =+L73/K73-1 -> -0.29036363 | M107: =+M73/L73-1 -> -0.25181096 | N107: =+N73/M73-1 -> -0.13027632 | O107: =+O73/N73-1 -> -0.02322696 | P107: =+P73/O73-1 -> 0.42330679 | Q107: =+Q73/P73-1 -> -0.35999187 | R107: =+R73/Q73-1 -> 0.25021665 | ... AS107: =+AS73/AR73-1 -> 0.4256658
D108: Crecimiento Annual | I108: % Año | J108: 0 | K108: =+J108 -> 0 | L108: =+K108 -> 0 | M108: =+L108 -> 0 | N108: =+M108 -> 0 | O108: =+N108 -> 0 | P108: =+O108 -> 0 | Q108: =+P108 -> 0 | R108: =+Q108 -> 0 | ... U108: =+T108 -> 0 | V108: =SUM(V73:AG73)/SUM(J73:U73) -> 1.3729217 | W108: =+V108 -> 1.3729217 | X108: =+W108 -> 1.3729217 | Y108: =+X108 -> 1.3729217 | Z108: =+Y108 -> 1.3729217 | AA108: =+Z108 -> 1.3729217 | AB108: =+AA108 -> 1.3729217 | AC108: =+AB108 -> 1.3729217 | AD108: =+AC108 -> 1.3729217 | ... AG108: =+AF108 -> 1.3729217 | AH108: =SUM(AH73:AS73)/SUM(V73:AG73) -> 1.960134 | AI108: =SUM(AI73:AT73)/SUM(W73:AH73) -> 1.2931552 | AJ108: =SUM(AJ73:AU73)/SUM(X73:AI73) -> 0.97663017 | AK108: =SUM(AK73:AV73)/SUM(Y73:AJ73) -> 0.8338735 | AL108: =SUM(AL73:AW73)/SUM(Z73:AK73) -> 0.69047179 | AM108: =SUM(AM73:AX73)/SUM(AA73:AL73) -> 0.6092433 | AN108: =SUM(AN73:AY73)/SUM(AB73:AM73) -> 0.50014034 | AO108: =SUM(AO73:AZ73)/SUM(AC73:AN73) -> 0.38059155 | ... AS108: =SUM(AS73:BD73)/SUM(AG73:AR73) -> 0.10491498
B111: 2 | C111: =+C93 -> TOLPOS SaaS | D111: Crecimiento Mensual | I111: % Mes | J111: 0 | K111: =+K74/J74-1 -> -0.35486642 | L111: =+L74/K74-1 -> -0.29036363 | M111: =+M74/L74-1 -> -0.25181096 | N111: =+N74/M74-1 -> -0.13027632 | O111: =+O74/N74-1 -> -0.02322696 | P111: =+P74/O74-1 -> 0.42330679 | Q111: =+Q74/P74-1 -> -0.35999187 | R111: =+R74/Q74-1 -> 0.25021665 | ... AQ111: =+AQ74/AP74-1 -> -1 | AR111: 0 | AS111: 0
D112: Crecimiento Annual | I112: % Año | J112: 0 | K112: =+J112 -> 0 | L112: =+K112 -> 0 | M112: =+L112 -> 0 | N112: =+M112 -> 0 | O112: =+N112 -> 0 | P112: =+O112 -> 0 | Q112: =+P112 -> 0 | R112: =+Q112 -> 0 | ... U112: =+T112 -> 0 | V112: =SUM(V74:AG74)/SUM(J74:U74) -> 1.3733045 | W112: =+V112 -> 1.3733045 | X112: =+W112 -> 1.3733045 | Y112: =+X112 -> 1.3733045 | Z112: =+Y112 -> 1.3733045 | AA112: =+Z112 -> 1.3733045 | AB112: =+AA112 -> 1.3733045 | AC112: =+AB112 -> 1.3733045 | AD112: =+AC112 -> 1.3733045 | ... AG112: =+AF112 -> 1.3733045 | AH112: =SUM(AH74:AS74)/SUM(V74:AG74) -> 0.72402258 | AI112: =SUM(AI74:AT74)/SUM(W74:AH74) -> 0.55407741 | AJ112: =SUM(AJ74:AU74)/SUM(X74:AI74) -> 0.42461779 | AK112: =SUM(AK74:AV74)/SUM(Y74:AJ74) -> 0.33498568 | AL112: =SUM(AL74:AW74)/SUM(Z74:AK74) -> 0.22721751 | AM112: =SUM(AM74:AX74)/SUM(AA74:AL74) -> 0.14192425 | AN112: =SUM(AN74:AY74)/SUM(AB74:AM74) -> 0.023352657 | AO112: =SUM(AO74:AZ74)/SUM(AC74:AN74) -> 0.013492211 | ... AS112: =SUM(AS74:BD74)/SUM(AG74:AR74) -> 0
B115: 3 | C115: =+C98 -> Plataforma UNIBUS | D115: Crecimiento Mensual | I115: % Mes | J115: 0 | K115: =+K75/J75-1 -> -0.35486642 | L115: =+L75/K75-1 -> -0.29036363 | M115: =+M75/L75-1 -> -0.25181096 | N115: =+N75/M75-1 -> -0.13027632 | O115: =+O75/N75-1 -> -0.02322696 | P115: =+P75/O75-1 -> 0.42330679 | Q115: =+Q75/P75-1 -> -0.35999187 | R115: =+R75/Q75-1 -> 0.25021665 | ... AS115: =+AS75/AR75-1 -> 0.031471977
D116: Crecimiento Annual | I116: % Año | J116: 0 | K116: =+J116 -> 0 | L116: =+K116 -> 0 | M116: =+L116 -> 0 | N116: =+M116 -> 0 | O116: =+N116 -> 0 | P116: =+O116 -> 0 | Q116: =+P116 -> 0 | R116: =+Q116 -> 0 | ... U116: =+T116 -> 0 | V116: =SUM(V75:AG75)/SUM(J75:U75) -> 1.3857777 | W116: =+V116 -> 1.3857777 | X116: =+W116 -> 1.3857777 | Y116: =+X116 -> 1.3857777 | Z116: =+Y116 -> 1.3857777 | AA116: =+Z116 -> 1.3857777 | AB116: =+AA116 -> 1.3857777 | AC116: =+AB116 -> 1.3857777 | AD116: =+AC116 -> 1.3857777 | ... AG116: =+AF116 -> 1.3857777 | AH116: =SUM(AH75:AS75)/SUM(V75:AG75) -> 0.89506989 | AI116: =SUM(AI75:AT75)/SUM(W75:AH75) -> 0.82614199 | AJ116: =SUM(AJ75:AU75)/SUM(X75:AI75) -> 0.75998645 | AK116: =SUM(AK75:AV75)/SUM(Y75:AJ75) -> 0.71064927 | AL116: =SUM(AL75:AW75)/SUM(Z75:AK75) -> 0.63637573 | AM116: =SUM(AM75:AX75)/SUM(AA75:AL75) -> 0.52533539 | AN116: =SUM(AN75:AY75)/SUM(AB75:AM75) -> 0.4554393 | AO116: =SUM(AO75:AZ75)/SUM(AC75:AN75) -> 0.39349404 | ... AS116: =SUM(AS75:BD75)/SUM(AG75:AR75) -> 0.096037676
B119: T | C119: TOTAL | D119: Crecimiento Mensual | I119: % Mes | J119: 0 | K119: =+K76/J76-1 -> -0.35486642 | L119: =+L76/K76-1 -> -0.29036363 | M119: =+M76/L76-1 -> -0.25181096 | N119: =+N76/M76-1 -> -0.13027632 | O119: =+O76/N76-1 -> -0.02322696 | P119: =+P76/O76-1 -> 0.42330679 | Q119: =+Q76/P76-1 -> -0.35999187 | R119: =+R76/Q76-1 -> 0.25021665 | ... AS119: =+AS76/AR76-1 -> 0.31549225
D120: Crecimiento Annual | I120: % Año | J120: 0 | K120: =+J120 -> 0 | L120: =+K120 -> 0 | M120: =+L120 -> 0 | N120: =+M120 -> 0 | O120: =+N120 -> 0 | P120: =+O120 -> 0 | Q120: =+P120 -> 0 | R120: =+Q120 -> 0 | ... U120: =+T120 -> 0 | V120: =SUM(V76:AG76)/SUM(J76:U76) -> 1.3778161 | W120: =+V120 -> 1.3778161 | X120: =+W120 -> 1.3778161 | Y120: =+X120 -> 1.3778161 | Z120: =+Y120 -> 1.3778161 | AA120: =+Z120 -> 1.3778161 | AB120: =+AA120 -> 1.3778161 | AC120: =+AB120 -> 1.3778161 | AD120: =+AC120 -> 1.3778161 | ... AG120: =+AF120 -> 1.3778161 | AH120: =SUM(AH76:AS76)/SUM(V76:AG76) -> 1.4753688 | AI120: =SUM(AI76:AT76)/SUM(W76:AH76) -> 1.0980497 | AJ120: =SUM(AJ76:AU76)/SUM(X76:AI76) -> 0.88137049 | AK120: =SUM(AK76:AV76)/SUM(Y76:AJ76) -> 0.77140979 | AL120: =SUM(AL76:AW76)/SUM(Z76:AK76) -> 0.65017151 | AM120: =SUM(AM76:AX76)/SUM(AA76:AL76) -> 0.56107474 | AN120: =SUM(AN76:AY76)/SUM(AB76:AM76) -> 0.46176617 | AO120: =SUM(AO76:AZ76)/SUM(AC76:AN76) -> 0.36492078 | ... AS120: =SUM(AS76:BD76)/SUM(AG76:AR76) -> 0.099131661
A125: 3 | C125: CLIENTES UNIBUS | D125: en AR$ | E125: HISTORICO
C127: INCIDENCIA SOBRE TOTAL | E127: 0.3788
C129: RESUMEN PARETTO
C131: =C148 -> ANDESMAR | E131: =+G131/$G$143 -> 0.3604671 | G131: =SUM(J131:AS131) -> 4.3931593e+08 | H131: =+G131/$G$143 -> 0.3604671 | I131: AR$ | J131: =J148 -> 8147928.5 | K131: =K148 -> 5160179 | L131: =L148 -> 3837619.5 | M131: =M148 -> 3419216.1 | N131: =N148 -> 3113566 | O131: =O148 -> 3059867.2 | P131: =P148 -> 4858664 | Q131: =Q148 -> 4127266.7 | ... AS131: =AS148 -> 13038527
C132: =C149 -> PLUSMAR | E132: =+G132/$G$143 -> 0.13415481 | G132: =SUM(J132:AS132) -> 1.6349993e+08 | H132: =+G132/$G$143 -> 0.13415481 | I132: AR$ | J132: =J149 -> 1777320.1 | K132: =K149 -> 1125597.8 | L132: =L149 -> 837105.83 | M132: =M149 -> 745838.86 | N132: =N149 -> 679166.93 | O132: =O149 -> 667453.53 | P132: =P149 -> 1059827.8 | Q132: =Q149 -> 900287.01 | ... AS132: =AS149 -> 19312740
C133: =C150 -> 20 DE JUNIO | E133: =+G133/$G$143 -> 0.055335036 | G133: =SUM(J133:AS133) -> 67439061 | H133: =+G133/$G$143 -> 0.055335036 | I133: AR$ | J133: =J150 -> 1306266.3 | K133: =K150 -> 827273.84 | L133: =L150 -> 615242.66 | M133: =M150 -> 548164.72 | N133: =N150 -> 499163.25 | O133: =O150 -> 490554.33 | P133: =P150 -> 778935.33 | Q133: =Q150 -> 661678.55 | ... AS133: =AS150 -> 784306.68
C134: =C151 -> TURISMO IN AND OUT S.A. | E134: =+G134/$G$143 -> 0.048210924 | G134: =SUM(J134:AS134) -> 58756616 | H134: =+G134/$G$143 -> 0.048210924 | I134: AR$ | J134: =J151 -> 1099015.3 | K134: =K151 -> 696019.34 | L134: =L151 -> 517628.82 | M134: =M151 -> 461193.41 | N134: =N151 -> 419966.47 | O134: =O151 -> 412723.43 | P134: =P151 -> 655350.16 | Q134: =Q151 -> 556697.24 | ... AS134: =AS151 -> 1172935.8
C135: =C152 -> DEL SUR Y MEDIA AGUA | E135: =+G135/$G$143 -> 0.038245121 | G135: =SUM(J135:AS135) -> 46610886 | H135: =+G135/$G$143 -> 0.038245121 | I135: AR$ | J135: =J152 -> 873166.16 | K135: =K152 -> 552986.4 | L135: =L152 -> 411255.39 | M135: =M152 -> 366417.53 | N135: =N152 -> 333662.78 | O135: =O152 -> 327908.19 | P135: =P152 -> 520674.8 | Q135: =Q152 -> 442295.19 | ... AS135: =AS152 -> 913796.99
C136: =C153 -> MARGA | E136: =+G136/$G$143 -> 0.02319655 | G136: =SUM(J136:AS136) -> 28270580 | H136: =+G136/$G$143 -> 0.02319655 | I136: AR$ | J136: =J153 -> 556840.27 | K136: =K153 -> 352653.5 | L136: =L153 -> 262268.02 | M136: =M153 -> 233673.78 | N136: =N153 -> 212785.24 | O136: =O153 -> 209115.4 | P136: =P153 -> 332047.57 | Q136: =Q153 -> 282062.89 | ... AS136: =AS153 -> 212871.34
C137: =C154 -> BUSES LEP | E137: =+G137/$G$143 -> 0.022419548 | G137: =SUM(J137:AS137) -> 27323616 | H137: =+G137/$G$143 -> 0.022419548 | I137: AR$ | J137: =J154 -> 543431.56 | K137: =K154 -> 344161.6 | L137: =L154 -> 255952.61 | M137: =M154 -> 228046.92 | N137: =N154 -> 207661.38 | O137: =O154 -> 204079.9 | P137: =P154 -> 324051.86 | Q137: =Q154 -> 275270.82 | ... AS137: =AS154 -> 140042.11
C138: =C155 -> RIO URUGUAY | E138: =+G138/$G$143 -> 0.019840752 | G138: =SUM(J138:AS138) -> 24180733 | H138: =+G138/$G$143 -> 0.019840752 | I138: AR$ | J138: =J155 -> 477297.11 | K138: =K155 -> 302277.88 | L138: =L155 -> 224803.73 | M138: =M155 -> 200294.1 | N138: =N155 -> 182389.43 | O138: =O155 -> 179243.81 | P138: =P155 -> 284615.45 | Q138: =Q155 -> 241770.96 | ... AS138: =AS155 -> 169373.15
C139: =C156 -> LA TOSTADENSE Y CIA SRL | E139: =+G139/$G$143 -> 0.018720657 | G139: =SUM(J139:AS139) -> 22815627 | H139: =+G139/$G$143 -> 0.018720657 | I139: AR$ | J139: =J156 -> 449604.46 | K139: =K156 -> 284739.8 | L139: =L156 -> 211760.68 | M139: =M156 -> 188673.09 | N139: =N156 -> 171807.25 | O139: =O156 -> 168844.14 | P139: =P156 -> 268102.14 | Q139: =Q156 -> 227743.47 | ... AS139: =AS156 -> 169173.22
C140: =C157 -> EL PRACTICO S.A. | E140: =+G140/$G$143 -> 0.017703442 | G140: =SUM(J140:AS140) -> 21575905 | H140: =+G140/$G$143 -> 0.017703442 | I140: AR$ | J140: =J157 -> 423981.06 | K140: =K157 -> 268512.19 | L140: =L157 -> 199692.23 | M140: =M157 -> 177920.42 | N140: =N157 -> 162015.78 | O140: =O157 -> 159221.54 | P140: =P157 -> 252822.73 | Q140: =Q157 -> 214764.15 | ... AS140: =AS157 -> 174934.6
C141: =C158 -> BALUT | E141: =+G141/$G$143 -> 0.027111078 | G141: =SUM(J141:AS141) -> 33041374 | H141: =+G141/$G$143 -> 0.027111078 | I141: AR$ | J141: =J158 -> 408221.04 | K141: =K158 -> 258531.19 | L141: =L158 -> 192269.36 | M141: =M158 -> 171306.85 | N141: =N158 -> 155993.41 | O141: =O158 -> 153303.04 | P141: =P158 -> 243424.93 | Q141: =Q158 -> 206781.04 | ... AS141: =AS158 -> 3288344.3
C142: Otros | E142: =+G142/$G$143 -> 0.23459497 | G142: =SUM(J142:AS142) -> 2.8591044e+08 | H142: =+G142/$G$143 -> 0.23459497 | I142: AR$ | J142: =J190-SUM(J131:J141) -> 4604326.6 | K142: =K190-SUM(K131:K141) -> 2915974.2 | L142: =L190-SUM(L131:L141) -> 2168606.9 | M142: =M190-SUM(M131:M141) -> 1932170.6 | N142: =N190-SUM(N131:N141) -> 1759450.3 | O142: =O190-SUM(O131:O141) -> 1729105.5 | P142: =P190-SUM(P131:P141) -> 2745590.7 | Q142: =Q190-SUM(Q131:Q141) -> 2332284.1 | ... AS142: =AS190-SUM(AS131:AS141) -> 15023262
C143: Totales | G143: =SUM(J143:AS143) -> 1.2187407e+09 | H143: =+G143/$G$143 -> 1 | I143: AR$ | J143: =SUM(J131:J142) -> 20667399 | K143: =SUM(K131:K142) -> 13088907 | L143: =SUM(L131:L142) -> 9734205.7 | M143: =SUM(M131:M142) -> 8672916.4 | N143: =SUM(N131:N142) -> 7897628.2 | O143: =SUM(O131:O142) -> 7761420 | P143: =SUM(P131:P142) -> 12324108 | Q143: =SUM(Q131:Q142) -> 10468902 | ... AS143: =SUM(AS131:AS142) -> 54400307
C146: TOTAL CLIENTES UNIBUS
C148: ANDESMAR | E148: =+D148 -> 0 | G148: =SUM(J148:AS148) -> 4.3931593e+08 | H148: =+G148/$G$190 -> 0.3604671 | I148: AR$ | J148: 8147928.5 | K148: 5160179 | L148: 3837619.5 | M148: 3419216.1 | N148: 3113566 | O148: 3059867.2 | P148: 4858664 | Q148: 4127266.7 | R148: 5690112.2 | S148: 7240432.4 | T148: 10459345 | U148: 17789290 | V148: 28575667 | W148: 18608049 | X148: 15444228 | Y148: 11061894 | Z148: 10226310 | AA148: 13192093 | AB148: 13886557 | AC148: 14203645 | AD148: 17991652 | AE148: 20142107 | AF148: 19339513 | AG148: 18707475 | AH148: 21070129 | AI148: 17192110 | AJ148: 14539699 | AK148: 13287035 | AL148: 16820458 | AM148: 13151476 | AN148: 13556771 | AO148: 13519564 | AP148: =+AP$43 -> 6051290.8 | AQ148: =+AQ$43 -> 9774406.6 | AR148: =+AR$43 -> 9031788.9 | AS148: =+AS$43 -> 13038527
C149: PLUSMAR | D149: 0.46692236 | E149: =+D149 -> 0.46692236 | G149: =SUM(J149:AS149) -> 1.6349993e+08 | H149: =+G149/$G$190 -> 0.13415481 | I149: AR$ | J149: 1777320.1 | K149: 1125597.8 | L149: 837105.83 | M149: 745838.86 | N149: 679166.93 | O149: 667453.53 | P149: 1059827.8 | Q149: 900287.01 | R149: 1241192.9 | S149: 1579366.6 | T149: 2281512.9 | U149: 3880405.2 | V149: 6233254 | W149: 4059002.4 | X149: 3368873.1 | Y149: 2412948 | Z149: 2230680.8 | AA149: 2877611.4 | AB149: 3029096 | AC149: 3098262.8 | AD149: 3924546.6 | AE149: 4393628.7 | AF149: 4218557.6 | AG149: 4080690.2 | AH149: 4596059.6 | AI149: 3750141.3 | AJ149: 3171566.9 | AK149: 2898321.3 | AL149: 3669072.3 | AM149: 2868751.7 | AN149: 2957159.3 | AO149: 2949043.3 | AP149: =+$E149*AP$44 -> 17967395 | AQ149: =+$E149*AQ$44 -> 18248899 | AR149: =+$E149*AR$44 -> 20408556 | AS149: =+$E149*AS$44 -> 19312740
C150: 20 DE JUNIO | D150: 0.018962111 | E150: =+D150 -> 0.018962111 | G150: =SUM(J150:AS150) -> 67439061 | H150: =+G150/$G$190 -> 0.055335036 | I150: AR$ | J150: 1306266.3 | K150: 827273.84 | L150: 615242.66 | M150: 548164.72 | N150: 499163.25 | O150: 490554.33 | P150: 778935.33 | Q150: 661678.55 | R150: 912232.12 | S150: 1160777.6 | T150: 1676829.9 | U150: 2851958.2 | V150: 4581217.4 | W150: 2983220.7 | X150: 2476000.5 | Y150: 1773429.9 | Z150: 1639470.1 | AA150: 2114940.9 | AB150: 2226276.6 | AC150: 2277111.7 | AD150: 2884400.5 | AE150: 3229159 | AF150: 3100488.1 | AG150: 2999160.4 | AH150: 3377938.5 | AI150: 2756218.9 | AJ150: 2330987.5 | AK150: 2130161.9 | AL150: 2696636.1 | AM150: 2108429.3 | AN150: 2173405.7 | AO150: 2167440.7 | AP150: =+$E150*AP$44 -> 729671.07 | AQ150: =+$E150*AQ$44 -> 741103.18 | AR150: =+$E150*AR$44 -> 828808.7 | AS150: =+$E150*AS$44 -> 784306.68
C151: TURISMO IN AND OUT S.A. | D151: 0.028357962 | E151: =+D151 -> 0.028357962 | G151: =SUM(J151:AS151) -> 58756616 | H151: =+G151/$G$190 -> 0.048210924 | I151: AR$ | J151: 1099015.3 | K151: 696019.34 | L151: 517628.82 | M151: 461193.41 | N151: 419966.47 | O151: 412723.43 | P151: 655350.16 | Q151: 556697.24 | R151: 767498.21 | S151: 976609.73 | T151: 1410785.6 | U151: 2399469.1 | V151: 3854365.7 | W151: 2509905.6 | X151: 2083160.5 | Y151: 1492059.2 | Z151: 1379353.3 | AA151: 1779386.3 | AB151: 1873057.6 | AC151: 1915827.2 | AD151: 2426764.2 | AE151: 2716823.6 | AF151: 2608567.5 | AG151: 2523316.4 | AH151: 2841997.8 | AI151: 2318919.8 | AJ151: 1961155.2 | AK151: 1792192.3 | AL151: 2268790.3 | AM151: 1773907.8 | AN151: 1828575.1 | AO151: 1823556.5 | AP151: =+$E151*AP$44 -> 1091227.9 | AQ151: =+$E151*AQ$44 -> 1108324.7 | AR151: =+$E151*AR$44 -> 1239488.9 | AS151: =+$E151*AS$44 -> 1172935.8
C152: DEL SUR Y MEDIA AGUA | D152: 0.022092787 | E152: =+D152 -> 0.022092787 | G152: =SUM(J152:AS152) -> 46610886 | H152: =+G152/$G$190 -> 0.038245121 | I152: AR$ | J152: 873166.16 | K152: 552986.4 | L152: 411255.39 | M152: 366417.53 | N152: 333662.78 | O152: 327908.19 | P152: 520674.8 | Q152: 442295.19 | R152: 609776.27 | S152: 775915.08 | T152: 1120867.2 | U152: 1906374.9 | V152: 3062288.2 | W152: 1994116.6 | X152: 1655068.2 | Y152: 1185438.9 | Z152: 1095894.3 | AA152: 1413719.9 | AB152: 1488141.7 | AC152: 1522122.1 | AD152: 1928060.8 | AE152: 2158512.6 | AF152: 2072503.3 | AG152: 2004771.4 | AH152: 2257963.4 | AI152: 1842378.6 | AJ152: 1558135.1 | AK152: 1423894.3 | AL152: 1802550.7 | AM152: 1409367.3 | AN152: 1452800.4 | AO152: 1448813.2 | AP152: =+$E152*AP$44 -> 850140.95 | AQ152: =+$E152*AQ$44 -> 863460.52 | AR152: =+$E152*AR$44 -> 965646.36 | AS152: =+$E152*AS$44 -> 913796.99
C153: MARGA | D153: 0.0051465711 | E153: =+D153 -> 0.0051465711 | G153: =SUM(J153:AS153) -> 28270580 | H153: =+G153/$G$190 -> 0.02319655 | I153: AR$ | J153: 556840.27 | K153: 352653.5 | L153: 262268.02 | M153: 233673.78 | N153: 212785.24 | O153: 209115.4 | P153: 332047.57 | Q153: 282062.89 | R153: 388869.84 | S153: 494820.79 | T153: 714805.54 | U153: 1215743.8 | V153: 1952899.1 | W153: 1271698.9 | X153: 1055479.1 | Y153: 755984.57 | Z153: 698879.66 | AA153: 901565.17 | AB153: 949025.8 | AC153: 970695.97 | AD153: 1229573.4 | AE153: 1376538.4 | AF153: 1321688.1 | AG153: 1278493.7 | AH153: 1439960.7 | AI153: 1174931.7 | AJ153: 993662.39 | AK153: 908053.64 | AL153: 1149532.5 | AM153: 898789.39 | AN153: 926487.78 | AO153: 923945 | AP153: =+$E153*AP$44 -> 198042.51 | AQ153: =+$E153*AQ$44 -> 201145.33 | AR153: =+$E153*AR$44 -> 224949.79 | AS153: =+$E153*AS$44 -> 212871.34
C154: BUSES LEP | D154: 0.0033857852 | E154: =+D154 -> 0.0033857852 | G154: =SUM(J154:AS154) -> 27323616 | H154: =+G154/$G$190 -> 0.022419548 | I154: AR$ | J154: 543431.56 | K154: 344161.6 | L154: 255952.61 | M154: 228046.92 | N154: 207661.38 | O154: 204079.9 | P154: 324051.86 | Q154: 275270.82 | R154: 379505.85 | S154: 482905.5 | T154: 697593.03 | U154: 1186468.7 | V154: 1905873.3 | W154: 1241076.4 | X154: 1030063.1 | Y154: 737780.46 | Z154: 682050.64 | AA154: 879855.49 | AB154: 926173.26 | AC154: 947321.61 | AD154: 1199965.3 | AE154: 1343391.4 | AF154: 1289861.8 | AG154: 1247707.6 | AH154: 1405286.4 | AI154: 1146639.3 | AJ154: 969735 | AK154: 886187.71 | AL154: 1121851.7 | AM154: 877146.55 | AN154: 904177.95 | AO154: 901696.41 | AP154: =+$E154*AP$44 -> 130286.63 | AQ154: =+$E154*AQ$44 -> 132327.89 | AR154: =+$E154*AR$44 -> 147988.18 | AS154: =+$E154*AS$44 -> 140042.11
C155: RIO URUGUAY | D155: 0.0040949193 | E155: =+D155 -> 0.0040949193 | G155: =SUM(J155:AS155) -> 24180733 | H155: =+G155/$G$190 -> 0.019840752 | I155: AR$ | J155: 477297.11 | K155: 302277.88 | L155: 224803.73 | M155: 200294.1 | N155: 182389.43 | O155: 179243.81 | P155: 284615.45 | Q155: 241770.96 | R155: 333320.81 | S155: 424136.94 | T155: 612697.46 | U155: 1042078 | V155: 1673932.6 | W155: 1090040 | X155: 904706.68 | Y155: 647994.17 | Z155: 599046.55 | AA155: 772778.97 | AB155: 813459.97 | AC155: 832034.62 | AD155: 1053932.1 | AE155: 1179903.5 | AF155: 1132888.4 | AG155: 1095864.3 | AH155: 1234266.1 | AI155: 1007095.8 | AJ155: 851720.34 | AK155: 778340.58 | AL155: 985324.79 | AM155: 770399.7 | AN155: 794141.45 | AO155: 791961.9 | AP155: =+$E155*AP$44 -> 157574.44 | AQ155: =+$E155*AQ$44 -> 160043.24 | AR155: =+$E155*AR$44 -> 178983.49 | AS155: =+$E155*AS$44 -> 169373.15
C156: LA TOSTADENSE Y CIA SRL | D156: 0.0040900855 | E156: =+D156 -> 0.0040900855 | G156: =SUM(J156:AS156) -> 22815627 | H156: =+G156/$G$190 -> 0.018720657 | I156: AR$ | J156: 449604.46 | K156: 284739.8 | L156: 211760.68 | M156: 188673.09 | N156: 171807.25 | O156: 168844.14 | P156: 268102.14 | Q156: 227743.47 | R156: 313981.63 | S156: 399528.64 | T156: 577148.92 | U156: 981616.9 | V156: 1576811.5 | W156: 1026796.2 | X156: 852215.85 | Y156: 610397.73 | Z156: 564290.03 | AA156: 727942.55 | AB156: 766263.25 | AC156: 783760.2 | AD156: 992783.26 | AE156: 1111445.8 | AF156: 1067158.5 | AG156: 1032282.5 | AH156: 1162654.3 | AI156: 948664.37 | AJ156: 802303.76 | AK156: 733181.47 | AL156: 928156.52 | AM156: 725701.32 | AN156: 748065.58 | AO156: 746012.49 | AP156: =+$E156*AP$44 -> 157388.44 | AQ156: =+$E156*AQ$44 -> 159854.32 | AR156: =+$E156*AR$44 -> 178772.21 | AS156: =+$E156*AS$44 -> 169173.22
C157: EL PRACTICO S.A. | D157: 0.004229378 | E157: =+D157 -> 0.004229378 | G157: =SUM(J157:AS157) -> 21575905 | H157: =+G157/$G$190 -> 0.017703442 | I157: AR$ | J157: 423981.06 | K157: 268512.19 | L157: 199692.23 | M157: 177920.42 | N157: 162015.78 | O157: 159221.54 | P157: 252822.73 | Q157: 214764.15 | R157: 296087.5 | S157: 376759.1 | T157: 544256.63 | U157: 925673.59 | V157: 1486947.5 | W157: 968278.08 | X157: 803647.23 | Y157: 575610.56 | Z157: 532130.59 | AA157: 686456.38 | AB157: 722593.15 | AC157: 739092.93 | AD157: 936203.56 | AE157: 1048103.5 | AF157: 1006340.1 | AG157: 973451.73 | AH157: 1096393.5 | AI157: 894599.05 | AJ157: 756579.68 | AK157: 691396.73 | AL157: 875259.96 | AM157: 684342.89 | AN157: 705432.58 | AO157: 703496.5 | AP157: =+$E157*AP$44 -> 162748.48 | AQ157: =+$E157*AQ$44 -> 165298.34 | AR157: =+$E157*AR$44 -> 184860.49 | AS157: =+$E157*AS$44 -> 174934.6
C158: BALUT | D158: 0.079502 | E158: =+D158 -> 0.079502 | G158: =SUM(J158:AS158) -> 33041374 | H158: =+G158/$G$190 -> 0.027111078 | I158: AR$ | J158: 408221.04 | K158: 258531.19 | L158: 192269.36 | M158: 171306.85 | N158: 155993.41 | O158: 153303.04 | P158: 243424.93 | Q158: 206781.04 | R158: 285081.48 | S158: 362754.4 | T158: 524025.79 | U158: 891264.89 | V158: 1431675.4 | W158: 932285.71 | X158: 773774.44 | Y158: 554214.24 | Z158: 512350.48 | AA158: 660939.76 | AB158: 695733.26 | AC158: 711619.72 | AD158: 901403.45 | AE158: 1009143.9 | AF158: 968932.92 | AG158: 937267.04 | AH158: 1055638.9 | AI158: 861345.44 | AJ158: 728456.46 | AK158: 665696.47 | AL158: 842725.22 | AM158: 658904.82 | AN158: 679210.58 | AO158: 677346.47 | AP158: =+$E158*AP$44 -> 3059274.8 | AQ158: =+$E158*AQ$44 -> 3107206 | AR158: =+$E158*AR$44 -> 3474926.9 | AS158: =+$E158*AS$44 -> 3288344.3
C159: CRUCERO DEL NORTE | D159: 0.0031499023 | E159: =+D159 -> 0.0031499023 | G159: =SUM(J159:AS159) -> 19990606 | H159: =+G159/$G$190 -> 0.016402674 | I159: AR$ | J159: 395366.5 | K159: 250390.26 | L159: 186214.96 | M159: 165912.54 | N159: 151081.31 | O159: 148475.65 | P159: 235759.68 | Q159: 200269.67 | R159: 276104.5 | S159: 351331.56 | T159: 507524.65 | U159: 863199.71 | V159: 1386593.1 | W159: 902928.82 | X159: 749408.93 | Y159: 536762.5 | Z159: 496217 | AA159: 640127.32 | AB159: 673825.2 | AC159: 689211.41 | AD159: 873019.01 | AE159: 977366.76 | AF159: 938422.04 | AG159: 907753.29 | AH159: 1022397.7 | AI159: 834222.39 | AJ159: 705517.98 | AK159: 644734.24 | AL159: 816188.51 | AM159: 638156.46 | AN159: 657822.81 | AO159: 656017.39 | AP159: =+$E159*AP$44 -> 121209.74 | AQ159: =+$E159*AQ$44 -> 123108.79 | AR159: =+$E159*AR$44 -> 137678.05 | AS159: =+$E159*AS$44 -> 130285.57
...

Sheet Engine
A2: VAL | B2: =+'Valuation Dashboard'!D10 -> 6.6935852 | C2: M USD | D2: 1 | H2: ANDESMAR
B3: =+B2*D3 -> 4.6855096 | C3: M USD | D3: 0.7
O6: =+YEAR(O8) -> 2023 | P6: =+YEAR(P8) -> 2023 | Q6: =+YEAR(Q8) -> 2023 | R6: =+YEAR(R8) -> 2023 | S6: =+YEAR(S8) -> 2023 | T6: =+YEAR(T8) -> 2023 | U6: =+YEAR(U8) -> 2023 | V6: =+YEAR(V8) -> 2023 | ... AX6: =+YEAR(AX8) -> 2025
N7: VENTAS HISTORICAS | O7: Q1 | P7: =+O7 -> Q1 | Q7: =+P7 -> Q1 | R7: Q2 | S7: =+R7 -> Q2 | T7: =+S7 -> Q2 | U7: Q3 | V7: =+U7 -> Q3 | W7: =+V7 -> Q3 | X7: Q4 | Y7: =+X7 -> Q4 | Z7: =+Y7 -> Q4 | AA7: Q1 | AB7: =+AA7 -> Q1 | AC7: =+AB7 -> Q1 | AD7: Q2 | AE7: =+AD7 -> Q2 | AF7: =+AE7 -> Q2 | AG7: Q3 | AH7: =+AG7 -> Q3 | AI7: =+AH7 -> Q3 | AJ7: Q4 | AK7: =+AJ7 -> Q4 | AL7: =+AK7 -> Q4 | AM7: Q1 | AN7: =+AM7 -> Q1 | AO7: =+AN7 -> Q1 | AP7: Q2 | AQ7: =+AP7 -> Q2 | AR7: =+AQ7 -> Q2 | AS7: Q3 | AT7: =+AS7 -> Q3 | AU7: =+AT7 -> Q3 | AV7: Q4 | AW7: =+AV7 -> Q4 | AX7: =+AW7 -> Q4
O8: =+Timeline!J5 -> 44957 | P8: =+Timeline!K5 -> 44985 | Q8: =+Timeline!L5 -> 45016 | R8: =+Timeline!M5 -> 45046 | S8: =+Timeline!N5 -> 45077 | T8: =+Timeline!O5 -> 45107 | U8: =+Timeline!P5 -> 45138 | V8: =+Timeline!Q5 -> 45169 | ... AX8: =+Timeline!AS5 -> 46022
N9: TOLWEB SaaS | O9: =+Timeline!J679 -> 79567.891 | P9: =+Timeline!K679 -> 51331.919 | Q9: =+Timeline!L679 -> 36426.997 | R9: =+Timeline!M679 -> 27254.28 | S9: =+Timeline!N679 -> 23703.692 | T9: =+Timeline!O679 -> 23153.128 | U9: =+Timeline!P679 -> 32954.004 | V9: =+Timeline!Q679 -> 21090.83 | ... AX9: =+Timeline!AS679 -> 133220.38
M10: FALSE | N10: Andesmar - TOLWEB | O10: =+Timeline!J680 -> 18377.078 | P10: =+Timeline!K680 -> 11855.67 | Q10: =+Timeline!L680 -> 8413.2146 | R10: =+Timeline!M680 -> 6294.6749 | S10: =+Timeline!N680 -> 5474.6279 | T10: =+Timeline!O680 -> 5347.4689 | U10: =+Timeline!P680 -> 7611.0888 | V10: =+Timeline!Q680 -> 4871.1587 | ... AX10: =+Timeline!AS680 -> 0
N11: Total TOLWEB | O11: =+O9-(O10*(1-$M$10)) -> 61190.814 | P11: =+P9-(P10*(1-$M$10)) -> 39476.249 | Q11: =+Q9-(Q10*(1-$M$10)) -> 28013.782 | R11: =+R9-(R10*(1-$M$10)) -> 20959.605 | S11: =+S9-(S10*(1-$M$10)) -> 18229.065 | T11: =+T9-(T10*(1-$M$10)) -> 17805.659 | U11: =+U9-(U10*(1-$M$10)) -> 25342.915 | V11: =+V9-(V10*(1-$M$10)) -> 16219.672 | ... AX11: =+AX9-(AX10*(1-$M$10)) -> 133220.38
N13: TOLPOS SaaS | O13: =+Timeline!J684 -> 9156.6837 | P13: =+Timeline!K684 -> 5907.2842 | Q13: =+Timeline!L684 -> 4192.0237 | R13: =+Timeline!M684 -> 3136.4262 | S13: =+Timeline!N684 -> 2727.8241 | T13: =+Timeline!O684 -> 2664.4651 | U13: =+Timeline!P684 -> 3792.3512 | V13: =+Timeline!Q684 -> 2427.1356 | ... AX13: =+Timeline!AS684 -> 0
M14: =+M10 -> FALSE | N14: Andesmar - TOLPOS | O14: =+Timeline!J685 -> 9156.6837 | P14: =+Timeline!K685 -> 5907.2842 | Q14: =+Timeline!L685 -> 4192.0237 | R14: =+Timeline!M685 -> 3136.4262 | S14: =+Timeline!N685 -> 2727.8241 | T14: =+Timeline!O685 -> 2664.4651 | U14: =+Timeline!P685 -> 3792.3512 | V14: =+Timeline!Q685 -> 2427.1356 | ... AX14: =+Timeline!AS685 -> 0
N15: Total TOLPOS | O15: =+O13-(O14*(1-$M$14)) -> 0 | P15: =+P13-(P14*(1-$M$14)) -> 0 | Q15: =+Q13-(Q14*(1-$M$14)) -> 0 | R15: =+R13-(R14*(1-$M$14)) -> 0 | S15: =+S13-(S14*(1-$M$14)) -> 0 | T15: =+T13-(T14*(1-$M$14)) -> 0 | U15: =+U13-(U14*(1-$M$14)) -> 0 | V15: =+V13-(V14*(1-$M$14)) -> 0 | ... AX15: =+AX13-(AX14*(1-$M$14)) -> 0
N17: Plataforma UNIBUS | O17: =+Timeline!J689 -> 54103.138 | P17: =+Timeline!K689 -> 34903.751 | Q17: =+Timeline!L689 -> 24768.971 | R17: =+Timeline!M689 -> 18531.873 | S17: =+Timeline!N689 -> 16117.609 | T17: =+Timeline!O689 -> 15743.246 | U17: =+Timeline!P689 -> 22407.468 | V17: =+Timeline!Q689 -> 14340.962 | ... AX17: =+Timeline!AS689 -> 37388.527
M18: TRUE | N18: Andesmar - UNIBUS | O18: =+Timeline!J690 -> 4652.6705 | P18: =+Timeline!K690 -> 3001.594 | Q18: =+Timeline!L690 -> 2130.0403 | R18: =+Timeline!M690 -> 1593.6728 | S18: =+Timeline!N690 -> 1386.055 | T18: =+Timeline!O690 -> 1353.8611 | U18: =+Timeline!P690 -> 1926.9597 | V18: =+Timeline!Q690 -> 1233.2699 | ... AX18: =+Timeline!AS690 -> 8961.187
N19: Total UNIBUS | O19: =+O17-(O18*(1-$M$18)) -> 54103.138 | P19: =+P17-(P18*(1-$M$18)) -> 34903.751 | Q19: =+Q17-(Q18*(1-$M$18)) -> 24768.971 | R19: =+R17-(R18*(1-$M$18)) -> 18531.873 | S19: =+S17-(S18*(1-$M$18)) -> 16117.609 | T19: =+T17-(T18*(1-$M$18)) -> 15743.246 | U19: =+U17-(U18*(1-$M$18)) -> 22407.468 | V19: =+V17-(V18*(1-$M$18)) -> 14340.962 | ... AX19: =+AX17-(AX18*(1-$M$18)) -> 37388.527
N21: Ventas Totales | O21: =+O19+O15+O11 -> 115293.95 | P21: =+P19+P15+P11 -> 74380 | Q21: =+Q19+Q15+Q11 -> 52782.753 | R21: =+R19+R15+R11 -> 39491.477 | S21: =+S19+S15+S11 -> 34346.673 | T21: =+T19+T15+T11 -> 33548.904 | U21: =+U19+U15+U11 -> 47750.383 | V21: =+V19+V15+V11 -> 30560.633 | ... AX21: =+AX19+AX15+AX11 -> 170608.91
N31: VENTAS HISTORICAS | O31: =+Timeline!J667 -> 142827.71
O32: =+O8 -> 44957 | P32: =+P8 -> 44985 | Q32: =+Q8 -> 45016 | R32: =+R8 -> 45046 | S32: =+S8 -> 45077 | T32: =+T8 -> 45107 | U32: =+U8 -> 45138 | V32: =+V8 -> 45169 | ... AX32: =+AX8 -> 46022
N33: Ventas totales | O33: =+O21 -> 115293.95 | P33: =+P21 -> 74380 | Q33: =+Q21 -> 52782.753 | R33: =+R21 -> 39491.477 | S33: =+S21 -> 34346.673 | T33: =+T21 -> 33548.904 | U33: =+U21 -> 47750.383 | V33: =+V21 -> 30560.633 | ... AX33: =+AX21 -> 170608.91
N34: Ventas SIN Andesmar | O34: =+Timeline!J671 -> 110641.28 | P34: =+Timeline!K671 -> 71378.406 | Q34: =+Timeline!L671 -> 50652.713 | R34: =+Timeline!M671 -> 37897.805 | S34: =+Timeline!N671 -> 32960.618 | T34: =+Timeline!O671 -> 32195.043 | U34: =+Timeline!P671 -> 45823.423 | V34: =+Timeline!Q671 -> 29327.363 | ... AX34: =+Timeline!AS671 -> 161647.72
N51: VENTAS HISTORICAS | O51: =+O33 -> 115293.95 | P51: =+P33 -> 74380 | Q51: =+Q33 -> 52782.753 | R51: =+R33 -> 39491.477 | S51: =+S33 -> 34346.673 | T51: =+T33 -> 33548.904 | U51: =+U33 -> 47750.383 | V51: =+V33 -> 30560.633 | ... AX51: =+AX33 -> 170608.91
N53: CORRELACION COSTOS SOBRE VENTAS TOTALES
O55: =+O32 -> 44957 | P55: =+P32 -> 44985 | Q55: =+Q32 -> 45016 | R55: =+R32 -> 45046 | S55: =+S32 -> 45077 | T55: =+T32 -> 45107 | U55: =+U32 -> 45138 | V55: =+V32 -> 45169 | ... AX55: =+AX32 -> 46022
N56: =+Timeline!C735 -> OPERACIONES | O56: =+Timeline!J739 -> 0.075101017 | P56: =+Timeline!K739 -> 0.11717327 | Q56: =+Timeline!L739 -> 0.11446752 | R56: =+Timeline!M739 -> 0.083133023 | S56: =+Timeline!N739 -> 0.10071376 | T56: =+Timeline!O739 -> 0.10172088 | U56: =+Timeline!P739 -> 0.12609303 | V56: =+Timeline!Q739 -> 0.10068697 | ... AO56: =+Timeline!AJ739 -> 0.21183623 | AP56: =+CHOOSE($AO$61,AP63,AP68,AP73) -> 0.14 | AQ56: =+CHOOSE($AO$61,AQ63,AQ68,AQ73) -> 0.14 | AR56: =+CHOOSE($AO$61,AR63,AR68,AR73) -> 0.09 | AS56: =+CHOOSE($AO$61,AS63,AS68,AS73) -> 0.09 | AT56: =+CHOOSE($AO$61,AT63,AT68,AT73) -> 0.09 | AU56: =+CHOOSE($AO$61,AU63,AU68,AU73) -> 0.08 | AV56: =+CHOOSE($AO$61,AV63,AV68,AV73) -> 0.08 | AW56: =+CHOOSE($AO$61,AW63,AW68,AW73) -> 0.08 | AX56: =+CHOOSE($AO$61,AX63,AX68,AX73) -> 0.1
N57: =+Timeline!C741 -> INFRAESTRUCTURA | O57: =+Timeline!J745 -> 0.058523589 | P57: =+Timeline!K745 -> 0.13161717 | Q57: =+Timeline!L745 -> 0.18330572 | R57: =+Timeline!M745 -> 0.18379562 | S57: =+Timeline!N745 -> 0.22849083 | T57: =+Timeline!O745 -> 0.25064117 | U57: =+Timeline!P745 -> 0.19507916 | V57: =+Timeline!Q745 -> 0.23457804 | ... AO57: =+Timeline!AJ745 -> 0.19733822 | AP57: =+CHOOSE($AO$61,AP64,AP69,AP74) -> 0.28 | AQ57: =+CHOOSE($AO$61,AQ64,AQ69,AQ74) -> 0.28 | AR57: =+CHOOSE($AO$61,AR64,AR69,AR74) -> 0.18 | AS57: =+CHOOSE($AO$61,AS64,AS69,AS74) -> 0.18 | AT57: =+CHOOSE($AO$61,AT64,AT69,AT74) -> 0.18 | AU57: =+CHOOSE($AO$61,AU64,AU69,AU74) -> 0.2 | AV57: =+CHOOSE($AO$61,AV64,AV69,AV74) -> 0.2 | AW57: =+CHOOSE($AO$61,AW64,AW69,AW74) -> 0.2 | AX57: =+CHOOSE($AO$61,AX64,AX69,AX74) -> 0.22
N58: =+Timeline!C747 -> PERSONAL | O58: =+Timeline!J751 -> 0.14712334 | P58: =+Timeline!K751 -> 0.2233149 | Q58: =+Timeline!L751 -> 0.35124486 | R58: =+Timeline!M751 -> 0.42719317 | S58: =+Timeline!N751 -> 0.52080671 | T58: =+Timeline!O751 -> 0.77602276 | U58: =+Timeline!P751 -> 0.36093712 | V58: =+Timeline!Q751 -> 0.46792428 | ... AO58: =+Timeline!AJ751 -> 0.37090348 | AP58: =+CHOOSE($AO$61,AP65,AP70,AP75) -> 0.52 | AQ58: =+CHOOSE($AO$61,AQ65,AQ70,AQ75) -> 0.52 | AR58: =+CHOOSE($AO$61,AR65,AR70,AR75) -> 0.41 | AS58: =+CHOOSE($AO$61,AS65,AS70,AS75) -> 0.41 | AT58: =+CHOOSE($AO$61,AT65,AT70,AT75) -> 0.41 | AU58: =+CHOOSE($AO$61,AU65,AU70,AU75) -> 0.5 | AV58: =+CHOOSE($AO$61,AV65,AV70,AV75) -> 0.5 | AW58: =+CHOOSE($AO$61,AW65,AW70,AW75) -> 0.5 | AX58: =+CHOOSE($AO$61,AX65,AX70,AX75) -> 0.45
N59: =+Timeline!C753 -> TOTAL | O59: =+Timeline!J757 -> 0.28074795 | P59: =+Timeline!K757 -> 0.47210533 | Q59: =+Timeline!L757 -> 0.6490181 | R59: =+Timeline!M757 -> 0.69412181 | S59: =+Timeline!N757 -> 0.8500113 | T59: =+Timeline!O757 -> 1.1283848 | U59: =+Timeline!P757 -> 0.6821093 | V59: =+Timeline!Q757 -> 0.80318929 | ... AO59: =+Timeline!AJ757 -> 0.78007793 | AP59: =+CHOOSE($AO$61,AP66,AP71,AP76) -> 0.94 | AQ59: =+CHOOSE($AO$61,AQ66,AQ71,AQ76) -> 0.94 | AR59: =+CHOOSE($AO$61,AR66,AR71,AR76) -> 0.68 | AS59: =+CHOOSE($AO$61,AS66,AS71,AS76) -> 0.68 | AT59: =+CHOOSE($AO$61,AT66,AT71,AT76) -> 0.68 | AU59: =+CHOOSE($AO$61,AU66,AU71,AU76) -> 0.78 | AV59: =+CHOOSE($AO$61,AV66,AV71,AV76) -> 0.78 | AW59: =+CHOOSE($AO$61,AW66,AW71,AW76) -> 0.78 | AX59: =+CHOOSE($AO$61,AX66,AX71,AX76) -> 0.77
AO61: 1
AO63: IA | AP63: 0.14 | AQ63: 0.14 | AR63: 0.09 | AS63: 0.09 | AT63: 0.09 | AU63: 0.08 | AV63: 0.08 | AW63: 0.08 | AX63: 0.1
AP64: 0.28 | AQ64: 0.28 | AR64: 0.18 | AS64: 0.18 | AT64: 0.18 | AU64: 0.2 | AV64: 0.2 | AW64: 0.2 | AX64: 0.22
AP65: 0.52 | AQ65: 0.52 | AR65: 0.41 | AS65: 0.41 | AT65: 0.41 | AU65: 0.5 | AV65: 0.5 | AW65: 0.5 | AX65: 0.45
AP66: 0.94 | AQ66: 0.94 | AR66: 0.68 | AS66: 0.68 | AT66: 0.68 | AU66: 0.78 | AV66: 0.78 | AW66: 0.78 | AX66: 0.77
AO68: 2024 | AP68: =+AD56 -> 0.13229954 | AQ68: =+AE56 -> 0.11906064 | AR68: =+AF56 -> 0.080045379 | AS68: =+AG56 -> 0.10985019 | AT68: =+AH56 -> 0.10543363 | AU68: =+AI56 -> 0.095015276 | AV68: =+AJ56 -> 0.1052246 | AW68: =+AK56 -> 0.089020995 | AX68: =+AL56 -> 0.081760828
AP69: =+AD57 -> 0.31557251 | AQ69: =+AE57 -> 0.24849657 | AR69: =+AF57 -> 0.22506221 | AS69: =+AG57 -> 0.24224858 | AT69: =+AH57 -> 0.35466665 | AU69: =+AI57 -> 0.2050577 | AV69: =+AJ57 -> 0.17729756 | AW69: =+AK57 -> 0.14431648 | AX69: =+AL57 -> 0.094368514
AP70: =+AD58 -> 0.54945953 | AQ70: =+AE58 -> 0.5587482 | AR70: =+AF58 -> 0.66037274 | AS70: =+AG58 -> 0.40150863 | AT70: =+AH58 -> 0.50155842 | AU70: =+AI58 -> 0.38915707 | AV70: =+AJ58 -> 0.34029349 | AW70: =+AK58 -> 0.27759434 | AX70: =+AL58 -> 0.28461054
AP71: =+AD59 -> 0.99733158 | AQ71: =+AE59 -> 0.92630541 | AR71: =+AF59 -> 0.96548033 | AS71: =+AG59 -> 0.75360741 | AT71: =+AH59 -> 0.9616587 | AU71: =+AI59 -> 0.68923004 | AV71: =+AJ59 -> 0.62281565 | AW71: =+AK59 -> 0.51093182 | AX71: =+AL59 -> 0.46073989
AO73: Avg 2023/24 | AP73: =+AVERAGE(R56,AD56) -> 0.10771628 | AQ73: =+AVERAGE(S56,AE56) -> 0.1098872 | AR73: =+AVERAGE(T56,AF56) -> 0.09088313 | AS73: =+AVERAGE(U56,AG56) -> 0.11797161 | AT73: =+AVERAGE(V56,AH56) -> 0.1030603 | AU73: =+AVERAGE(W56,AI56) -> 0.082272095 | AV73: =+AVERAGE(X56,AJ56) -> 0.089882211 | AW73: =+AVERAGE(Y56,AK56) -> 0.078597888 | AX73: =+AVERAGE(Z56,AL56) -> 0.07497657
AP74: =+AVERAGE(R57,AD57) -> 0.24968406 | AQ74: =+AVERAGE(S57,AE57) -> 0.2384937 | AR74: =+AVERAGE(T57,AF57) -> 0.23785169 | AS74: =+AVERAGE(U57,AG57) -> 0.21866387 | AT74: =+AVERAGE(V57,AH57) -> 0.29462234 | AU74: =+AVERAGE(W57,AI57) -> 0.19914943 | AV74: =+AVERAGE(X57,AJ57) -> 0.16354791 | AW74: =+AVERAGE(Y57,AK57) -> 0.13330822 | AX74: =+AVERAGE(Z57,AL57) -> 0.092176881
AP75: =+AVERAGE(R58,AD58) -> 0.48832635 | AQ75: =+AVERAGE(S58,AE58) -> 0.53977745 | AR75: =+AVERAGE(T58,AF58) -> 0.71819775 | AS75: =+AVERAGE(U58,AG58) -> 0.38122288 | AT75: =+AVERAGE(V58,AH58) -> 0.48474135 | AU75: =+AVERAGE(W58,AI58) -> 0.37924812 | AV75: =+AVERAGE(X58,AJ58) -> 0.34786755 | AW75: =+AVERAGE(Y58,AK58) -> 0.28392576 | AX75: =+AVERAGE(Z58,AL58) -> 0.26838338
AP76: =+AVERAGE(R59,AD59) -> 0.84572669 | AQ76: =+AVERAGE(S59,AE59) -> 0.88815835 | AR76: =+AVERAGE(T59,AF59) -> 1.0469326 | AS76: =+AVERAGE(U59,AG59) -> 0.71785835 | AT76: =+AVERAGE(V59,AH59) -> 0.882424 | AU76: =+AVERAGE(W59,AI59) -> 0.66066964 | AV76: =+AVERAGE(X59,AJ59) -> 0.60129767 | AW76: =+AVERAGE(Y59,AK59) -> 0.49583186 | AX76: =+AVERAGE(Z59,AL59) -> 0.43553683
N79: COSTOS
O81: =+O55 -> 44957 | P81: =+P55 -> 44985 | Q81: =+Q55 -> 45016 | R81: =+R55 -> 45046 | S81: =+S55 -> 45077 | T81: =+T55 -> 45107 | U81: =+U55 -> 45138 | V81: =+V55 -> 45169 | ... AX81: =+AX55 -> 46022
N82: =+N56 -> OPERACIONES | O82: =+Timeline!J728 -> 10726.506 | P82: =+Timeline!K728 -> 10796.691 | Q82: =+Timeline!L728 -> 7484.8013 | R82: =+Timeline!M728 -> 4067.0818 | S82: =+Timeline!N728 -> 4285.2824 | T82: =+Timeline!O728 -> 4227.605 | U82: =+Timeline!P728 -> 7458.8846 | V82: =+Timeline!Q728 -> 3811.9008 | ... AO82: =+Timeline!AJ728 -> 26195.818 | AP82: =+AP$51*AP56 -> 12779.63 | AQ82: =+AQ$51*AQ56 -> 10386.257 | AR82: =+AR$51*AR56 -> 6842.6381 | AS82: =+AS$51*AS56 -> 7836.718 | AT82: =+AT$51*AT56 -> 6855.9421 | AU82: =+AU$51*AU56 -> 5930.8653 | AV82: =+AV$51*AV56 -> 7969.1297 | AW82: =+AW$51*AW56 -> 10375.365 | AX82: =+AX$51*AX56 -> 17060.891
N83: =+N57 -> INFRAESTRUCTURA | O83: =+Timeline!J729 -> 8358.7904 | P83: =+Timeline!K729 -> 12127.595 | Q83: =+Timeline!L729 -> 11985.993 | R83: =+Timeline!M729 -> 8991.7555 | S83: =+Timeline!N729 -> 9722.0848 | T83: =+Timeline!O729 -> 10416.857 | U83: =+Timeline!P729 -> 11539.678 | V83: =+Timeline!Q729 -> 8880.8728 | ... AO83: =+Timeline!AJ729 -> 24402.985 | AP83: =+AP$51*AP57 -> 25559.261 | AQ83: =+AQ$51*AQ57 -> 20772.514 | AR83: =+AR$51*AR57 -> 13685.276 | AS83: =+AS$51*AS57 -> 15673.436 | AT83: =+AT$51*AT57 -> 13711.884 | AU83: =+AU$51*AU57 -> 14827.163 | AV83: =+AV$51*AV57 -> 19922.824 | AW83: =+AW$51*AW57 -> 25938.413 | AX83: =+AX$51*AX57 -> 37533.959
N84: =+N58 -> PERSONAL | O84: =+Timeline!J730 -> 21013.29 | P84: =+Timeline!K730 -> 20576.895 | Q84: =+Timeline!L730 -> 22967.196 | R84: =+Timeline!M730 -> 20899.391 | S84: =+Timeline!N730 -> 22159.87 | T84: =+Timeline!O730 -> 32252.157 | U84: =+Timeline!P730 -> 21350.81 | V84: =+Timeline!Q730 -> 17715.112 | ... AO84: =+Timeline!AJ730 -> 45866.189 | AP84: =+AP$51*AP58 -> 47467.199 | AQ84: =+AQ$51*AQ58 -> 38577.525 | AR84: =+AR$51*AR58 -> 31172.018 | AS84: =+AS$51*AS58 -> 35700.604 | AT84: =+AT$51*AT58 -> 31232.625 | AU84: =+AU$51*AU58 -> 37067.908 | AV84: =+AV$51*AV58 -> 49807.06 | AW84: =+AW$51*AW58 -> 64846.032 | AX84: =+AX$51*AX58 -> 76774.008
N85: =+N59 -> TOTAL | O85: =+Timeline!J731 -> 40098.587 | P85: =+Timeline!K731 -> 43501.18 | Q85: =+Timeline!L731 -> 42437.99 | R85: =+Timeline!M731 -> 33958.229 | S85: =+Timeline!N731 -> 36167.237 | T85: =+Timeline!O731 -> 46896.619 | U85: =+Timeline!P731 -> 40349.373 | V85: =+Timeline!Q731 -> 30407.885 | ... AO85: =+Timeline!AJ731 -> 96464.992 | AP85: =+AP$51*AP59 -> 85806.09 | AQ85: =+AQ$51*AQ59 -> 69736.296 | AR85: =+AR$51*AR59 -> 51699.933 | AS85: =+AS$51*AS59 -> 59210.758 | AT85: =+AT$51*AT59 -> 51800.451 | AU85: =+AU$51*AU59 -> 57825.937 | AV85: =+AV$51*AV59 -> 77699.014 | AW85: =+AW$51*AW59 -> 101159.81 | AX85: =+AX$51*AX59 -> 131368.86
N100: EBITDA Historico
O101: =+O81 -> 44957 | P101: =+P81 -> 44985 | Q101: =+Q81 -> 45016 | R101: =+R81 -> 45046 | S101: =+S81 -> 45077 | T101: =+T81 -> 45107 | U101: =+U81 -> 45138 | V101: =+V81 -> 45169 | ... AX101: =+AX81 -> 46022
N102: =+N51 -> VENTAS HISTORICAS | O102: =+O51 -> 115293.95 | P102: =+P51 -> 74380 | Q102: =+Q51 -> 52782.753 | R102: =+R51 -> 39491.477 | S102: =+S51 -> 34346.673 | T102: =+T51 -> 33548.904 | U102: =+U51 -> 47750.383 | ... AX102: =+AX51 -> 170608.91
N103: COSTOS TOTALES | O103: =+O85 -> 40098.587 | P103: =+P85 -> 43501.18 | Q103: =+Q85 -> 42437.99 | R103: =+R85 -> 33958.229 | S103: =+S85 -> 36167.237 | T103: =+T85 -> 46896.619 | U103: =+U85 -> 40349.373 | V103: =+V85 -> 30407.885 | ... AX103: =+AX85 -> 131368.86
N104: EBITDA | O104: =+O102-O103 -> 75195.364 | P104: =+P102-P103 -> 30878.82 | Q104: =+Q102-Q103 -> 10344.763 | R104: =+R102-R103 -> 5533.2488 | S104: =+S102-S103 -> -1820.564 | T104: =+T102-T103 -> -13347.715 | U104: =+U102-U103 -> 7401.0103 | V104: =+V102-V103 -> 152.74805 | ... AX104: =+AX102-AX103 -> 39240.048
N121: QUARTERLY ANALYSIS | O121: 2023 | P121: =+O121 -> 2023 | Q121: =+P121 -> 2023 | R121: =+Q121 -> 2023 | S121: =+R121+1 -> 2024 | T121: =+S121 -> 2024 | U121: =+T121 -> 2024 | V121: =+U121 -> 2024 | W121: =+V121+1 -> 2025 | X121: =+W121 -> 2025 | Y121: =+X121 -> 2025 | Z121: =+Y121 -> 2025 | AA121: =+Z121+1 -> 2026 | AB121: =+AA121 -> 2026 | AC121: =+AB121 -> 2026 | AD121: =+AC121 -> 2026 | AE121: =+AD121+1 -> 2027 | AF121: =+AE121 -> 2027 | AG121: =+AF121 -> 2027 | AH121: =+AG121 -> 2027 | AI121: =+AH121+1 -> 2028 | AJ121: =+AI121 -> 2028 | AK121: =+AJ121 -> 2028 | AL121: =+AK121 -> 2028 | AM121: =+AL121+1 -> 2029 | AN121: =+AM121 -> 2029 | AO121: =+AN121 -> 2029 | AP121: =+AO121 -> 2029 | AQ121: =+AP121+1 -> 2030 | AR121: =+AQ121 -> 2030 | AS121: =+AR121 -> 2030 | AT121: =+AS121 -> 2030
O122: Q1 | P122: Q2 | Q122: Q3 | R122: Q4 | S122: Q1 | T122: Q2 | U122: Q3 | V122: Q4 | W122: Q1 | X122: Q2 | Y122: Q3 | Z122: Q4 | AA122: Q1 | AB122: Q2 | AC122: Q3 | AD122: Q4 | AE122: Q1 | AF122: Q2 | AG122: Q3 | AH122: Q4 | AI122: Q1 | AJ122: Q2 | AK122: Q3 | AL122: Q4 | AM122: Q1 | AN122: Q2 | AO122: Q3 | AP122: Q4 | AQ122: Q1 | AR122: Q2 | AS122: Q3 | AT122: Q4
O123: =+CONCATENATE(O121,"-",O122) -> 2023-Q1 | P123: =+CONCATENATE(P121,"-",P122) -> 2023-Q2 | Q123: =+CONCATENATE(Q121,"-",Q122) -> 2023-Q3 | R123: =+CONCATENATE(R121,"-",R122) -> 2023-Q4 | S123: =+CONCATENATE(S121,"-",S122) -> 2024-Q1 | T123: =+CONCATENATE(T121,"-",T122) -> 2024-Q2 | U123: =+CONCATENATE(U121,"-",U122) -> 2024-Q3 | V123: =+CONCATENATE(V121,"-",V122) -> 2024-Q4 | ... AT123: =+CONCATENATE(AT121,"-",AT122) -> 2030-Q4
N124: =+N9 -> TOLWEB SaaS | O124: =+SUMIFS($O9:$AX9,$O$6:$AX$6,O$121,$O$7:$AX$7,O$122) -> 167326.81 | P124: =+SUMIFS($O9:$AX9,$O$6:$AX$6,P$121,$O$7:$AX$7,P$122) -> 74111.1 | Q124: =+SUMIFS($O9:$AX9,$O$6:$AX$6,Q$121,$O$7:$AX$7,Q$122) -> 80412.941 | R124: =+SUMIFS($O9:$AX9,$O$6:$AX$6,R$121,$O$7:$AX$7,R$122) -> 138333.41 | S124: =+SUMIFS($O9:$AX9,$O$6:$AX$6,S$121,$O$7:$AX$7,S$122) -> 129567.78 | T124: =+SUMIFS($O9:$AX9,$O$6:$AX$6,T$121,$O$7:$AX$7,T$122) -> 72030.536 | U124: =+SUMIFS($O9:$AX9,$O$6:$AX$6,U$121,$O$7:$AX$7,U$122) -> 107251.92 | V124: =+SUMIFS($O9:$AX9,$O$6:$AX$6,V$121,$O$7:$AX$7,V$122) -> 322946.73 | ... Z124: =+SUMIFS($O9:$AX9,$O$6:$AX$6,Z$121,$O$7:$AX$7,Z$122) -> 294521.17 | AA124: =+W124*(1+AA142) -> 943851.89 | AB124: =+X124*(1+AB142) -> 498190.42 | AC124: =+Y124*(1+AC142) -> 494066.67 | AD124: =+Z124*(1+AD142) -> 478086.49 | AE124: =+AA124*(1+AE142) -> 1643473.5 | AF124: =+AB124*(1+AF142) -> 869644.3 | AG124: =+AC124*(1+AG142) -> 786324.15 | AH124: =+AD124*(1+AH142) -> 676736.83 | ... AT124: =+AP124*(1+AT142) -> 949096.63
N125: =+N10 -> Andesmar - TOLWEB | O125: =+SUMIFS($O10:$AX10,$O$6:$AX$6,O$121,$O$7:$AX$7,O$122) -> 38645.962 | P125: =+SUMIFS($O10:$AX10,$O$6:$AX$6,P$121,$O$7:$AX$7,P$122) -> 17116.772 | Q125: =+SUMIFS($O10:$AX10,$O$6:$AX$6,Q$121,$O$7:$AX$7,Q$122) -> 18572.251 | R125: =+SUMIFS($O10:$AX10,$O$6:$AX$6,R$121,$O$7:$AX$7,R$122) -> 31949.62 | S125: =+SUMIFS($O10:$AX10,$O$6:$AX$6,S$121,$O$7:$AX$7,S$122) -> 29925.099 | T125: =+SUMIFS($O10:$AX10,$O$6:$AX$6,T$121,$O$7:$AX$7,T$122) -> 16636.243 | U125: =+SUMIFS($O10:$AX10,$O$6:$AX$6,U$121,$O$7:$AX$7,U$122) -> 24771.008 | V125: =+SUMIFS($O10:$AX10,$O$6:$AX$6,V$121,$O$7:$AX$7,V$122) -> 74588.091 | ... Z125: =+SUMIFS($O10:$AX10,$O$6:$AX$6,Z$121,$O$7:$AX$7,Z$122) -> 1821.5686 | AA125: =+W125*(1+AA143) -> 290663.68 | AB125: =+X125*(1+AB143) -> 262533.37 | AC125: =+Y125*(1+AC143) -> 298243.07 | AD125: =+Z125*(1+AD143) -> 2148.5174 | AE125: =+AA125*(1+AE143) -> 563078.03 | AF125: =+AB125*(1+AF143) -> 623509.31 | AG125: =+AC125*(1+AG143) -> 658036.4 | AH125: =+AD125*(1+AH143) -> 2405.6054 | ... AT125: =+AP125*(1+AT143) -> 2665.0738
N126: =+N11 -> Total TOLWEB | O126: =+SUMIFS($O11:$AX11,$O$6:$AX$6,O$121,$O$7:$AX$7,O$122) -> 128680.84 | P126: =+SUMIFS($O11:$AX11,$O$6:$AX$6,P$121,$O$7:$AX$7,P$122) -> 56994.328 | Q126: =+SUMIFS($O11:$AX11,$O$6:$AX$6,Q$121,$O$7:$AX$7,Q$122) -> 61840.69 | R126: =+SUMIFS($O11:$AX11,$O$6:$AX$6,R$121,$O$7:$AX$7,R$122) -> 106383.79 | S126: =+SUMIFS($O11:$AX11,$O$6:$AX$6,S$121,$O$7:$AX$7,S$122) -> 99642.676 | T126: =+SUMIFS($O11:$AX11,$O$6:$AX$6,T$121,$O$7:$AX$7,T$122) -> 55394.293 | U126: =+SUMIFS($O11:$AX11,$O$6:$AX$6,U$121,$O$7:$AX$7,U$122) -> 82480.912 | V126: =+SUMIFS($O11:$AX11,$O$6:$AX$6,V$121,$O$7:$AX$7,V$122) -> 248358.64 | ... Z126: =+SUMIFS($O11:$AX11,$O$6:$AX$6,Z$121,$O$7:$AX$7,Z$122) -> 292699.6 | AA126: =+W126*(1+AA144) -> 659913.28 | AB126: =+X126*(1+AB144) -> 274216.01 | AC126: =+Y126*(1+AC144) -> 250617.77 | AD126: =+Z126*(1+AD144) -> 514139.92 | AE126: =+AA126*(1+AE144) -> 1110228.3 | AF126: =+AB126*(1+AF144) -> 426842.61 | AG126: =+AC126*(1+AG144) -> 352589.81 | AH126: =+AD126*(1+AH144) -> 773453.13 | ... AT126: =+AP126*(1+AT144) -> 1159381.9
N128: =+N13 -> TOLPOS SaaS | O128: =+SUMIFS($O13:$AX13,$O$6:$AX$6,O$121,$O$7:$AX$7,O$122) -> 19255.992 | P128: =+SUMIFS($O13:$AX13,$O$6:$AX$6,P$121,$O$7:$AX$7,P$122) -> 8528.7154 | Q128: =+SUMIFS($O13:$AX13,$O$6:$AX$6,Q$121,$O$7:$AX$7,Q$122) -> 9253.9321 | R128: =+SUMIFS($O13:$AX13,$O$6:$AX$6,R$121,$O$7:$AX$7,R$122) -> 15919.428 | S128: =+SUMIFS($O13:$AX13,$O$6:$AX$6,S$121,$O$7:$AX$7,S$122) -> 17525.714 | T128: =+SUMIFS($O13:$AX13,$O$6:$AX$6,T$121,$O$7:$AX$7,T$122) -> 14353.162 | U128: =+SUMIFS($O13:$AX13,$O$6:$AX$6,U$121,$O$7:$AX$7,U$122) -> 16715.734 | V128: =+SUMIFS($O13:$AX13,$O$6:$AX$6,V$121,$O$7:$AX$7,V$122) -> 24132.942 | ... Z128: =+SUMIFS($O13:$AX13,$O$6:$AX$6,Z$121,$O$7:$AX$7,Z$122) -> 0 | AA128: =+W128*(1+AA146) -> 30331.051 | AB128: =+X128*(1+AB146) -> 42630.441 | AC128: =+Y128*(1+AC146) -> 2063.3362 | AD128: =+Z128*(1+AD146) -> 0 | AE128: =+AA128*(1+AE146) -> 34075.734 | AF128: =+AB128*(1+AF146) -> 62807.221 | AG128: =+AC128*(1+AG146) -> 2017.9348 | AH128: =+AD128*(1+AH146) -> 0 | ... AT128: =+AP128*(1+AT146) -> 0
N129: =+N14 -> Andesmar - TOLPOS | O129: =+SUMIFS($O14:$AX14,$O$6:$AX$6,O$121,$O$7:$AX$7,O$122) -> 19255.992 | P129: =+SUMIFS($O14:$AX14,$O$6:$AX$6,P$121,$O$7:$AX$7,P$122) -> 8528.7154 | Q129: =+SUMIFS($O14:$AX14,$O$6:$AX$6,Q$121,$O$7:$AX$7,Q$122) -> 9253.9321 | R129: =+SUMIFS($O14:$AX14,$O$6:$AX$6,R$121,$O$7:$AX$7,R$122) -> 15919.428 | S129: =+SUMIFS($O14:$AX14,$O$6:$AX$6,S$121,$O$7:$AX$7,S$122) -> 17525.714 | T129: =+SUMIFS($O14:$AX14,$O$6:$AX$6,T$121,$O$7:$AX$7,T$122) -> 14353.162 | U129: =+SUMIFS($O14:$AX14,$O$6:$AX$6,U$121,$O$7:$AX$7,U$122) -> 16715.734 | V129: =+SUMIFS($O14:$AX14,$O$6:$AX$6,V$121,$O$7:$AX$7,V$122) -> 24132.942 | ... Z129: =+SUMIFS($O14:$AX14,$O$6:$AX$6,Z$121,$O$7:$AX$7,Z$122) -> 0 | AA129: =+W129*(1+AA147) -> 30331.051 | AB129: =+X129*(1+AB147) -> 42630.441 | AC129: =+Y129*(1+AC147) -> 2063.3362 | AD129: =+Z129*(1+AD147) -> 0 | AE129: =+AA129*(1+AE147) -> 34075.734 | AF129: =+AB129*(1+AF147) -> 62807.221 | AG129: =+AC129*(1+AG147) -> 2017.9348 | AH129: =+AD129*(1+AH147) -> 0 | ... AT129: =+AP129*(1+AT147) -> 0
N130: =+N15 -> Total TOLPOS | O130: =+SUMIFS($O15:$AX15,$O$6:$AX$6,O$121,$O$7:$AX$7,O$122) -> 0 | P130: =+SUMIFS($O15:$AX15,$O$6:$AX$6,P$121,$O$7:$AX$7,P$122) -> 0 | Q130: =+SUMIFS($O15:$AX15,$O$6:$AX$6,Q$121,$O$7:$AX$7,Q$122) -> 0 | R130: =+SUMIFS($O15:$AX15,$O$6:$AX$6,R$121,$O$7:$AX$7,R$122) -> 0 | S130: =+SUMIFS($O15:$AX15,$O$6:$AX$6,S$121,$O$7:$AX$7,S$122) -> 0 | T130: =+SUMIFS($O15:$AX15,$O$6:$AX$6,T$121,$O$7:$AX$7,T$122) -> 0 | U130: =+SUMIFS($O15:$AX15,$O$6:$AX$6,U$121,$O$7:$AX$7,U$122) -> 0 | V130: =+SUMIFS($O15:$AX15,$O$6:$AX$6,V$121,$O$7:$AX$7,V$122) -> 0 | ... Z130: =+SUMIFS($O15:$AX15,$O$6:$AX$6,Z$121,$O$7:$AX$7,Z$122) -> 0 | AA130: =+IFERROR(+W130*(1+AA148),0) -> 0 | AB130: =+IFERROR(+X130*(1+AB148),0) -> 0 | AC130: =+IFERROR(+Y130*(1+AC148),0) -> 0 | AD130: =+IFERROR(+Z130*(1+AD148),0) -> 0 | AE130: =+IFERROR(+AA130*(1+AE148),0) -> 0 | AF130: =+IFERROR(+AB130*(1+AF148),0) -> 0 | AG130: =+IFERROR(+AC130*(1+AG148),0) -> 0 | AH130: =+IFERROR(+AD130*(1+AH148),0) -> 0 | ... AT130: =+IFERROR(+AP130*(1+AT148),0) -> 0
N132: =+N17 -> Plataforma UNIBUS | O132: =+SUMIFS($O17:$AX17,$O$6:$AX$6,O$121,$O$7:$AX$7,O$122) -> 113775.86 | P132: =+SUMIFS($O17:$AX17,$O$6:$AX$6,P$121,$O$7:$AX$7,P$122) -> 50392.727 | Q132: =+SUMIFS($O17:$AX17,$O$6:$AX$6,Q$121,$O$7:$AX$7,Q$122) -> 54677.739 | R132: =+SUMIFS($O17:$AX17,$O$6:$AX$6,R$121,$O$7:$AX$7,R$122) -> 94061.455 | S132: =+SUMIFS($O17:$AX17,$O$6:$AX$6,S$121,$O$7:$AX$7,S$122) -> 145266.79 | T132: =+SUMIFS($O17:$AX17,$O$6:$AX$6,T$121,$O$7:$AX$7,T$122) -> 72582.692 | U132: =+SUMIFS($O17:$AX17,$O$6:$AX$6,U$121,$O$7:$AX$7,U$122) -> 90459.628 | V132: =+SUMIFS($O17:$AX17,$O$6:$AX$6,V$121,$O$7:$AX$7,V$122) -> 125311.51 | ... Z132: =+SUMIFS($O17:$AX17,$O$6:$AX$6,Z$121,$O$7:$AX$7,Z$122) -> 107215.49 | AA132: =+W132*(1+AA150) -> 107845.49 | AB132: =+X132*(1+AB150) -> 124669.67 | AC132: =+Y132*(1+AC150) -> 104573.53 | AD132: =+Z132*(1+AD150) -> 117284.21 | AE132: =+AA132*(1+AE150) -> 108349.18 | AF132: =+AB132*(1+AF150) -> 154117.04 | AG132: =+AC132*(1+AG150) -> 124031.02 | AH132: =+AD132*(1+AH150) -> 124627.05 | ... AT132: =+AP132*(1+AT150) -> 131561.64
N133: =+N18 -> Andesmar - UNIBUS | O133: =+SUMIFS($O18:$AX18,$O$6:$AX$6,O$121,$O$7:$AX$7,O$122) -> 9784.3048 | P133: =+SUMIFS($O18:$AX18,$O$6:$AX$6,P$121,$O$7:$AX$7,P$122) -> 4333.5888 | Q133: =+SUMIFS($O18:$AX18,$O$6:$AX$6,Q$121,$O$7:$AX$7,Q$122) -> 4702.0841 | R133: =+SUMIFS($O18:$AX18,$O$6:$AX$6,R$121,$O$7:$AX$7,R$122) -> 8088.9386 | S133: =+SUMIFS($O18:$AX18,$O$6:$AX$6,S$121,$O$7:$AX$7,S$122) -> 12492.409 | T133: =+SUMIFS($O18:$AX18,$O$6:$AX$6,T$121,$O$7:$AX$7,T$122) -> 6241.8441 | U133: =+SUMIFS($O18:$AX18,$O$6:$AX$6,U$121,$O$7:$AX$7,U$122) -> 7779.1948 | V133: =+SUMIFS($O18:$AX18,$O$6:$AX$6,V$121,$O$7:$AX$7,V$122) -> 10776.329 | ... Z133: =+SUMIFS($O18:$AX18,$O$6:$AX$6,Z$121,$O$7:$AX$7,Z$122) -> 21886.407 | AA133: =+W133*(1+AA151) -> 87149.943 | AB133: =+X133*(1+AB151) -> 43200.509 | AC133: =+Y133*(1+AC151) -> 20358.885 | AD133: =+Z133*(1+AD151) -> 36804.192 | AE133: =+AA133*(1+AE151) -> 157678.94 | AF133: =+AB133*(1+AF151) -> 79341.253 | AG133: =+AC133*(1+AG151) -> 28909.586 | AH133: =+AD133*(1+AH151) -> 53528.028 | ... AT133: =+AP133*(1+AT151) -> 77306.981
N134: =+N19 -> Total UNIBUS | O134: =+SUMIFS($O19:$AX19,$O$6:$AX$6,O$121,$O$7:$AX$7,O$122) -> 113775.86 | P134: =+SUMIFS($O19:$AX19,$O$6:$AX$6,P$121,$O$7:$AX$7,P$122) -> 50392.727 | Q134: =+SUMIFS($O19:$AX19,$O$6:$AX$6,Q$121,$O$7:$AX$7,Q$122) -> 54677.739 | R134: =+SUMIFS($O19:$AX19,$O$6:$AX$6,R$121,$O$7:$AX$7,R$122) -> 94061.455 | S134: =+SUMIFS($O19:$AX19,$O$6:$AX$6,S$121,$O$7:$AX$7,S$122) -> 145266.79 | T134: =+SUMIFS($O19:$AX19,$O$6:$AX$6,T$121,$O$7:$AX$7,T$122) -> 72582.692 | U134: =+SUMIFS($O19:$AX19,$O$6:$AX$6,U$121,$O$7:$AX$7,U$122) -> 90459.628 | V134: =+SUMIFS($O19:$AX19,$O$6:$AX$6,V$121,$O$7:$AX$7,V$122) -> 125311.51 | ... Z134: =+SUMIFS($O19:$AX19,$O$6:$AX$6,Z$121,$O$7:$AX$7,Z$122) -> 107215.49 | AA134: =+W134*(1+AA152) -> 107845.49 | AB134: =+X134*(1+AB152) -> 124669.67 | AC134: =+Y134*(1+AC152) -> 104573.53 | AD134: =+Z134*(1+AD152) -> 117284.21 | AE134: =+AA134*(1+AE152) -> 108349.18 | AF134: =+AB134*(1+AF152) -> 154117.04 | AG134: =+AC134*(1+AG152) -> 124031.02 | AH134: =+AD134*(1+AH152) -> 124627.05 | ... AT134: =+AP134*(1+AT152) -> 131561.64
N136: =+N21 -> Ventas Totales | O136: =+SUMIFS($O21:$AX21,$O$6:$AX$6,O$121,$O$7:$AX$7,O$122) -> 242456.7 | P136: =+SUMIFS($O21:$AX21,$O$6:$AX$6,P$121,$O$7:$AX$7,P$122) -> 107387.05 | Q136: =+SUMIFS($O21:$AX21,$O$6:$AX$6,Q$121,$O$7:$AX$7,Q$122) -> 116518.43 | R136: =+SUMIFS($O21:$AX21,$O$6:$AX$6,R$121,$O$7:$AX$7,R$122) -> 200445.25 | S136: =+SUMIFS($O21:$AX21,$O$6:$AX$6,S$121,$O$7:$AX$7,S$122) -> 244909.47 | T136: =+SUMIFS($O21:$AX21,$O$6:$AX$6,T$121,$O$7:$AX$7,T$122) -> 127976.99 | U136: =+SUMIFS($O21:$AX21,$O$6:$AX$6,U$121,$O$7:$AX$7,U$122) -> 172940.54 | V136: =+SUMIFS($O21:$AX21,$O$6:$AX$6,V$121,$O$7:$AX$7,V$122) -> 373670.15 | ... Z136: =+SUMIFS($O21:$AX21,$O$6:$AX$6,Z$121,$O$7:$AX$7,Z$122) -> 399915.09 | AA136: =+AA134+AA130+AA126 -> 767758.77 | AB136: =+AB134+AB130+AB126 -> 398885.68 | AC136: =+AC134+AC130+AC126 -> 355191.31 | AD136: =+AD134+AD130+AD126 -> 631424.12 | AE136: =+AE134+AE130+AE126 -> 1218577.5 | AF136: =+AF134+AF130+AF126 -> 580959.65 | AG136: =+AG134+AG130+AG126 -> 476620.83 | AH136: =+AH134+AH130+AH126 -> 898080.18 | ... AT136: =+AT134+AT130+AT126 -> 1290943.5
W137: -10950578
N140: CRECIMIENTO TRIMESTRAL (QS) | AA140: =+'Valuation Dashboard'!AY24 -> 1 | AE140: {=+'Valuation Dashboard'!BB24:BC24} -> 1.5 | AF140: 0 | AI140: {=+'Valuation Dashboard'!BE24:BF24} -> 2 | AJ140: 0 | AM140: =+'Valuation Dashboard'!BH24 -> 2 | AQ140: =+'Valuation Dashboard'!BK24 -> 2
N142: =+N124 -> TOLWEB SaaS | O142: 0 | P142: 0 | Q142: 0 | R142: 0 | S142: =+(S124-O124)/O124 -> -0.22566039 | T142: =+(T124-P124)/P124 -> -0.028073581 | U142: =+(U124-Q124)/Q124 -> 0.33376442 | V142: =+(V124-R124)/R124 -> 1.3345533 | W142: =+(W124-S124)/S124 -> 2.4493832 | X142: =+(X124-T124)/T124 -> 2.2648922 | Y142: =+(Y124-U124)/U124 -> 1.4408391 | Z142: =+(Z124-V124)/V124 -> -0.088019356 | AA142: =+AVERAGE(S142,W142)/$AA$140 -> 1.1118614 | AB142: =+AVERAGE(T142,X142)/$AA$140 -> 1.1184093 | AC142: =+AVERAGE(U142,Y142)/$AA$140 -> 0.88730174 | AD142: =+AVERAGE(V142,Z142)/$AA$140 -> 0.62326699 | AE142: =+AA142/$AE$140 -> 0.74124092 | AF142: =+AB142/$AE$140 -> 0.74560622 | AG142: =+AC142/$AE$140 -> 0.59153449 | AH142: =+AD142/$AE$140 -> 0.41551132 | AI142: =+AE142/$AI$140 -> 0.37062046 | AJ142: =+AF142/$AI$140 -> 0.37280311 | AK142: =+AG142/$AI$140 -> 0.29576725 | AL142: =+AH142/$AI$140 -> 0.20775566 | AM142: =+AI142/$AM$140 -> 0.18531023 | AN142: =+AJ142/$AM$140 -> 0.18640155 | AO142: =+AK142/$AM$140 -> 0.14788362 | AP142: =+AL142/$AM$140 -> 0.10387783 | AQ142: =+AM142/$AQ$140 -> 0.092655115 | AR142: =+AN142/$AQ$140 -> 0.093200777 | AS142: =+AO142/$AQ$140 -> 0.073941812 | AT142: =+AP142/$AQ$140 -> 0.051938916
N143: =+N125 -> Andesmar - TOLWEB | O143: 0 | P143: 0 | Q143: 0 | R143: 0 | S143: =+(S125-O125)/O125 -> -0.22566039 | T143: =+(T125-P125)/P125 -> -0.028073581 | U143: =+(U125-Q125)/Q125 -> 0.33376442 | V143: =+(V125-R125)/R125 -> 1.3345533 | W143: =+(W125-S125)/S125 -> 3.0373053 | X143: =+(X125-T125)/T125 -> 4.1529887 | Y143: =+(Y125-U125)/U125 -> 3.2853641 | Z143: =+(Z125-V125)/V125 -> -0.97557829 | AA143: =+AVERAGE(S143,W143)/$AA$140 -> 1.4058224 | AB143: =+AVERAGE(T143,X143)/$AA$140 -> 2.0624575 | AC143: =+AVERAGE(U143,Y143)/$AA$140 -> 1.8095642 | AD143: =+AVERAGE(V143,Z143)/$AA$140 -> 0.17948752 | AE143: =+AA143/$AE$140 -> 0.93721496 | AF143: =+AB143/$AE$140 -> 1.3749717 | AG143: =+AC143/$AE$140 -> 1.2063762 | AH143: =+AD143/$AE$140 -> 0.11965835 | AI143: =+AE143/$AI$140 -> 0.46860748 | AJ143: =+AF143/$AI$140 -> 0.68748584 | AK143: =+AG143/$AI$140 -> 0.60318808 | AL143: =+AH143/$AI$140 -> 0.059829173 | AM143: =+AI143/$AM$140 -> 0.23430374 | AN143: =+AJ143/$AM$140 -> 0.34374292 | AO143: =+AK143/$AM$140 -> 0.30159404 | AP143: =+AL143/$AM$140 -> 0.029914586 | AQ143: =+AM143/$AQ$140 -> 0.11715187 | AR143: =+AN143/$AQ$140 -> 0.17187146 | AS143: =+AO143/$AQ$140 -> 0.15079702 | AT143: =+AP143/$AQ$140 -> 0.014957293
N144: =+N126 -> Total TOLWEB | O144: 0 | P144: 0 | Q144: 0 | R144: 0 | S144: =+(S126-O126)/O126 -> -0.22566039 | T144: =+(T126-P126)/P126 -> -0.028073581 | U144: =+(U126-Q126)/Q126 -> 0.33376442 | V144: =+(V126-R126)/R126 -> 1.3345533 | W144: =+(W126-S126)/S126 -> 2.272816 | X144: =+(X126-T126)/T126 -> 1.6978513 | Y144: =+(Y126-U126)/U126 -> 0.8868837 | Z144: =+(Z126-V126)/V126 -> 0.17853601 | AA144: =+AVERAGE(S144,W144)/$AA$140 -> 1.0235778 | AB144: =+AVERAGE(T144,X144)/$AA$140 -> 0.83488888 | AC144: =+AVERAGE(U144,Y144)/$AA$140 -> 0.61032406 | AD144: =+AVERAGE(V144,Z144)/$AA$140 -> 0.75654467 | AE144: =+AA144/$AE$140 -> 0.68238519 | AF144: =+AB144/$AE$140 -> 0.55659258 | AG144: =+AC144/$AE$140 -> 0.40688271 | AH144: =+AD144/$AE$140 -> 0.50436311 | AI144: =+AE144/$AI$140 -> 0.34119259 | AJ144: =+AF144/$AI$140 -> 0.27829629 | AK144: =+AG144/$AI$140 -> 0.20344135 | AL144: =+AH144/$AI$140 -> 0.25218156 | AM144: =+AI144/$AM$140 -> 0.1705963 | AN144: =+AJ144/$AM$140 -> 0.13914815 | AO144: =+AK144/$AM$140 -> 0.10172068 | AP144: =+AL144/$AM$140 -> 0.12609078 | AQ144: =+AM144/$AQ$140 -> 0.085298149 | AR144: =+AN144/$AQ$140 -> 0.069574073 | AS144: =+AO144/$AQ$140 -> 0.050860338 | AT144: =+AP144/$AQ$140 -> 0.063045389
N146: =+N128 -> TOLPOS SaaS | O146: 0 | P146: 0 | Q146: 0 | R146: 0 | S146: =+(S128-O128)/O128 -> -0.089856583 | T146: =+(T128-P128)/P128 -> 0.68292187 | U146: =+(U128-Q128)/Q128 -> 0.80633849 | V146: =+(V128-R128)/R128 -> 0.5159428 | W146: =+(W128-S128)/S128 -> 0.46023771 | X146: =+(X128-T128)/T128 -> 0.73696351 | Y146: =+(Y128-U128)/U128 -> -0.87235005 | Z146: =+(Z128-V128)/V128 -> -1 | AA146: =+AVERAGE(S146,W146)/$AA$140 -> 0.18519056 | AB146: =+AVERAGE(T146,X146)/$AA$140 -> 0.70994269 | AC146: =+AVERAGE(U146,Y146)/$AA$140 -> -0.033005778 | AD146: =+AVERAGE(V146,Z146)/$AA$140 -> -0.2420286 | AE146: =+AA146/$AE$140 -> 0.12346038 | AF146: =+AB146/$AE$140 -> 0.47329513 | AG146: =+AC146/$AE$140 -> -0.022003852 | AH146: =+AD146/$AE$140 -> -0.1613524 | AI146: =+AE146/$AI$140 -> 0.061730188 | AJ146: =+AF146/$AI$140 -> 0.23664756 | AK146: =+AG146/$AI$140 -> -0.011001926 | AL146: =+AH146/$AI$140 -> -0.080676199 | AM146: =+AI146/$AM$140 -> 0.030865094 | AN146: =+AJ146/$AM$140 -> 0.11832378 | AO146: =+AK146/$AM$140 -> -0.0055009629 | AP146: =+AL146/$AM$140 -> -0.0403381 | AQ146: =+AM146/$AQ$140 -> 0.015432547 | AR146: =+AN146/$AQ$140 -> 0.059161891 | AS146: =+AO146/$AQ$140 -> -0.0027504815 | AT146: =+AP146/$AQ$140 -> -0.02016905
N147: =+N129 -> Andesmar - TOLPOS | O147: 0 | P147: 0 | Q147: 0 | R147: 0 | S147: =+(S129-O129)/O129 -> -0.089856583 | T147: =+(T129-P129)/P129 -> 0.68292187 | U147: =+(U129-Q129)/Q129 -> 0.80633849 | V147: =+(V129-R129)/R129 -> 0.5159428 | W147: =+(W129-S129)/S129 -> 0.46023771 | X147: =+(X129-T129)/T129 -> 0.73696351 | Y147: =+(Y129-U129)/U129 -> -0.87235005 | Z147: =+(Z129-V129)/V129 -> -1 | AA147: =+AVERAGE(S147,W147)/$AA$140 -> 0.18519056 | AB147: =+AVERAGE(T147,X147)/$AA$140 -> 0.70994269 | AC147: =+AVERAGE(U147,Y147)/$AA$140 -> -0.033005778 | AD147: =+AVERAGE(V147,Z147)/$AA$140 -> -0.2420286 | AE147: =+AA147/$AE$140 -> 0.12346038 | AF147: =+AB147/$AE$140 -> 0.47329513 | AG147: =+AC147/$AE$140 -> -0.022003852 | AH147: =+AD147/$AE$140 -> -0.1613524 | AI147: =+AE147/$AI$140 -> 0.061730188 | AJ147: =+AF147/$AI$140 -> 0.23664756 | AK147: =+AG147/$AI$140 -> -0.011001926 | AL147: =+AH147/$AI$140 -> -0.080676199 | AM147: =+AI147/$AM$140 -> 0.030865094 | AN147: =+AJ147/$AM$140 -> 0.11832378 | AO147: =+AK147/$AM$140 -> -0.0055009629 | AP147: =+AL147/$AM$140 -> -0.0403381 | AQ147: =+AM147/$AQ$140 -> 0.015432547 | AR147: =+AN147/$AQ$140 -> 0.059161891 | AS147: =+AO147/$AQ$140 -> -0.0027504815 | AT147: =+AP147/$AQ$140 -> -0.02016905
N148: =+N130 -> Total TOLPOS | O148: 0 | P148: 0 | Q148: 0 | R148: 0 | S148: =+IFERROR(+(S130-O130)/O130,0) -> 0 | T148: =+IFERROR(+(T130-P130)/P130,0) -> 0 | U148: =+IFERROR(+(U130-Q130)/Q130,0) -> 0 | V148: =+IFERROR(+(V130-R130)/R130,0) -> 0 | W148: =+IFERROR(+(W130-S130)/S130,0) -> 0 | X148: =+IFERROR(+(X130-T130)/T130,0) -> 0 | Y148: =+IFERROR(+(Y130-U130)/U130,0) -> 0 | Z148: =+IFERROR(+(Z130-V130)/V130,0) -> 0 | AA148: =+AVERAGE(S148,W148)/$AA$140 -> 0 | AB148: =+AVERAGE(T148,X148)/$AA$140 -> 0 | AC148: =+AVERAGE(U148,Y148)/$AA$140 -> 0 | AD148: =+AVERAGE(V148,Z148)/$AA$140 -> 0 | AE148: =+AA148/$AE$140 -> 0 | AF148: =+AB148/$AE$140 -> 0 | AG148: =+AC148/$AE$140 -> 0 | AH148: =+AD148/$AE$140 -> 0 | AI148: =+AE148/$AI$140 -> 0 | AJ148: =+AF148/$AI$140 -> 0 | AK148: =+AG148/$AI$140 -> 0 | AL148: =+AH148/$AI$140 -> 0 | AM148: =+AI148/$AM$140 -> 0 | AN148: =+AJ148/$AM$140 -> 0 | AO148: =+AK148/$AM$140 -> 0 | AP148: =+AL148/$AM$140 -> 0 | AQ148: =+AM148/$AQ$140 -> 0 | AR148: =+AN148/$AQ$140 -> 0 | AS148: =+AO148/$AQ$140 -> 0 | AT148: =+AP148/$AQ$140 -> 0
N150: =+N132 -> Plataforma UNIBUS | O150: 0 | P150: 0 | Q150: 0 | R150: 0 | S150: =+(S132-O132)/O132 -> 0.27678045 | T150: =+(T132-P132)/P132 -> 0.44034064 | U150: =+(U132-Q132)/Q132 -> 0.65441421 | V150: =+(V132-R132)/R132 -> 0.33223023 | W150: =+(W132-S132)/S132 -> -0.26276888 | X150: =+(X132-T132)/T132 -> 0.26826886 | Y150: =+(Y132-U132)/U132 -> -0.096218859 | Z150: =+(Z132-V132)/V132 -> -0.14440828 | AA150: =+AVERAGE(S150,W150)/$AA$140 -> 0.0070057875 | AB150: =+AVERAGE(T150,X150)/$AA$140 -> 0.35430475 | AC150: =+AVERAGE(U150,Y150)/$AA$140 -> 0.27909767 | AD150: =+AVERAGE(V150,Z150)/$AA$140 -> 0.093910975 | AE150: =+AA150/$AE$140 -> 0.004670525 | AF150: =+AB150/$AE$140 -> 0.23620317 | AG150: =+AC150/$AE$140 -> 0.18606512 | AH150: =+AD150/$AE$140 -> 0.062607317 | AI150: =+AE150/$AI$140 -> 0.0023352625 | AJ150: =+AF150/$AI$140 -> 0.11810158 | AK150: =+AG150/$AI$140 -> 0.093032558 | AL150: =+AH150/$AI$140 -> 0.031303658 | AM150: =+AI150/$AM$140 -> 0.0011676313 | AN150: =+AJ150/$AM$140 -> 0.059050791 | AO150: =+AK150/$AM$140 -> 0.046516279 | AP150: =+AL150/$AM$140 -> 0.015651829 | AQ150: =+AM150/$AQ$140 -> 0.00058381563 | AR150: =+AN150/$AQ$140 -> 0.029525396 | AS150: =+AO150/$AQ$140 -> 0.023258139 | AT150: =+AP150/$AQ$140 -> 0.0078259146
N151: =+N133 -> Andesmar - UNIBUS | O151: 0 | P151: 0 | Q151: 0 | R151: 0 | S151: =+(S133-O133)/O133 -> 0.27678045 | T151: =+(T133-P133)/P133 -> 0.44034064 | U151: =+(U133-Q133)/Q133 -> 0.65441421 | V151: =+(V133-R133)/R133 -> 0.33223023 | W151: =+(W133-S133)/S133 -> 2.1510696 | X151: =+(X133-T133)/T133 -> 2.0694037 | Y151: =+(Y133-U133)/U133 -> 0.60558137 | Z151: =+(Z133-V133)/V133 -> 1.0309707 | AA151: =+AVERAGE(S151,W151)/$AA$140 -> 1.213925 | AB151: =+AVERAGE(T151,X151)/$AA$140 -> 1.2548722 | AC151: =+AVERAGE(U151,Y151)/$AA$140 -> 0.62999779 | AD151: =+AVERAGE(V151,Z151)/$AA$140 -> 0.68160045 | AE151: =+AA151/$AE$140 -> 0.80928336 | AF151: =+AB151/$AE$140 -> 0.83658145 | AG151: =+AC151/$AE$140 -> 0.41999853 | AH151: =+AD151/$AE$140 -> 0.4544003 | AI151: =+AE151/$AI$140 -> 0.40464168 | AJ151: =+AF151/$AI$140 -> 0.41829073 | AK151: =+AG151/$AI$140 -> 0.20999926 | AL151: =+AH151/$AI$140 -> 0.22720015 | AM151: =+AI151/$AM$140 -> 0.20232084 | AN151: =+AJ151/$AM$140 -> 0.20914536 | AO151: =+AK151/$AM$140 -> 0.10499963 | AP151: =+AL151/$AM$140 -> 0.11360007 | AQ151: =+AM151/$AQ$140 -> 0.10116042 | AR151: =+AN151/$AQ$140 -> 0.10457268 | AS151: =+AO151/$AQ$140 -> 0.052499816 | AT151: =+AP151/$AQ$140 -> 0.056800037
N152: =+N134 -> Total UNIBUS | O152: 0 | P152: 0 | Q152: 0 | R152: 0 | S152: =+(S134-O134)/O134 -> 0.27678045 | T152: =+(T134-P134)/P134 -> 0.44034064 | U152: =+(U134-Q134)/Q134 -> 0.65441421 | V152: =+(V134-R134)/R134 -> 0.33223023 | W152: =+(W134-S134)/S134 -> -0.26276888 | X152: =+(X134-T134)/T134 -> 0.26826886 | Y152: =+(Y134-U134)/U134 -> -0.096218859 | Z152: =+(Z134-V134)/V134 -> -0.14440828 | AA152: =+AVERAGE(S152,W152)/$AA$140 -> 0.0070057875 | AB152: =+AVERAGE(T152,X152)/$AA$140 -> 0.35430475 | AC152: =+AVERAGE(U152,Y152)/$AA$140 -> 0.27909767 | AD152: =+AVERAGE(V152,Z152)/$AA$140 -> 0.093910975 | AE152: =+AA152/$AE$140 -> 0.004670525 | AF152: =+AB152/$AE$140 -> 0.23620317 | AG152: =+AC152/$AE$140 -> 0.18606512 | AH152: =+AD152/$AE$140 -> 0.062607317 | AI152: =+AE152/$AI$140 -> 0.0023352625 | AJ152: =+AF152/$AI$140 -> 0.11810158 | AK152: =+AG152/$AI$140 -> 0.093032558 | AL152: =+AH152/$AI$140 -> 0.031303658 | AM152: =+AI152/$AM$140 -> 0.0011676313 | AN152: =+AJ152/$AM$140 -> 0.059050791 | AO152: =+AK152/$AM$140 -> 0.046516279 | AP152: =+AL152/$AM$140 -> 0.015651829 | AQ152: =+AM152/$AQ$140 -> 0.00058381563 | AR152: =+AN152/$AQ$140 -> 0.029525396 | AS152: =+AO152/$AQ$140 -> 0.023258139 | AT152: =+AP152/$AQ$140 -> 0.0078259146
N154: Variacion Trimestral | O154: 0 | P154: =+(P136-O136)/O136 -> -0.55708771 | Q154: =+(Q136-P136)/P136 -> 0.085032355 | R154: =+(R136-Q136)/Q136 -> 0.72028794 | S154: =+(S136-R136)/R136 -> 0.22182726 | T154: =+(T136-S136)/S136 -> -0.47745187 | U154: =+(U136-T136)/T136 -> 0.35134094 | V154: =+(V136-U136)/U136 -> 1.1606857 | W154: =+(W136-V136)/V136 -> 0.15933086 | ... AT154: =+(AT136-AS136)/AS136 -> 1.0283959
N155: Crecimiento Acumulado | O155: =+O154 -> 0 | P155: =+P154+O155 -> -0.55708771 | Q155: =+Q154+P155 -> -0.47205535 | R155: =+R154+Q155 -> 0.24823259 | S155: =+S154+R155 -> 0.47005985 | T155: =+T154+S155 -> -0.0073920169 | U155: =+U154+T155 -> 0.34394893 | V155: =+V154+U155 -> 1.5046346 | W155: =+W154+V155 -> 1.6639655 | ... AT155: =+AT154+AS155 -> 6.7987153
N162: PROYECCION VENTAS ANUALES
O163: 2023 | P163: 2024 | Q163: 2025 | R163: 2026 | S163: 2027 | T163: 2028 | U163: 2029 | V163: 2030
N164: TOLWEB | O164: =+SUMIFS($O$126:$AT$126,$O$121:$AT$121,O163) -> 353899.66 | P164: =+SUMIFS($O$126:$AT$126,$O$121:$AT$121,P163) -> 485876.52 | Q164: =+SUMIFS($O$126:$AT$126,$O$121:$AT$121,Q163) -> 923889.19 | R164: =+SUMIFS($O$126:$AT$126,$O$121:$AT$121,R163) -> 1698887 | S164: =+SUMIFS($O$126:$AT$126,$O$121:$AT$121,S163) -> 2663113.9 | T164: =+SUMIFS($O$126:$AT$126,$O$121:$AT$121,T163) -> 3427486.2 | U164: =+SUMIFS($O$126:$AT$126,$O$121:$AT$121,U163) -> 3922714.4 | V164: =+SUMIFS($O$126:$AT$126,$O$121:$AT$121,V163) -> 4207172.9
N165: TOLPOS | O165: =+SUMIFS($O$130:$AT$130,$O$121:$AT$121,O163) -> 0 | P165: =+SUMIFS($O$130:$AT$130,$O$121:$AT$121,P163) -> 0 | Q165: =+SUMIFS($O$130:$AT$130,$O$121:$AT$121,Q163) -> 0 | R165: =+SUMIFS($O$130:$AT$130,$O$121:$AT$121,R163) -> 0 | S165: =+SUMIFS($O$130:$AT$130,$O$121:$AT$121,S163) -> 0 | T165: =+SUMIFS($O$130:$AT$130,$O$121:$AT$121,T163) -> 0 | U165: =+SUMIFS($O$130:$AT$130,$O$121:$AT$121,U163) -> 0 | V165: =+SUMIFS($O$130:$AT$130,$O$121:$AT$121,V163) -> 0
N166: UNIBUS | O166: =+SUMIFS($O$134:$AT$134,$O$121:$AT$121,O163) -> 312907.78 | P166: =+SUMIFS($O$134:$AT$134,$O$121:$AT$121,P163) -> 433620.63 | Q166: =+SUMIFS($O$134:$AT$134,$O$121:$AT$121,Q163) -> 388120.77 | R166: =+SUMIFS($O$134:$AT$134,$O$121:$AT$121,R163) -> 454372.89 | S166: =+SUMIFS($O$134:$AT$134,$O$121:$AT$121,S163) -> 511124.3 | T166: =+SUMIFS($O$134:$AT$134,$O$121:$AT$121,T163) -> 545018.99 | U166: =+SUMIFS($O$134:$AT$134,$O$121:$AT$121,U163) -> 563639.26 | V166: =+SUMIFS($O$134:$AT$134,$O$121:$AT$121,V163) -> 573412.31
N167: Total | O167: =SUM(O164:O166) -> 666807.44 | P167: =SUM(P164:P166) -> 919497.15 | Q167: =SUM(Q164:Q166) -> 1312010 | R167: =SUM(R164:R166) -> 2153259.9 | S167: =SUM(S164:S166) -> 3174238.2 | T167: =SUM(T164:T166) -> 3972505.2 | U167: =SUM(U164:U166) -> 4486353.7 | V167: =SUM(V164:V166) -> 4780585.2
N169: Actuales TOLWEB | O169: =+O164 -> 353899.66 | P169: =+P164 -> 485876.52 | Q169: =+Q164 -> 923889.19 | R169: 0 | S169: 0 | T169: 0 | U169: 0 | V169: 0
N170: Actuales TOLPOS | O170: =+O165 -> 0 | P170: =+P165 -> 0 | Q170: =+Q165 -> 0 | R170: 0 | S170: 0 | T170: 0 | U170: 0 | V170: 0
N171: Actuales UNIBUS | O171: =+O166 -> 312907.78 | P171: =+P166 -> 433620.63 | Q171: =+Q166 -> 388120.77 | R171: 0 | S171: 0 | T171: 0 | U171: 0 | V171: 0
N172: Proyectadas TOLWEB | O172: 0 | P172: 0 | Q172: 0 | R172: =+R164 -> 1698887 | S172: =+S164 -> 2663113.9 | T172: =+T164 -> 3427486.2 | U172: =+U164 -> 3922714.4 | V172: =+V164 -> 4207172.9
N173: Proyectadas TOLPOS | O173: 0 | P173: 0 | Q173: 0 | R173: =+R165 -> 0 | S173: =+S165 -> 0 | T173: =+T165 -> 0 | U173: =+U165 -> 0 | V173: =+V165 -> 0
N174: Proyectadas UNIBUS | O174: 0 | P174: 0 | Q174: 0 | R174: =+R166 -> 454372.89 | S174: =+S166 -> 511124.3 | T174: =+T166 -> 545018.99 | U174: =+U166 -> 563639.26 | V174: =+V166 -> 573412.31
N175: Total | O175: =SUM(O169:O174) -> 666807.44 | P175: =SUM(P169:P174) -> 919497.15 | Q175: =SUM(Q169:Q174) -> 1312010 | R175: =SUM(R169:R174) -> 2153259.9 | S175: =SUM(S169:S174) -> 3174238.2 | T175: =SUM(T169:T174) -> 3972505.2 | U175: =SUM(U169:U174) -> 4486353.7 | V175: =SUM(V169:V174) -> 4780585.2
P176: =+(P175-O175)/O175 -> 0.37895455 | Q176: =+(Q175-P175)/P175 -> 0.42687769 | R176: =+(R175-Q175)/Q175 -> 0.64119171 | S176: =+(S175-R175)/R175 -> 0.4741547 | T176: =+(T175-S175)/S175 -> 0.25148304 | U176: =+(U175-T175)/T175 -> 0.12935124 | V176: =+(V175-U175)/U175 -> 0.065583657
N178: Curva Crecimiento Annual Acumulada | O178: 0 | P178: =+P176 -> 0.37895455 | Q178: =+Q176+P178 -> 0.80583223 | R178: =+R176+Q178 -> 1.4470239 | S178: =+S176+R178 -> 1.9211786 | T178: =+T176+S178 -> 2.1726617 | U178: =+U176+T178 -> 2.3020129 | V178: =+V176+U178 -> 2.3675966
N179: Saas Tourism LATAM - Projeccion de Ventas Anuales (M USD) | O179: =+'Benchmark Projections'!L66*1000 -> 44574681 | P179: =+'Benchmark Projections'!M66*1000 -> 50176395 | Q179: =+'Benchmark Projections'!N66*1000 -> 56482078 | R179: =+'Benchmark Projections'!O66*1000 -> 63580199 | S179: =+'Benchmark Projections'!P66*1000 -> 71570342 | T179: =+'Benchmark Projections'!Q66*1000 -> 80564609 | U179: =+'Benchmark Projections'!R66*1000 -> 90689188 | V179: =+'Benchmark Projections'!S66*1000 -> 1.0208613e+08
M180: =+'Valuation Dashboard'!$AI$23 -> 0.015
M181: TRUE | N181: =+'Valuation Dashboard'!$AC$23 -> Ajuste Costos Andesmar
M182: =+M10 -> FALSE | N182: =+'Valuation Dashboard'!$W$23 -> ANDESMAR INCL.
N184: COSTOS QUARTERLY | O184: 2023 | P184: =+O184 -> 2023 | Q184: =+P184 -> 2023 | R184: =+Q184 -> 2023 | S184: =+R184+1 -> 2024 | T184: =+S184 -> 2024 | U184: =+T184 -> 2024 | V184: =+U184 -> 2024 | W184: =+V184+1 -> 2025 | X184: =+W184 -> 2025 | Y184: =+X184 -> 2025 | Z184: =+Y184 -> 2025 | AA184: =+Z184+1 -> 2026 | AB184: =+AA184 -> 2026 | AC184: =+AB184 -> 2026 | AD184: =+AC184 -> 2026 | AE184: =+AD184+1 -> 2027 | AF184: =+AE184 -> 2027 | AG184: =+AF184 -> 2027 | AH184: =+AG184 -> 2027 | AI184: =+AH184+1 -> 2028 | AJ184: =+AI184 -> 2028 | AK184: =+AJ184 -> 2028 | AL184: =+AK184 -> 2028 | AM184: =+AL184+1 -> 2029 | AN184: =+AM184 -> 2029 | AO184: =+AN184 -> 2029 | AP184: =+AO184 -> 2029 | AQ184: =+AP184+1 -> 2030 | AR184: =+AQ184 -> 2030 | AS184: =+AR184 -> 2030 | AT184: =+AS184 -> 2030
O185: Q1 | P185: Q2 | Q185: Q3 | R185: Q4 | S185: Q1 | T185: Q2 | U185: Q3 | V185: Q4 | W185: Q1 | X185: Q2 | Y185: Q3 | Z185: Q4 | AA185: Q1 | AB185: Q2 | AC185: Q3 | AD185: Q4 | AE185: Q1 | AF185: Q2 | AG185: Q3 | AH185: Q4 | AI185: Q1 | AJ185: Q2 | AK185: Q3 | AL185: Q4 | AM185: Q1 | AN185: Q2 | AO185: Q3 | AP185: Q4 | AQ185: Q1 | AR185: Q2 | AS185: Q3 | AT185: Q4
O186: =+CONCATENATE(O184,"-",O185) -> 2023-Q1 | P186: =+CONCATENATE(P184,"-",P185) -> 2023-Q2 | Q186: =+CONCATENATE(Q184,"-",Q185) -> 2023-Q3 | R186: =+CONCATENATE(R184,"-",R185) -> 2023-Q4 | S186: =+CONCATENATE(S184,"-",S185) -> 2024-Q1 | T186: =+CONCATENATE(T184,"-",T185) -> 2024-Q2 | U186: =+CONCATENATE(U184,"-",U185) -> 2024-Q3 | V186: =+CONCATENATE(V184,"-",V185) -> 2024-Q4 | ... AT186: =+CONCATENATE(AT184,"-",AT185) -> 2030-Q4
N187: =+N82 -> OPERACIONES | O187: =+SUMIFS($O82:$AX82,$O$7:$AX$7,O185,$O$6:$AX$6,O184) -> 29007.999 | P187: =+SUMIFS($O82:$AX82,$O$7:$AX$7,P185,$O$6:$AX$6,P184) -> 12579.969 | Q187: =+SUMIFS($O82:$AX82,$O$7:$AX$7,Q185,$O$6:$AX$6,Q184) -> 14561.718 | R187: =+SUMIFS($O82:$AX82,$O$7:$AX$7,R185,$O$6:$AX$6,R184) -> 17266.264 | S187: =+SUMIFS($O82:$AX82,$O$7:$AX$7,S185,$O$6:$AX$6,S184) -> 31189.794 | T187: =+SUMIFS($O82:$AX82,$O$7:$AX$7,T185,$O$6:$AX$6,T184) -> 17422.573 | U187: =+SUMIFS($O82:$AX82,$O$7:$AX$7,U185,$O$6:$AX$6,U184) -> 22048.334 | V187: =+SUMIFS($O82:$AX82,$O$7:$AX$7,V185,$O$6:$AX$6,V184) -> 42235.204 | ... Z187: =+SUMIFS($O82:$AX82,$O$7:$AX$7,Z185,$O$6:$AX$6,Z184) -> 35405.385 | AA187: =+AA$136*AA195*AA$192 -> 114186.16 | AB187: =+AB$136*AB195*AB$192 -> 49445.891 | AC187: =+AC$136*AC195*AC$192 -> 39574.379 | AD187: =+AD$136*AD195*AD$192 -> 59645.238 | AE187: =+AE$136*AE195*AE$192 -> 181234.91 | AF187: =+AF$136*AF195*AF$192 -> 72015.79 | AG187: =+AG$136*AG195*AG$192 -> 53103.703 | AH187: =+AH$136*AH195*AH$192 -> 84833.956 | ... AT187: =+AT$136*AT195*AT$192 -> 121944.4
N188: =+N83 -> INFRAESTRUCTURA | O188: =+SUMIFS($O83:$AX83,$O$7:$AX$7,O185,$O$6:$AX$6,O184) -> 32472.378 | P188: =+SUMIFS($O83:$AX83,$O$7:$AX$7,P185,$O$6:$AX$6,P184) -> 29130.698 | Q188: =+SUMIFS($O83:$AX83,$O$7:$AX$7,Q185,$O$6:$AX$6,Q184) -> 29567.014 | R188: =+SUMIFS($O83:$AX83,$O$7:$AX$7,R185,$O$6:$AX$6,R184) -> 28025.506 | S188: =+SUMIFS($O83:$AX83,$O$7:$AX$7,S185,$O$6:$AX$6,S184) -> 39937.125 | T188: =+SUMIFS($O83:$AX83,$O$7:$AX$7,T185,$O$6:$AX$6,T184) -> 41815.281 | U188: =+SUMIFS($O83:$AX83,$O$7:$AX$7,U185,$O$6:$AX$6,U184) -> 55604.816 | V188: =+SUMIFS($O83:$AX83,$O$7:$AX$7,V185,$O$6:$AX$6,V184) -> 61072.964 | ... Z188: =+SUMIFS($O83:$AX83,$O$7:$AX$7,Z185,$O$6:$AX$6,Z184) -> 83395.196 | AA188: =+AA$136*AA196*AA192 -> 129615.52 | AB188: =+AB$136*AB196*AB192 -> 110867.46 | AC188: =+AC$136*AC196*AC192 -> 88809.986 | AD188: =+AD$136*AD196*AD192 -> 106102.94 | AE188: =+AE$136*AE196*AE192 -> 205724.19 | AF188: =+AF$136*AF196*AF192 -> 161473.64 | AG188: =+AG$136*AG196*AG192 -> 119171.52 | AH188: =+AH$136*AH196*AH192 -> 150911.15 | ... AT188: =+AT$136*AT196*AT192 -> 216926.93
...

Sheet WACC
B1: Componente | C1: Valor | D1: Explicación
B2: Rf (Tasa libre de riesgo) | C2: 0.044 | D2: Tasa libre de riesgo, basada en bonos del Tesoro de EE.UU. a 10 años. | E2: NOTA
B3: Riesgo Pais | C3: 0.063 | E3: NOTA
B4: Prima de mercado (Rm - Rf) | C4: 0.042 | D4: Prima que el mercado exige sobre la tasa libre de riesgo, incluye riesgo país.
B5: Beta (β) | C5: 1.1 | D5: Sensibilidad de la empresa respecto al mercado, estimada por comparables del sector. Despegar, Booking.
B6: Prima Tamaño | C6: 0.0245
B7: Ke (Costo del Equity) | C7: =+C2+C5*C4+C3+C6 -> 0.1777 | D7: Costo del equity, calculado con CAPM: Rf + β*(Rm - Rf).
B8: Kd (Costo de la deuda) | C8: 0.07 | D8: Costo nominal estimado de la deuda en USD.
B9: Tasa Impositiva (T) | C9: 0.35 | D9: Tasa de impuesto corporativo aplicada a la deducción de intereses.
B10: E/V (Proporción Equity) | C10: 0.75 | D10: Proporción del capital financiado por equity (patrimonio).
B11: D/V (Proporción Deuda) | C11: 0.76 | D11: Proporción del capital financiado por deuda.
B13: Equity Cost (Ke) | C13: =+C7 -> 0.1777
B14: Debt Cost (Kd) | C14: =+C8*(1-C9) -> 0.0455
B16: E/V (Proporción Equity) | C16: 0.75
B17: D/V (Proporción Deuda) | C17: 0.62
B19: WACC | C19: =+(C16*C13+C17*C14) -> 0.161485

Sheet Benchmark Projections
A1: Quarter | B1: SaaS Tourism (USD B) | C1: AI in Tourism SaaS (USD B) | D1: OTAs (USD B) | F1: Quarter | G1: 2023-Q%q | H1: 2023-Q%q | I1: 2023-Q%q | J1: 2023-Q%q | K1: 2024-Q%q | L1: 2024-Q%q | M1: 2024-Q%q | N1: 2024-Q%q | O1: 2025-Q%q | P1: 2025-Q%q | Q1: 2025-Q%q | R1: 2025-Q%q | S1: 2026-Q%q | T1: 2026-Q%q | U1: 2026-Q%q | V1: 2026-Q%q | W1: 2027-Q%q | X1: 2027-Q%q | Y1: 2027-Q%q | Z1: 2027-Q%q | AA1: 2028-Q%q | AB1: 2028-Q%q | AC1: 2028-Q%q | AD1: 2028-Q%q | AE1: 2029-Q%q | AF1: 2029-Q%q | AG1: 2029-Q%q | AH1: 2029-Q%q | AI1: 2030-Q%q | AJ1: 2030-Q%q | AK1: 2030-Q%q | AL1: 2030-Q%q
A2: 2023-Q%q | B2: 10.65 | C2: 0.69 | D2: 8.43 | F2: SaaS Tourism (USD B) | G2: 10.65 | H2: 10.969966 | I2: 11.299545 | J2: 11.639025 | K2: 11.988705 | L2: 12.348891 | M2: 12.719897 | N2: 13.102051 | O2: 13.495685 | P2: 13.901146 | Q2: 14.318788 | R2: 14.748978 | S2: 15.192093 | T2: 15.64852 | U2: 16.11866 | V2: 16.602925 | W2: 17.101739 | X2: 17.615539 | Y2: 18.144776 | Z2: 18.689913 | AA2: 19.251427 | AB2: 19.829812 | AC2: 20.425574 | AD2: 21.039235 | AE2: 21.671332 | AF2: 22.32242 | AG2: 22.993069 | AH2: 23.683866 | AI2: 24.395418 | AJ2: 25.128348 | AK2: 25.883297 | AL2: 26.660928
A3: 2023-Q%q | B3: 10.969966 | C3: 0.72249399 | D3: 8.6118115 | F3: AI in Tourism SaaS (USD B) | G3: 0.69 | H3: 0.72249399 | I3: 0.75651822 | J3: 0.79214473 | K3: 0.829449 | L3: 0.86851003 | M3: 0.90941055 | N3: 0.95223718 | O3: 0.99708064 | P3: 1.0440359 | Q3: 1.0932024 | R3: 1.1446843 | S3: 1.1985906 | T3: 1.2550356 | U3: 1.3141386 | V3: 1.376025 | W3: 1.4408258 | X3: 1.5086782 | Y3: 1.579726 | Z3: 1.6541197 | AA3: 1.7320167 | AB3: 1.8135821 | AC3: 1.8989887 | AD3: 1.9884173 | AE3: 2.0820573 | AF3: 2.1801071 | AG3: 2.2827743 | AH3: 2.3902764 | AI3: 2.5028411 | AJ3: 2.6207067 | AK3: 2.744123 | AL3: 2.8733512
A4: 2023-Q%q | B4: 11.299545 | C4: 0.75651822 | D4: 8.7975441 | F4: OTAs (USD B) | G4: 8.43 | H4: 8.6118115 | I4: 8.7975441 | J4: 8.9872825 | K4: 9.181113 | L4: 9.3791239 | M4: 9.5814053 | N4: 9.7880494 | O4: 9.9991502 | P4: 10.214804 | Q4: 10.435109 | R4: 10.660165 | S4: 10.890074 | T4: 11.124943 | U4: 11.364877 | V4: 11.609985 | W4: 11.86038 | X4: 12.116175 | Y4: 12.377487 | Z4: 12.644435 | AA4: 12.91714 | AB4: 13.195726 | AC4: 13.480321 | AD4: 13.771054 | AE4: 14.068057 | AF4: 14.371466 | AG4: 14.681418 | AH4: 14.998055 | AI4: 15.321521 | AJ4: 15.651963 | AK4: 15.989532 | AL4: 16.334382
A5: 2023-Q%q | B5: 11.639025 | C5: 0.79214473 | D5: 8.9872825 | G5: 2023 | H5: 2023 | I5: 2023 | J5: 2023 | K5: 2024 | L5: 2024 | M5: 2024 | N5: 2024 | O5: 2025 | P5: 2025 | Q5: 2025 | R5: 2025 | S5: 2026 | T5: 2026 | U5: 2026 | V5: 2026 | W5: 2027 | X5: 2027 | Y5: 2027 | Z5: 2027 | AA5: 2028 | AB5: 2028 | AC5: 2028 | AD5: 2028 | AE5: 2029 | AF5: 2029 | AG5: 2029 | AH5: 2029 | AI5: 2030 | AJ5: 2030 | AK5: 2030 | AL5: 2030
A6: 2024-Q%q | B6: 11.988705 | C6: 0.829449 | D6: 9.181113 | G6: Q1 | H6: Q2 | I6: Q3 | J6: Q4 | K6: Q1 | L6: Q2 | M6: Q3 | N6: Q4 | O6: Q1 | P6: Q2 | Q6: Q3 | R6: Q4 | S6: Q1 | T6: Q2 | U6: Q3 | V6: Q4 | W6: Q1 | X6: Q2 | Y6: Q3 | Z6: Q4 | AA6: Q1 | AB6: Q2 | AC6: Q3 | AD6: Q4 | AE6: Q1 | AF6: Q2 | AG6: Q3 | AH6: Q4 | AI6: Q1 | AJ6: Q2 | AK6: Q3 | AL6: Q4
A7: 2024-Q%q | B7: 12.348891 | C7: 0.86851003 | D7: 9.3791239 | G7: 2023 Q1 | H7: 2023 Q2 | I7: 2023 Q3 | J7: 2023 Q4 | K7: 2024 Q1 | L7: 2024 Q2 | M7: 2024 Q3 | N7: 2024 Q4 | O7: 2025 Q1 | P7: 2025 Q2 | Q7: 2025 Q3 | R7: 2025 Q4 | S7: 2026 Q1 | T7: 2026 Q2 | U7: 2026 Q3 | V7: 2026 Q4 | W7: 2027 Q1 | X7: 2027 Q2 | Y7: 2027 Q3 | Z7: 2027 Q4 | AA7: 2028 Q1 | AB7: 2028 Q2 | AC7: 2028 Q3 | AD7: 2028 Q4 | AE7: 2029 Q1 | AF7: 2029 Q2 | AG7: 2029 Q3 | AH7: 2029 Q4 | AI7: 2030 Q1 | AJ7: 2030 Q2 | AK7: 2030 Q3 | AL7: 2030 Q4
A8: 2024-Q%q | B8: 12.719897 | C8: 0.90941055 | D8: 9.5814053 | F8: SaaS Tourism (USD B) | G8: 10.65 | H8: 21.619966 | I8: 32.91951 | J8: 44.558536 | K8: 56.547241 | L8: 68.896131 | M8: 81.616028 | N8: 94.718079 | O8: 108.21376 | P8: 122.11491 | Q8: 136.4337 | R8: 151.18268 | S8: 166.37477 | T8: 182.02329 | U8: 198.14195 | V8: 214.74488 | W8: 231.84661 | X8: 249.46215 | Y8: 267.60693 | Z8: 286.29684 | AA8: 305.54827 | AB8: 325.37808 | AC8: 345.80366 | AD8: 366.84289 | AE8: 388.51422 | AF8: 410.83664 | AG8: 433.82971 | AH8: 457.51358 | AI8: 481.909 | AJ8: 507.03734 | AK8: 532.92064 | AL8: 559.58157
A9: 2024-Q%q | B9: 13.102051 | C9: 0.95223718 | D9: 9.7880494 | F9: AI in Tourism SaaS (USD B) | G9: 0.69 | H9: 1.412494 | I9: 2.1690122 | J9: 2.9611569 | K9: 3.7906059 | L9: 4.659116 | M9: 5.5685265 | N9: 6.5207637 | O9: 7.5178443 | P9: 8.5618802 | Q9: 9.6550827 | R9: 10.799767 | S9: 11.998358 | T9: 13.253393 | U9: 14.567532 | V9: 15.943557 | W9: 17.384383 | X9: 18.893061 | Y9: 20.472787 | Z9: 22.126907 | AA9: 23.858923 | AB9: 25.672505 | AC9: 27.571494 | AD9: 29.559911 | AE9: 31.641969 | AF9: 33.822076 | AG9: 36.10485 | AH9: 38.495126 | AI9: 40.997967 | AJ9: 43.618674 | AK9: 46.362797 | AL9: 49.236148
A10: 2025-Q%q | B10: 13.495685 | C10: 0.99708064 | D10: 9.9991502 | F10: OTAs (USD B) | G10: 8.43 | H10: 17.041811 | I10: 25.839356 | J10: 34.826638 | K10: 44.007751 | L10: 53.386875 | M10: 62.96828 | N10: 72.75633 | O10: 82.75548 | P10: 92.970284 | Q10: 103.40539 | R10: 114.06556 | S10: 124.95563 | T10: 136.08057 | U10: 147.44545 | V10: 159.05544 | W10: 170.91582 | X10: 183.03199 | Y10: 195.40948 | Z10: 208.05391 | AA10: 220.97105 | AB10: 234.16678 | AC10: 247.6471 | AD10: 261.41816 | AE10: 275.48621 | AF10: 289.85768 | AG10: 304.5391 | AH10: 319.53715 | AI10: 334.85867 | AJ10: 350.51064 | AK10: 366.50017 | AL10: 382.83455
A11: 2025-Q%q | B11: 13.901146 | C11: 1.0440359 | D11: 10.214804
A12: 2025-Q%q | B12: 14.318788 | C12: 1.0932024 | D12: 10.435109
A13: 2025-Q%q | B13: 14.748978 | C13: 1.1446843 | D13: 10.660165
A14: 2026-Q%q | B14: 15.192093 | C14: 1.1985906 | D14: 10.890074
A15: 2026-Q%q | B15: 15.64852 | C15: 1.2550356 | D15: 11.124943
A16: 2026-Q%q | B16: 16.11866 | C16: 1.3141386 | D16: 11.364877
A17: 2026-Q%q | B17: 16.602925 | C17: 1.376025 | D17: 11.609985
A18: 2027-Q%q | B18: 17.101739 | C18: 1.4408258 | D18: 11.86038
A19: 2027-Q%q | B19: 17.615539 | C19: 1.5086782 | D19: 12.116175
A20: 2027-Q%q | B20: 18.144776 | C20: 1.579726 | D20: 12.377487
A21: 2027-Q%q | B21: 18.689913 | C21: 1.6541197 | D21: 12.644435
A22: 2028-Q%q | B22: 19.251427 | C22: 1.7320167 | D22: 12.91714
... A33: 2030-Q%q | B33: 26.660928 | C33: 2.8733512 | D33: 16.334382
G38: =+G7 -> 2023 Q1 | H38: =+H7 -> 2023 Q2 | I38: =+I7 -> 2023 Q3 | J38: =+J7 -> 2023 Q4 | K38: =+K7 -> 2024 Q1 | L38: =+L7 -> 2024 Q2 | M38: =+M7 -> 2024 Q3 | N38: =+N7 -> 2024 Q4 | ... AL38: =+AL7 -> 2030 Q4
F39: =+F8 -> SaaS Tourism (USD B) | G39: =+G2 -> 10.65 | H39: =+H2 -> 10.969966 | I39: =+I2 -> 11.299545 | J39: =+J2 -> 11.639025 | K39: =+K2 -> 11.988705 | L39: =+L2 -> 12.348891 | M39: =+M2 -> 12.719897 | N39: =+N2 -> 13.102051 | ... AL39: =+AL2 -> 26.660928
F40: =+F9 -> AI in Tourism SaaS (USD B) | G40: =+G3 -> 0.69 | H40: =+H3 -> 0.72249399 | I40: =+I3 -> 0.75651822 | J40: =+J3 -> 0.79214473 | K40: =+K3 -> 0.829449 | L40: =+L3 -> 0.86851003 | M40: =+M3 -> 0.90941055 | N40: =+N3 -> 0.95223718 | ... AL40: =+AL3 -> 2.8733512
F41: =+F10 -> OTAs (USD B) | G41: =+G4 -> 8.43 | H41: =+H4 -> 8.6118115 | I41: =+I4 -> 8.7975441 | J41: =+J4 -> 8.9872825 | K41: =+K4 -> 9.181113 | L41: =+L4 -> 9.3791239 | M41: =+M4 -> 9.5814053 | N41: =+N4 -> 9.7880494 | ... AL41: =+AL4 -> 16.334382
F44: CURVAS TRIMESTRALES
F45: =+F39 -> SaaS Tourism (USD B) | G45: 0 | H45: =+(H39-G39)/G39 -> 0.030043739 | I45: =+(I39-H39)/H39 -> 0.030043738 | J45: =+(J39-I39)/I39 -> 0.030043739 | K45: =+(K39-J39)/J39 -> 0.030043739 | L45: =+(L39-K39)/K39 -> 0.030043739 | M45: =+(M39-L39)/L39 -> 0.030043739 | N45: =+(N39-M39)/M39 -> 0.030043738 | O45: =+(O39-N39)/N39 -> 0.030043739 | ... AL45: =+(AL39-AK39)/AK39 -> 0.030043739
F46: =+F40 -> AI in Tourism SaaS (USD B) | G46: 0 | H46: =+(H40-G40)/G40 -> 0.047092742 | I46: =+(I40-H40)/H40 -> 0.047092742 | J46: =+(J40-I40)/I40 -> 0.047092742 | K46: =+(K40-J40)/J40 -> 0.047092743 | L46: =+(L40-K40)/K40 -> 0.047092742 | M46: =+(M40-L40)/L40 -> 0.047092742 | N46: =+(N40-M40)/M40 -> 0.047092742 | O46: =+(O40-N40)/N40 -> 0.047092742 | ... AL46: =+(AL40-AK40)/AK40 -> 0.047092742
F47: =+F41 -> OTAs (USD B) | G47: 0 | H47: =+(H41-G41)/G41 -> 0.021567198 | I47: =+(I41-H41)/H41 -> 0.021567198 | J47: =+(J41-I41)/I41 -> 0.021567198 | K47: =+(K41-J41)/J41 -> 0.021567198 | L47: =+(L41-K41)/K41 -> 0.021567198 | M47: =+(M41-L41)/L41 -> 0.021567198 | N47: =+(N41-M41)/M41 -> 0.021567198 | O47: =+(O41-N41)/N41 -> 0.021567198 | ... AL47: =+(AL41-AK41)/AK41 -> 0.021567198
F50: CURVAS ACUMULADAS
F51: =+F45 -> SaaS Tourism (USD B) | G51: =+G45 -> 0 | H51: =+H45+G51 -> 0.030043739 | I51: =+I45+H51 -> 0.060087477 | J51: =+J45+I51 -> 0.090131216 | K51: =+K45+J51 -> 0.12017495 | L51: =+L45+K51 -> 0.15021869 | M51: =+M45+L51 -> 0.18026243 | N51: =+N45+M51 -> 0.21030617 | O51: =+O45+N51 -> 0.24034991 | ... AL51: =+AL45+AK51 -> 0.9313559
F52: =+F46 -> AI in Tourism SaaS (USD B) | G52: =+G46 -> 0 | H52: =+H46+G52 -> 0.047092742 | I52: =+I46+H52 -> 0.094185484 | J52: =+J46+I52 -> 0.14127823 | K52: =+K46+J52 -> 0.18837097 | L52: =+L46+K52 -> 0.23546371 | M52: =+M46+L52 -> 0.28255645 | N52: =+N46+M52 -> 0.32964919 | O52: =+O46+N52 -> 0.37674194 | ... AL52: =+AL46+AK52 -> 1.459875
F53: =+F47 -> OTAs (USD B) | G53: =+G47 -> 0 | H53: =+H47+G53 -> 0.021567198 | I53: =+I47+H53 -> 0.043134396 | J53: =+J47+I53 -> 0.064701594 | K53: =+K47+J53 -> 0.086268792 | L53: =+L47+K53 -> 0.10783599 | M53: =+M47+L53 -> 0.12940319 | N53: =+N47+M53 -> 0.15097039 | O53: =+O47+N53 -> 0.17253758 | ... AL53: =+AL47+AK53 -> 0.66858314
F56: Quarter | G56: =+G38 -> 2023 Q1 | H56: =+H38 -> 2023 Q2 | I56: =+I38 -> 2023 Q3 | J56: =+J38 -> 2023 Q4 | K56: =+K38 -> 2024 Q1 | L56: =+L38 -> 2024 Q2 | M56: =+M38 -> 2024 Q3 | N56: =+N38 -> 2024 Q4 | ... AL56: =+AL38 -> 2030 Q4
F57: SaaS Tourism Revenue (USD million) | G57: 10653.967 | H57: 10973.98 | I57: 11303.604 | J57: 11643.13 | K57: 11992.854 | L57: 12353.083 | M57: 12724.132 | N57: 13106.326 | O57: 13500 | P57: 13905.499 | Q57: 14323.178 | R57: 14753.402 | S57: 15196.549 | T57: 15653.007 | U57: 16123.176 | V57: 16607.467 | W57: 17106.304 | X57: 17620.125 | Y57: 18149.38 | Z57: 18694.532 | AA57: 19256.059 | AB57: 19834.452 | AC57: 20430.218 | AD57: 21043.88 | AE57: 21675.974 | AF57: 22327.054 | AG57: 22997.69 | AH57: 23688.471 | AI57: 24400 | AJ57: 25132.902 | AK57: 25887.817 | AL57: 26665.408
G59: 0 | H59: =+(H57-G57)/G57 -> 0.030036947 | I59: =+(I57-H57)/H57 -> 0.030036947 | J59: =+(J57-I57)/I57 -> 0.030036947 | K59: =+(K57-J57)/J57 -> 0.030036947 | L59: =+(L57-K57)/K57 -> 0.030036947 | M59: =+(M57-L57)/L57 -> 0.030036947 | N59: =+(N57-M57)/M57 -> 0.030036947 | O59: =+(O57-N57)/N57 -> 0.030036947 | ... AL59: =+(AL57-AK57)/AK57 -> 0.030036947
H60: =+H59 -> 0.030036947 | I60: =+H60+I59 -> 0.060073894 | J60: =+I60+J59 -> 0.090110841 | K60: =+J60+K59 -> 0.12014779 | L60: =+K60+L59 -> 0.15018473 | M60: =+L60+M59 -> 0.18022168 | N60: =+M60+N59 -> 0.21025863 | O60: =+N60+O59 -> 0.24029557 | P60: =+O60+P59 -> 0.27033252 | ... AL60: =+AK60+AL59 -> 0.93114535
H63: 2023
H64: 2024
H65: 2025 | L65: 2023 | M65: 2024 | N65: 2025 | O65: 2026 | P65: 2027 | Q65: 2028 | R65: 2029 | S65: 2030
H66: 2026 | L66: =SUM(G57:J57) -> 44574.681 | M66: =SUM(K57:N57) -> 50176.395 | N66: =SUM(O57:R57) -> 56482.078 | O66: =SUM(S57:V57) -> 63580.199 | P66: =SUM(W57:Z57) -> 71570.342 | Q66: =SUM(AA57:AD57) -> 80564.609 | R66: =SUM(AE57:AH57) -> 90689.188 | S66: =SUM(AI57:AL57) -> 102086.13
H67: 2027 | M67: =+(M66-L66)/L66 -> 0.12567031 | N67: =+(N66-M66)/M66 -> 0.12567031 | O67: =+(O66-N66)/N66 -> 0.12567031 | P67: =+(P66-O66)/O66 -> 0.12567031 | Q67: =+(Q66-P66)/P66 -> 0.12567031 | R67: =+(R66-Q66)/Q66 -> 0.12567031 | S67: =+(S66-R66)/R66 -> 0.12567031
H68: 2028 | M68: =+M67 -> 0.12567031 | N68: =+M68+N67 -> 0.25134062 | O68: =+N68+O67 -> 0.37701093 | P68: =+O68+P67 -> 0.50268124 | Q68: =+P68+Q67 -> 0.62835155 | R68: =+Q68+R67 -> 0.75402186 | S68: =+R68+S67 -> 0.87969217
H69: 2029
H70: 2030

Sheet Curva Dolar Blue
A1: category | B1: valor | I1: 44927 | J1: 178.1417 | K1: =+I1 -> 44927 | L1: =+SUMIFS($J$1:$J$574,$I$1:$I$574,K1) -> 178.1417
A2: =DATE(D2,B2,C2) -> 44928 | B2: 1 | C2: 2 | D2: 2023 | E2: 344 | F2: 44927 | G2: =+IF(SUMIFS($E$2:$E$575,$A$2:$A$575,F2)=0,G1,SUMIFS($E$2:$E$575,$A$2:$A$575,F2)) -> 0 | I2: 44928 | J2: 178.1417 | K2: =+K1+1 -> 44928 | L2: =+IF(SUMIFS($J$1:$J$1574,$I$1:$I$1574,K2)=0,L1,SUMIFS($J$1:$J$1574,$I$1:$I$1574,K2)) -> 178.1417 | Q2: 44927 | R2: 6 | S2: =+R2/100 -> 0.06
A3: =DATE(D3,B3,C3) -> 44929 | B3: 1 | C3: 3 | D3: 2023 | E3: 353 | F3: =F2+1 -> 44928 | G3: =+IF(SUMIFS($E$2:$E$1575,$A$2:$A$1575,F3)=0,G2,SUMIFS($E$2:$E$1575,$A$2:$A$1575,F3)) -> 344 | I3: 44929 | J3: 178.4317 | K3: =+K2+1 -> 44929 | L3: =+IF(SUMIFS($J$1:$J$574,$I$1:$I$574,K3)=0,L2,SUMIFS($J$1:$J$574,$I$1:$I$574,K3)) -> 178.4317 | Q3: 44958 | R3: 6.6 | S3: =+R3/100 -> 0.066
A4: =DATE(D4,B4,C4) -> 44930 | B4: 1 | C4: 4 | D4: 2023 | E4: 354 | F4: =F3+1 -> 44929 | G4: =+IF(SUMIFS($E$2:$E$1575,$A$2:$A$1575,F4)=0,G3,SUMIFS($E$2:$E$1575,$A$2:$A$1575,F4)) -> 353 | I4: 44930 | J4: 178.6533 | K4: =+K3+1 -> 44930 | L4: =+IF(SUMIFS($J$1:$J$574,$I$1:$I$574,K4)=0,L3,SUMIFS($J$1:$J$574,$I$1:$I$574,K4)) -> 178.6533 | Q4: 44986 | R4: 7.7 | S4: =+R4/100 -> 0.077
A5: =DATE(D5,B5,C5) -> 44931 | B5: 1 | C5: 5 | D5: 2023 | E5: 353 | F5: =F4+1 -> 44930 | G5: =+IF(SUMIFS($E$2:$E$1575,$A$2:$A$1575,F5)=0,G4,SUMIFS($E$2:$E$1575,$A$2:$A$1575,F5)) -> 354 | I5: 44931 | J5: 178.94 | K5: =+K4+1 -> 44931 | L5: =+IF(SUMIFS($J$1:$J$574,$I$1:$I$574,K5)=0,L4,SUMIFS($J$1:$J$574,$I$1:$I$574,K5)) -> 178.94 | Q5: 45017 | R5: 8.4 | S5: =+R5/100 -> 0.084
A6: =DATE(D6,B6,C6) -> 44932 | B6: 1 | C6: 6 | D6: 2023 | E6: 354 | F6: =F5+1 -> 44931 | G6: =+IF(SUMIFS($E$2:$E$1575,$A$2:$A$1575,F6)=0,G5,SUMIFS($E$2:$E$1575,$A$2:$A$1575,F6)) -> 353 | I6: 44932 | J6: 179.2433 | K6: =+K5+1 -> 44932 | L6: =+IF(SUMIFS($J$1:$J$574,$I$1:$I$574,K6)=0,L5,SUMIFS($J$1:$J$574,$I$1:$I$574,K6)) -> 179.2433 | Q6: 45047 | R6: 7.8 | S6: =+R6/100 -> 0.078
A7: =DATE(D7,B7,C7) -> 44935 | B7: 1 | C7: 9 | D7: 2023 | E7: 355 | F7: =F6+1 -> 44932 | G7: =+IF(SUMIFS($E$2:$E$1575,$A$2:$A$1575,F7)=0,G6,SUMIFS($E$2:$E$1575,$A$2:$A$1575,F7)) -> 354 | I7: 44935 | J7: 180.1367 | K7: =+K6+1 -> 44933 | L7: =+IF(SUMIFS($J$1:$J$1574,$I$1:$I$1574,K7)=0,L6,SUMIFS($J$1:$J$1574,$I$1:$I$1574,K7)) -> 179.2433 | Q7: 45078 | R7: 6 | S7: =+R7/100 -> 0.06
A8: =DATE(D8,B8,C8) -> 44936 | B8: 1 | C8: 10 | D8: 2023 | E8: 357 | F8: =F7+1 -> 44933 | G8: =+IF(SUMIFS($E$2:$E$1575,$A$2:$A$1575,F8)=0,G7,SUMIFS($E$2:$E$1575,$A$2:$A$1575,F8)) -> 354 | I8: 44936 | J8: 180.4017 | K8: =+K7+1 -> 44934 | L8: =+IF(SUMIFS($J$1:$J$1574,$I$1:$I$1574,K8)=0,L7,SUMIFS($J$1:$J$1574,$I$1:$I$1574,K8)) -> 179.2433 | Q8: 45108 | R8: 6.3 | S8: =+R8/100 -> 0.063
A9: =DATE(D9,B9,C9) -> 44937 | B9: 1 | C9: 11 | D9: 2023 | E9: 358 | F9: =F8+1 -> 44934 | G9: =+IF(SUMIFS($E$2:$E$1575,$A$2:$A$1575,F9)=0,G8,SUMIFS($E$2:$E$1575,$A$2:$A$1575,F9)) -> 354 | I9: 44937 | J9: 180.6883 | K9: =+K8+1 -> 44935 | L9: =+IF(SUMIFS($J$1:$J$1574,$I$1:$I$1574,K9)=0,L8,SUMIFS($J$1:$J$1574,$I$1:$I$1574,K9)) -> 180.1367 | Q9: 45139 | R9: 12.4 | S9: =+R9/100 -> 0.124
A10: =DATE(D10,B10,C10) -> 44938 | B10: 1 | C10: 12 | D10: 2023 | E10: 361 | F10: =F9+1 -> 44935 | G10: =+IF(SUMIFS($E$2:$E$1575,$A$2:$A$1575,F10)=0,G9,SUMIFS($E$2:$E$1575,$A$2:$A$1575,F10)) -> 355 | I10: 44938 | J10: 180.97 | K10: =+K9+1 -> 44936 | L10: =+IF(SUMIFS($J$1:$J$1574,$I$1:$I$1574,K10)=0,L9,SUMIFS($J$1:$J$1574,$I$1:$I$1574,K10)) -> 180.4017 | Q10: 45170 | R10: 12.7 | S10: =+R10/100 -> 0.127
A11: =DATE(D11,B11,C11) -> 44939 | B11: 1 | C11: 13 | D11: 2023 | E11: 368 | F11: =F10+1 -> 44936 | G11: =+IF(SUMIFS($E$2:$E$1575,$A$2:$A$1575,F11)=0,G10,SUMIFS($E$2:$E$1575,$A$2:$A$1575,F11)) -> 357 | I11: 44939 | J11: 181.28 | K11: =+K10+1 -> 44937 | L11: =+IF(SUMIFS($J$1:$J$1574,$I$1:$I$1574,K11)=0,L10,SUMIFS($J$1:$J$1574,$I$1:$I$1574,K11)) -> 180.6883 | Q11: 45200 | R11: 8.3 | S11: =+R11/100 -> 0.083
A12: =DATE(D12,B12,C12) -> 44942 | B12: 1 | C12: 16 | D12: 2023 | E12: 368 | F12: =F11+1 -> 44937 | G12: =+IF(SUMIFS($E$2:$E$1575,$A$2:$A$1575,F12)=0,G11,SUMIFS($E$2:$E$1575,$A$2:$A$1575,F12)) -> 358 | I12: 44942 | J12: 182.1633 | K12: =+K11+1 -> 44938 | L12: =+IF(SUMIFS($J$1:$J$1574,$I$1:$I$1574,K12)=0,L11,SUMIFS($J$1:$J$1574,$I$1:$I$1574,K12)) -> 180.97 | Q12: 45231 | R12: 12.8 | S12: =+R12/100 -> 0.128
A13: =DATE(D13,B13,C13) -> 44943 | B13: 1 | C13: 17 | D13: 2023 | E13: 377 | F13: =F12+1 -> 44938 | G13: =+IF(SUMIFS($E$2:$E$1575,$A$2:$A$1575,F13)=0,G12,SUMIFS($E$2:$E$1575,$A$2:$A$1575,F13)) -> 361 | I13: 44943 | J13: 182.4917 | K13: =+K12+1 -> 44939 | L13: =+IF(SUMIFS($J$1:$J$1574,$I$1:$I$1574,K13)=0,L12,SUMIFS($J$1:$J$1574,$I$1:$I$1574,K13)) -> 181.28 | Q13: 45261 | R13: 25.5 | S13: =+R13/100 -> 0.255
A14: =DATE(D14,B14,C14) -> 44944 | B14: 1 | C14: 18 | D14: 2023 | E14: 376 | F14: =F13+1 -> 44939 | G14: =+IF(SUMIFS($E$2:$E$1575,$A$2:$A$1575,F14)=0,G13,SUMIFS($E$2:$E$1575,$A$2:$A$1575,F14)) -> 368 | I14: 44944 | J14: 182.8033 | K14: =+K13+1 -> 44940 | L14: =+IF(SUMIFS($J$1:$J$1574,$I$1:$I$1574,K14)=0,L13,SUMIFS($J$1:$J$1574,$I$1:$I$1574,K14)) -> 181.28 | Q14: 45292 | R14: 20.6 | S14: =+R14/100 -> 0.206
A15: =DATE(D15,B15,C15) -> 44945 | B15: 1 | C15: 19 | D15: 2023 | E15: 374 | F15: =F14+1 -> 44940 | G15: =+IF(SUMIFS($E$2:$E$1575,$A$2:$A$1575,F15)=0,G14,SUMIFS($E$2:$E$1575,$A$2:$A$1575,F15)) -> 368 | I15: 44945 | J15: 183.125 | K15: =+K14+1 -> 44941 | L15: =+IF(SUMIFS($J$1:$J$1574,$I$1:$I$1574,K15)=0,L14,SUMIFS($J$1:$J$1574,$I$1:$I$1574,K15)) -> 181.28 | Q15: 45323 | R15: 13.2 | S15: =+R15/100 -> 0.132
A16: =DATE(D16,B16,C16) -> 44946 | B16: 1 | C16: 20 | D16: 2023 | E16: 375 | F16: =F15+1 -> 44941 | G16: =+IF(SUMIFS($E$2:$E$1575,$A$2:$A$1575,F16)=0,G15,SUMIFS($E$2:$E$1575,$A$2:$A$1575,F16)) -> 368 | I16: 44946 | J16: 183.4367 | K16: =+K15+1 -> 44942 | L16: =+IF(SUMIFS($J$1:$J$1574,$I$1:$I$1574,K16)=0,L15,SUMIFS($J$1:$J$1574,$I$1:$I$1574,K16)) -> 182.1633 | Q16: 45352 | R16: 11 | S16: =+R16/100 -> 0.11
A17: =DATE(D17,B17,C17) -> 44949 | B17: 1 | C17: 23 | D17: 2023 | E17: 375 | F17: =F16+1 -> 44942 | G17: =+IF(SUMIFS($E$2:$E$1575,$A$2:$A$1575,F17)=0,G16,SUMIFS($E$2:$E$1575,$A$2:$A$1575,F17)) -> 368 | I17: 44949 | J17: 184.3733 | K17: =+K16+1 -> 44943 | L17: =+IF(SUMIFS($J$1:$J$1574,$I$1:$I$1574,K17)=0,L16,SUMIFS($J$1:$J$1574,$I$1:$I$1574,K17)) -> 182.4917 | Q17: 45383 | R17: 8.8 | S17: =+R17/100 -> 0.088
A18: =DATE(D18,B18,C18) -> 44950 | B18: 1 | C18: 24 | D18: 2023 | E18: 381 | F18: =F17+1 -> 44943 | G18: =+IF(SUMIFS($E$2:$E$1575,$A$2:$A$1575,F18)=0,G17,SUMIFS($E$2:$E$1575,$A$2:$A$1575,F18)) -> 377 | I18: 44950 | J18: 184.6867 | K18: =+K17+1 -> 44944 | L18: =+IF(SUMIFS($J$1:$J$1574,$I$1:$I$1574,K18)=0,L17,SUMIFS($J$1:$J$1574,$I$1:$I$1574,K18)) -> 182.8033 | Q18: 45413 | R18: 4.2 | S18: =+R18/100 -> 0.042
... A28: =DATE(D28,B28,C28) -> 44964 | B28: 2 | C28: 7 | D28: 2023 | E28: 377 | F28: =F27+1 -> 44953 | G28: =+IF(SUMIFS($E$2:$E$1575,$A$2:$A$1575,F28)=0,G27,SUMIFS($E$2:$E$1575,$A$2:$A$1575,F28)) -> 386 | I28: 44964 | J28: 189.4567 | K28: =+K27+1 -> 44954 | L28: =+IF(SUMIFS($J$1:$J$1574,$I$1:$I$1574,K28)=0,L27,SUMIFS($J$1:$J$1574,$I$1:$I$1574,K28)) -> 185.63 | Q28: 45717 | R28: 3.7 | S28: =+R28/100 -> 0.037
A29: =DATE(D29,B29,C29) -> 44965 | B29: 2 | C29: 8 | D29: 2023 | E29: 379 | F29: =F28+1 -> 44954 | G29: =+IF(SUMIFS($E$2:$E$1575,$A$2:$A$1575,F29)=0,G28,SUMIFS($E$2:$E$1575,$A$2:$A$1575,F29)) -> 386 | I29: 44965 | J29: 189.8633 | K29: =+K28+1 -> 44955 | L29: =+IF(SUMIFS($J$1:$J$1574,$I$1:$I$1574,K29)=0,L28,SUMIFS($J$1:$J$1574,$I$1:$I$1574,K29)) -> 185.63
A30: =DATE(D30,B30,C30) -> 44966 | B30: 2 | C30: 9 | D30: 2023 | E30: 380 | F30: =F29+1 -> 44955 | G30: =+IF(SUMIFS($E$2:$E$1575,$A$2:$A$1575,F30)=0,G29,SUMIFS($E$2:$E$1575,$A$2:$A$1575,F30)) -> 386 | I30: 44966 | J30: 190.2033 | K30: =+K29+1 -> 44956 | L30: =+IF(SUMIFS($J$1:$J$1574,$I$1:$I$1574,K30)=0,L29,SUMIFS($J$1:$J$1574,$I$1:$I$1574,K30)) -> 186.5783
A31: =DATE(D31,B31,C31) -> 44967 | B31: 2 | C31: 10 | D31: 2023 | E31: 377 | F31: =F30+1 -> 44956 | G31: =+IF(SUMIFS($E$2:$E$1575,$A$2:$A$1575,F31)=0,G30,SUMIFS($E$2:$E$1575,$A$2:$A$1575,F31)) -> 386 | I31: 44967 | J31: 190.5283 | K31: =+K30+1 -> 44957 | L31: =+IF(SUMIFS($J$1:$J$1574,$I$1:$I$1574,K31)=0,L30,SUMIFS($J$1:$J$1574,$I$1:$I$1574,K31)) -> 186.875
A32: =DATE(D32,B32,C32) -> 44970 | B32: 2 | C32: 13 | D32: 2023 | E32: 378 | F32: =F31+1 -> 44957 | G32: =+IF(SUMIFS($E$2:$E$1575,$A$2:$A$1575,F32)=0,G31,SUMIFS($E$2:$E$1575,$A$2:$A$1575,F32)) -> 382 | I32: 44970 | J32: 191.64 | K32: =+K31+1 -> 44958 | L32: =+IF(SUMIFS($J$1:$J$1574,$I$1:$I$1574,K32)=0,L31,SUMIFS($J$1:$J$1574,$I$1:$I$1574,K32)) -> 187.3083
A33: =DATE(D33,B33,C33) -> 44971 | B33: 2 | C33: 14 | D33: 2023 | E33: 381 | F33: =F32+1 -> 44958 | G33: =+IF(SUMIFS($E$2:$E$1575,$A$2:$A$1575,F33)=0,G32,SUMIFS($E$2:$E$1575,$A$2:$A$1575,F33)) -> 377 | I33: 44971 | J33: 192.02 | K33: =+K32+1 -> 44959 | L33: =+IF(SUMIFS($J$1:$J$1574,$I$1:$I$1574,K33)=0,L32,SUMIFS($J$1:$J$1574,$I$1:$I$1574,K33)) -> 187.6133
A34: =DATE(D34,B34,C34) -> 44972 | B34: 2 | C34: 15 | D34: 2023 | E34: 379 | F34: =F33+1 -> 44959 | G34: =+IF(SUMIFS($E$2:$E$1575,$A$2:$A$1575,F34)=0,G33,SUMIFS($E$2:$E$1575,$A$2:$A$1575,F34)) -> 378 | I34: 44972 | J34: 192.375 | K34: =+K33+1 -> 44960 | L34: =+IF(SUMIFS($J$1:$J$1574,$I$1:$I$1574,K34)=0,L33,SUMIFS($J$1:$J$1574,$I$1:$I$1574,K34)) -> 187.95
A35: =DATE(D35,B35,C35) -> 44973 | B35: 2 | C35: 16 | D35: 2023 | E35: 377 | F35: =F34+1 -> 44960 | G35: =+IF(SUMIFS($E$2:$E$1575,$A$2:$A$1575,F35)=0,G34,SUMIFS($E$2:$E$1575,$A$2:$A$1575,F35)) -> 379 | I35: 44973 | J35: 192.7833 | K35: =+K34+1 -> 44961 | L35: =+IF(SUMIFS($J$1:$J$1574,$I$1:$I$1574,K35)=0,L34,SUMIFS($J$1:$J$1574,$I$1:$I$1574,K35)) -> 187.95
A36: =DATE(D36,B36,C36) -> 44974 | B36: 2 | C36: 17 | D36: 2023 | E36: 377 | F36: =F35+1 -> 44961 | G36: =+IF(SUMIFS($E$2:$E$1575,$A$2:$A$1575,F36)=0,G35,SUMIFS($E$2:$E$1575,$A$2:$A$1575,F36)) -> 379 | I36: 44974 | J36: 193.1933 | K36: =+K35+1 -> 44962 | L36: =+IF(SUMIFS($J$1:$J$1574,$I$1:$I$1574,K36)=0,L35,SUMIFS($J$1:$J$1574,$I$1:$I$1574,K36)) -> 187.95
A37: =DATE(D37,B37,C37) -> 44977 | B37: 2 | C37: 20 | D37: 2023 | E37: 377 | F37: =F36+1 -> 44962 | G37: =+IF(SUMIFS($E$2:$E$1575,$A$2:$A$1575,F37)=0,G36,SUMIFS($E$2:$E$1575,$A$2:$A$1575,F37)) -> 379 | I37: 44979 | J37: 194.98 | K37: =+K36+1 -> 44963 | L37: =+IF(SUMIFS($J$1:$J$1574,$I$1:$I$1574,K37)=0,L36,SUMIFS($J$1:$J$1574,$I$1:$I$1574,K37)) -> 189.095
A38: =DATE(D38,B38,C38) -> 44978 | B38: 2 | C38: 21 | D38: 2023 | E38: 377 | F38: =F37+1 -> 44963 | G38: =+IF(SUMIFS($E$2:$E$1575,$A$2:$A$1575,F38)=0,G37,SUMIFS($E$2:$E$1575,$A$2:$A$1575,F38)) -> 377 | I38: 44980 | J38: 195.35 | K38: =+K37+1 -> 44964 | L38: =+IF(SUMIFS($J$1:$J$1574,$I$1:$I$1574,K38)=0,L37,SUMIFS($J$1:$J$1574,$I$1:$I$1574,K38)) -> 189.4567
A39: =DATE(D39,B39,C39) -> 44979 | B39: 2 | C39: 22 | D39: 2023 | E39: 377 | F39: =F38+1 -> 44964 | G39: =+IF(SUMIFS($E$2:$E$1575,$A$2:$A$1575,F39)=0,G38,SUMIFS($E$2:$E$1575,$A$2:$A$1575,F39)) -> 377 | I39: 44981 | J39: 195.7383 | K39: =+K38+1 -> 44965 | L39: =+IF(SUMIFS($J$1:$J$1574,$I$1:$I$1574,K39)=0,L38,SUMIFS($J$1:$J$1574,$I$1:$I$1574,K39)) -> 189.8633
A40: =DATE(D40,B40,C40) -> 44980 | B40: 2 | C40: 23 | D40: 2023 | E40: 379 | F40: =F39+1 -> 44965 | G40: =+IF(SUMIFS($E$2:$E$1575,$A$2:$A$1575,F40)=0,G39,SUMIFS($E$2:$E$1575,$A$2:$A$1575,F40)) -> 379 | I40: 44984 | J40: 196.8117 | K40: =+K39+1 -> 44966 | L40: =+IF(SUMIFS($J$1:$J$1574,$I$1:$I$1574,K40)=0,L39,SUMIFS($J$1:$J$1574,$I$1:$I$1574,K40)) -> 190.2033
... A668: =DATE(D668,B668,C668) -> 45789 | B668: 5 | C668: 12 | D668: 2025 | E668: 1170 | F668: =F667+1 -> 45593 | G668: =+IF(SUMIFS($E$2:$E$1575,$A$2:$A$1575,F668)=0,G667,SUMIFS($E$2:$E$1575,$A$2:$A$1575,F668)) -> 1220 | I668: 45926 | J668: 1332 | K668: =+K667+1 -> 45594 | L668: =+IF(SUMIFS($J$1:$J$1574,$I$1:$I$1574,K668)=0,L667,SUMIFS($J$1:$J$1574,$I$1:$I$1574,K668)) -> 989.25
A669: =+A668+1 -> 45790 | E669: 1160 | F669: =F668+1 -> 45594 | G669: =+IF(SUMIFS($E$2:$E$1575,$A$2:$A$1575,F669)=0,G668,SUMIFS($E$2:$E$1575,$A$2:$A$1575,F669)) -> 1195 | I669: 45929 | J669: 1341 | K669: =+K668+1 -> 45595 | L669: =+IF(SUMIFS($J$1:$J$1574,$I$1:$I$1574,K669)=0,L668,SUMIFS($J$1:$J$1574,$I$1:$I$1574,K669)) -> 990.25
A670: =+A669+1 -> 45791 | E670: 1165 | F670: =F669+1 -> 45595 | G670: =+IF(SUMIFS($E$2:$E$1575,$A$2:$A$1575,F670)=0,G669,SUMIFS($E$2:$E$1575,$A$2:$A$1575,F670)) -> 1180 | I670: 45930 | J670: 1366.5833 | K670: =+K669+1 -> 45596 | L670: =+IF(SUMIFS($J$1:$J$1574,$I$1:$I$1574,K670)=0,L669,SUMIFS($J$1:$J$1574,$I$1:$I$1574,K670)) -> 990.75
A671: =+A670+1 -> 45792 | E671: 1165 | F671: =F670+1 -> 45596 | G671: =+IF(SUMIFS($E$2:$E$1575,$A$2:$A$1575,F671)=0,G670,SUMIFS($E$2:$E$1575,$A$2:$A$1575,F671)) -> 1190 | I671: 45931 | J671: 1423.8333 | K671: =+K670+1 -> 45597 | L671: =+IF(SUMIFS($J$1:$J$1574,$I$1:$I$1574,K671)=0,L670,SUMIFS($J$1:$J$1574,$I$1:$I$1574,K671)) -> 992.75
A672: =+A671+1 -> 45793 | E672: 1165 | F672: =F671+1 -> 45597 | G672: =+IF(SUMIFS($E$2:$E$1575,$A$2:$A$1575,F672)=0,G671,SUMIFS($E$2:$E$1575,$A$2:$A$1575,F672)) -> 1190 | I672: 45932 | J672: 1424.75 | K672: =+K671+1 -> 45598 | L672: =+IF(SUMIFS($J$1:$J$1574,$I$1:$I$1574,K672)=0,L671,SUMIFS($J$1:$J$1574,$I$1:$I$1574,K672)) -> 992.75
A673: =+A672+1 -> 45794 | E673: 1165 | F673: =F672+1 -> 45598 | G673: =+IF(SUMIFS($E$2:$E$1575,$A$2:$A$1575,F673)=0,G672,SUMIFS($E$2:$E$1575,$A$2:$A$1575,F673)) -> 1190 | I673: 45933 | J673: 1424.75 | K673: =+K672+1 -> 45599 | L673: =+IF(SUMIFS($J$1:$J$1574,$I$1:$I$1574,K673)=0,L672,SUMIFS($J$1:$J$1574,$I$1:$I$1574,K673)) -> 992.75
A674: =+A673+1 -> 45795 | E674: 1165 | F674: =F673+1 -> 45599 | G674: =+IF(SUMIFS($E$2:$E$1575,$A$2:$A$1575,F674)=0,G673,SUMIFS($E$2:$E$1575,$A$2:$A$1575,F674)) -> 1190 | I674: 45936 | J674: 1429.75 | K674: =+K673+1 -> 45600 | L674: =+IF(SUMIFS($J$1:$J$1574,$I$1:$I$1574,K674)=0,L673,SUMIFS($J$1:$J$1574,$I$1:$I$1574,K674)) -> 993.3333
A675: =+A674+1 -> 45796 | E675: 1165 | F675: =F674+1 -> 45600 | G675: =+IF(SUMIFS($E$2:$E$1575,$A$2:$A$1575,F675)=0,G674,SUMIFS($E$2:$E$1575,$A$2:$A$1575,F675)) -> 1170 | I675: 45937 | J675: 1429.75 | K675: =+K674+1 -> 45601 | L675: =+IF(SUMIFS($J$1:$J$1574,$I$1:$I$1574,K675)=0,L674,SUMIFS($J$1:$J$1574,$I$1:$I$1574,K675)) -> 994.75
A676: =+A675+1 -> 45797 | E676: 1175 | F676: =F675+1 -> 45601 | G676: =+IF(SUMIFS($E$2:$E$1575,$A$2:$A$1575,F676)=0,G675,SUMIFS($E$2:$E$1575,$A$2:$A$1575,F676)) -> 1135 | I676: 45938 | J676: 1429.75 | K676: =+K675+1 -> 45602 | L676: =+IF(SUMIFS($J$1:$J$1574,$I$1:$I$1574,K676)=0,L675,SUMIFS($J$1:$J$1574,$I$1:$I$1574,K676)) -> 994.75
A677: =+A676+1 -> 45798 | E677: 1175 | F677: =F676+1 -> 45602 | G677: =+IF(SUMIFS($E$2:$E$1575,$A$2:$A$1575,F677)=0,G676,SUMIFS($E$2:$E$1575,$A$2:$A$1575,F677)) -> 1135 | I677: 45939 | J677: 1451.75 | K677: =+K676+1 -> 45603 | L677: =+IF(SUMIFS($J$1:$J$1574,$I$1:$I$1574,K677)=0,L676,SUMIFS($J$1:$J$1574,$I$1:$I$1574,K677)) -> 995.33333
A678: =+A677+1 -> 45799 | E678: 1165 | F678: =F677+1 -> 45603 | G678: =+IF(SUMIFS($E$2:$E$1575,$A$2:$A$1575,F678)=0,G677,SUMIFS($E$2:$E$1575,$A$2:$A$1575,F678)) -> 1120 | I678: 45943 | J678: 1347.6667 | K678: =+K677+1 -> 45604 | L678: =+IF(SUMIFS($J$1:$J$1574,$I$1:$I$1574,K678)=0,L677,SUMIFS($J$1:$J$1574,$I$1:$I$1574,K678)) -> 997.25
A679: =+A678+1 -> 45800 | E679: 1170 | F679: =F678+1 -> 45604 | G679: =+IF(SUMIFS($E$2:$E$1575,$A$2:$A$1575,F679)=0,G678,SUMIFS($E$2:$E$1575,$A$2:$A$1575,F679)) -> 1135 | I679: 45944 | J679: 1359.8333 | K679: =+K678+1 -> 45605 | L679: =+IF(SUMIFS($J$1:$J$1574,$I$1:$I$1574,K679)=0,L678,SUMIFS($J$1:$J$1574,$I$1:$I$1574,K679)) -> 997.25
A680: =+A679+1 -> 45801 | E680: 1170 | F680: =F679+1 -> 45605 | G680: =+IF(SUMIFS($E$2:$E$1575,$A$2:$A$1575,F680)=0,G679,SUMIFS($E$2:$E$1575,$A$2:$A$1575,F680)) -> 1135 | I680: 45945 | J680: 1373.5 | K680: =+K679+1 -> 45606 | L680: =+IF(SUMIFS($J$1:$J$1574,$I$1:$I$1574,K680)=0,L679,SUMIFS($J$1:$J$1574,$I$1:$I$1574,K680)) -> 997.25
... A692: =+A691+1 -> 45813 | E692: 1175 | F692: =F691+1 -> 45617 | G692: =+IF(SUMIFS($E$2:$E$1575,$A$2:$A$1575,F692)=0,G691,SUMIFS($E$2:$E$1575,$A$2:$A$1575,F692)) -> 1130 | I692: 45961 | J692: 1443 | K692: =+K691+1 -> 45618 | L692: =+IF(SUMIFS($J$1:$J$1574,$I$1:$I$1574,K692)=0,L691,SUMIFS($J$1:$J$1574,$I$1:$I$1574,K692)) -> 1006.75
A693: =+A692+1 -> 45814 | E693: 1165 | F693: =F692+1 -> 45618 | G693: =+IF(SUMIFS($E$2:$E$1575,$A$2:$A$1575,F693)=0,G692,SUMIFS($E$2:$E$1575,$A$2:$A$1575,F693)) -> 1135 | K693: =+K692+1 -> 45619 | L693: =+IF(SUMIFS($J$1:$J$1574,$I$1:$I$1574,K693)=0,L692,SUMIFS($J$1:$J$1574,$I$1:$I$1574,K693)) -> 1006.75
A694: =+A693+1 -> 45815 | E694: 1165 | F694: =F693+1 -> 45619 | G694: =+IF(SUMIFS($E$2:$E$1575,$A$2:$A$1575,F694)=0,G693,SUMIFS($E$2:$E$1575,$A$2:$A$1575,F694)) -> 1135 | K694: =+K693+1 -> 45620 | L694: =+IF(SUMIFS($J$1:$J$1574,$I$1:$I$1574,K694)=0,L693,SUMIFS($J$1:$J$1574,$I$1:$I$1574,K694)) -> 1006.75
A695: =+A694+1 -> 45816 | E695: 1165 | F695: =F694+1 -> 45620 | G695: =+IF(SUMIFS($E$2:$E$1575,$A$2:$A$1575,F695)=0,G694,SUMIFS($E$2:$E$1575,$A$2:$A$1575,F695)) -> 1135 | K695: =+K694+1 -> 45621 | L695: =+IF(SUMIFS($J$1:$J$1574,$I$1:$I$1574,K695)=0,L694,SUMIFS($J$1:$J$1574,$I$1:$I$1574,K695)) -> 1007.25
A696: =+A695+1 -> 45817 | E696: 1195 | F696: =F695+1 -> 45621 | G696: =+IF(SUMIFS($E$2:$E$1575,$A$2:$A$1575,F696)=0,G695,SUMIFS($E$2:$E$1575,$A$2:$A$1575,F696)) -> 1130 | K696: =+K695+1 -> 45622 | L696: =+IF(SUMIFS($J$1:$J$1574,$I$1:$I$1574,K696)=0,L695,SUMIFS($J$1:$J$1574,$I$1:$I$1574,K696)) -> 1007.75
A697: =+A696+1 -> 45818 | E697: 1190 | F697: =F696+1 -> 45622 | G697: =+IF(SUMIFS($E$2:$E$1575,$A$2:$A$1575,F697)=0,G696,SUMIFS($E$2:$E$1575,$A$2:$A$1575,F697)) -> 1135 | K697: =+K696+1 -> 45623 | L697: =+IF(SUMIFS($J$1:$J$1574,$I$1:$I$1574,K697)=0,L696,SUMIFS($J$1:$J$1574,$I$1:$I$1574,K697)) -> 1008.75
A698: =+A697+1 -> 45819 | E698: 1190 | F698: =F697+1 -> 45623 | G698: =+IF(SUMIFS($E$2:$E$1575,$A$2:$A$1575,F698)=0,G697,SUMIFS($E$2:$E$1575,$A$2:$A$1575,F698)) -> 1125 | K698: =+K697+1 -> 45624 | L698: =+IF(SUMIFS($J$1:$J$1574,$I$1:$I$1574,K698)=0,L697,SUMIFS($J$1:$J$1574,$I$1:$I$1574,K698)) -> 1009.25
A699: =+A698+1 -> 45820 | E699: 1190 | F699: =F698+1 -> 45624 | G699: =+IF(SUMIFS($E$2:$E$1575,$A$2:$A$1575,F699)=0,G698,SUMIFS($E$2:$E$1575,$A$2:$A$1575,F699)) -> 1120 | K699: =+K698+1 -> 45625 | L699: =+IF(SUMIFS($J$1:$J$1574,$I$1:$I$1574,K699)=0,L698,SUMIFS($J$1:$J$1574,$I$1:$I$1574,K699)) -> 1011.75
A700: =+A699+1 -> 45821 | E700: 1190 | F700: =F699+1 -> 45625 | G700: =+IF(SUMIFS($E$2:$E$1575,$A$2:$A$1575,F700)=0,G699,SUMIFS($E$2:$E$1575,$A$2:$A$1575,F700)) -> 1120 | K700: =+K699+1 -> 45626 | L700: =+IF(SUMIFS($J$1:$J$1574,$I$1:$I$1574,K700)=0,L699,SUMIFS($J$1:$J$1574,$I$1:$I$1574,K700)) -> 1011.75
A701: =+A700+1 -> 45822 | E701: 1190 | F701: =F700+1 -> 45626 | G701: =+IF(SUMIFS($E$2:$E$1575,$A$2:$A$1575,F701)=0,G700,SUMIFS($E$2:$E$1575,$A$2:$A$1575,F701)) -> 1120 | K701: =+K700+1 -> 45627 | L701: =+IF(SUMIFS($J$1:$J$1574,$I$1:$I$1574,K701)=0,L700,SUMIFS($J$1:$J$1574,$I$1:$I$1574,K701)) -> 1011.75
A702: =+A701+1 -> 45823 | E702: 1190 | F702: =F701+1 -> 45627 | G702: =+IF(SUMIFS($E$2:$E$1575,$A$2:$A$1575,F702)=0,G701,SUMIFS($E$2:$E$1575,$A$2:$A$1575,F702)) -> 1120 | K702: =+K701+1 -> 45628 | L702: =+IF(SUMIFS($J$1:$J$1574,$I$1:$I$1574,K702)=0,L701,SUMIFS($J$1:$J$1574,$I$1:$I$1574,K702)) -> 1011.9167
A703: =+A702+1 -> 45824 | E703: 1190 | F703: =F702+1 -> 45628 | G703: =+IF(SUMIFS($E$2:$E$1575,$A$2:$A$1575,F703)=0,G702,SUMIFS($E$2:$E$1575,$A$2:$A$1575,F703)) -> 1100 | K703: =+K702+1 -> 45629 | L703: =+IF(SUMIFS($J$1:$J$1574,$I$1:$I$1574,K703)=0,L702,SUMIFS($J$1:$J$1574,$I$1:$I$1574,K703)) -> 1013.1667
A704: =+A703+1 -> 45825 | E704: 1200 | F704: =F703+1 -> 45629 | G704: =+IF(SUMIFS($E$2:$E$1575,$A$2:$A$1575,F704)=0,G703,SUMIFS($E$2:$E$1575,$A$2:$A$1575,F704)) -> 1090 | K704: =+K703+1 -> 45630 | L704: =+IF(SUMIFS($J$1:$J$1574,$I$1:$I$1574,K704)=0,L703,SUMIFS($J$1:$J$1574,$I$1:$I$1574,K704)) -> 1013.25
... A838: =+A837+1 -> 45959 | E838: 1455 | F838: =F837+1 -> 45763 | G838: =+IF(SUMIFS($E$2:$E$1575,$A$2:$A$1575,F838)=0,G837,SUMIFS($E$2:$E$1575,$A$2:$A$1575,F838)) -> 1250 | K838: =+K837+1 -> 45764 | L838: =+IF(SUMIFS($J$1:$J$1574,$I$1:$I$1574,K838)=0,L837,SUMIFS($J$1:$J$1574,$I$1:$I$1574,K838)) -> 1172.8333
F839: =F838+1 -> 45764 | G839: =+IF(SUMIFS($E$2:$E$1575,$A$2:$A$1575,F839)=0,G838,SUMIFS($E$2:$E$1575,$A$2:$A$1575,F839)) -> 1250 | K839: =+K838+1 -> 45765 | L839: =+IF(SUMIFS($J$1:$J$1574,$I$1:$I$1574,K839)=0,L838,SUMIFS($J$1:$J$1574,$I$1:$I$1574,K839)) -> 1172.8333
F840: =F839+1 -> 45765 | G840: =+IF(SUMIFS($E$2:$E$1575,$A$2:$A$1575,F840)=0,G839,SUMIFS($E$2:$E$1575,$A$2:$A$1575,F840)) -> 1250 | K840: =+K839+1 -> 45766 | L840: =+IF(SUMIFS($J$1:$J$1574,$I$1:$I$1574,K840)=0,L839,SUMIFS($J$1:$J$1574,$I$1:$I$1574,K840)) -> 1172.8333
F841: =F840+1 -> 45766 | G841: =+IF(SUMIFS($E$2:$E$1575,$A$2:$A$1575,F841)=0,G840,SUMIFS($E$2:$E$1575,$A$2:$A$1575,F841)) -> 1250 | K841: =+K840+1 -> 45767 | L841: =+IF(SUMIFS($J$1:$J$1574,$I$1:$I$1574,K841)=0,L840,SUMIFS($J$1:$J$1574,$I$1:$I$1574,K841)) -> 1172.8333
F842: =F841+1 -> 45767 | G842: =+IF(SUMIFS($E$2:$E$1575,$A$2:$A$1575,F842)=0,G841,SUMIFS($E$2:$E$1575,$A$2:$A$1575,F842)) -> 1250 | K842: =+K841+1 -> 45768 | L842: =+IF(SUMIFS($J$1:$J$1574,$I$1:$I$1574,K842)=0,L841,SUMIFS($J$1:$J$1574,$I$1:$I$1574,K842)) -> 1070.4167
F843: =F842+1 -> 45768 | G843: =+IF(SUMIFS($E$2:$E$1575,$A$2:$A$1575,F843)=0,G842,SUMIFS($E$2:$E$1575,$A$2:$A$1575,F843)) -> 1150 | K843: =+K842+1 -> 45769 | L843: =+IF(SUMIFS($J$1:$J$1574,$I$1:$I$1574,K843)=0,L842,SUMIFS($J$1:$J$1574,$I$1:$I$1574,K843)) -> 1093.3333
F844: =F843+1 -> 45769 | G844: =+IF(SUMIFS($E$2:$E$1575,$A$2:$A$1575,F844)=0,G843,SUMIFS($E$2:$E$1575,$A$2:$A$1575,F844)) -> 1185 | K844: =+K843+1 -> 45770 | L844: =+IF(SUMIFS($J$1:$J$1574,$I$1:$I$1574,K844)=0,L843,SUMIFS($J$1:$J$1574,$I$1:$I$1574,K844)) -> 1122.5
F845: =F844+1 -> 45770 | G845: =+IF(SUMIFS($E$2:$E$1575,$A$2:$A$1575,F845)=0,G844,SUMIFS($E$2:$E$1575,$A$2:$A$1575,F845)) -> 1210 | K845: =+K844+1 -> 45771 | L845: =+IF(SUMIFS($J$1:$J$1574,$I$1:$I$1574,K845)=0,L844,SUMIFS($J$1:$J$1574,$I$1:$I$1574,K845)) -> 1176.4167
F846: =F845+1 -> 45771 | G846: =+IF(SUMIFS($E$2:$E$1575,$A$2:$A$1575,F846)=0,G845,SUMIFS($E$2:$E$1575,$A$2:$A$1575,F846)) -> 1225 | K846: =+K845+1 -> 45772 | L846: =+IF(SUMIFS($J$1:$J$1574,$I$1:$I$1574,K846)=0,L845,SUMIFS($J$1:$J$1574,$I$1:$I$1574,K846)) -> 1174.1667
F847: =F846+1 -> 45772 | G847: =+IF(SUMIFS($E$2:$E$1575,$A$2:$A$1575,F847)=0,G846,SUMIFS($E$2:$E$1575,$A$2:$A$1575,F847)) -> 1210 | K847: =+K846+1 -> 45773 | L847: =+IF(SUMIFS($J$1:$J$1574,$I$1:$I$1574,K847)=0,L846,SUMIFS($J$1:$J$1574,$I$1:$I$1574,K847)) -> 1174.1667
F848: =F847+1 -> 45773 | G848: =+IF(SUMIFS($E$2:$E$1575,$A$2:$A$1575,F848)=0,G847,SUMIFS($E$2:$E$1575,$A$2:$A$1575,F848)) -> 1210 | K848: =+K847+1 -> 45774 | L848: =+IF(SUMIFS($J$1:$J$1574,$I$1:$I$1574,K848)=0,L847,SUMIFS($J$1:$J$1574,$I$1:$I$1574,K848)) -> 1174.1667
F849: =F848+1 -> 45774 | G849: =+IF(SUMIFS($E$2:$E$1575,$A$2:$A$1575,F849)=0,G848,SUMIFS($E$2:$E$1575,$A$2:$A$1575,F849)) -> 1210 | K849: =+K848+1 -> 45775 | L849: =+IF(SUMIFS($J$1:$J$1574,$I$1:$I$1574,K849)=0,L848,SUMIFS($J$1:$J$1574,$I$1:$I$1574,K849)) -> 1163.1667
F850: =F849+1 -> 45775 | G850: =+IF(SUMIFS($E$2:$E$1575,$A$2:$A$1575,F850)=0,G849,SUMIFS($E$2:$E$1575,$A$2:$A$1575,F850)) -> 1205 | K850: =+K849+1 -> 45776 | L850: =+IF(SUMIFS($J$1:$J$1574,$I$1:$I$1574,K850)=0,L849,SUMIFS($J$1:$J$1574,$I$1:$I$1574,K850)) -> 1170.6667
... F1159: =F1158+1 -> 46084 | G1159: =+IF(SUMIFS($E$2:$E$1575,$A$2:$A$1575,F1159)=0,G1158,SUMIFS($E$2:$E$1575,$A$2:$A$1575,F1159)) -> 1455 | K1159: =+K1158+1 -> 46085 | L1159: =+IF(SUMIFS($J$1:$J$1574,$I$1:$I$1574,K1159)=0,L1158,SUMIFS($J$1:$J$1574,$I$1:$I$1574,K1159)) -> 1443

Sheet RESULTADO_CON_AND
B1: 2025 | C1: 2025 | D1: 2025 | E1: 2025 | F1: 2025 | G1: 2025 | H1: 2025 | I1: 2025 | J1: 2025 | K1: 2025 | L1: 2025 | M1: 2025
B2: ENERO | C2: FEBRERO | D2: MARZO | E2: ABRIL | F2: MAYO | G2: JUNIO | H2: JULIO | I2: AGOSTO | J2: SEPTIEMBRE | K2: OCTUBRE | L2: NOVIEMBRE | M2: DICIEMBRE | O2: PROMEDIO
A3: INGRESOS | B3: 2.417312e+08 | C3: 1.7854281e+08 | D3: 1.1913108e+08 | E3: 1.0126142e+08 | F3: 1.215137e+08 | G3: 1.3366508e+08 | H3: 1.4569493e+08 | I3: 1.3841019e+08 | J3: 1.6609222e+08 | K3: 2.0761528e+08 | L3: 2.595191e+08 | M3: 3.2439887e+08 | O3: 1.7813132e+08
A4: GASTOS GENERALES
A5: COSTOS DE VENTA A DISTRIBUIR | B5: -40582375 | C5: -34161536 | D5: -34196279 | E5: =+AVERAGE(B5/B$3,C5/C$3,D5/D$3)*E$3 -> -21813904 | F5: =+AVERAGE(C5/C$3,D5/D$3,E5/E$3)*F$3 -> -28102249 | G5: =+AVERAGE(D5/D$3,E5/E$3,F5/F$3)*G$3 -> -32691684 | H5: =+AVERAGE(E5/E$3,F5/F$3,G5/G$3)*H$3 -> -33571459 | I5: =+AVERAGE(F5/F$3,G5/G$3,H5/H$3)*I$3 -> -32584997 | J5: =+AVERAGE(G5/G$3,H5/H$3,I5/I$3)*J$3 -> -39332049 | K5: =+AVERAGE(H5/H$3,I5/I$3,J5/J$3)*K$3 -> -48627295 | L5: =+AVERAGE(I5/I$3,J5/J$3,K5/K$3)*L$3 -> -61112439 | M5: =+AVERAGE(J5/J$3,K5/K$3,L5/L$3)*M$3 -> -76397035 | O5: =+AVERAGE(B5:M5) -> -40264442 | P5: =+O5/$O$3 -> -0.22603796
A6: DIRECTORIO | B6: -20595417 | C6: -17198713 | D6: -17467098 | E6: =+AVERAGE(B6/B$3,C6/C$3,D6/D$3)*E$3 -> -11076269 | F6: =+AVERAGE(C6/C$3,D6/D$3,E6/E$3)*F$3 -> -14271054 | G6: =+AVERAGE(D6/D$3,E6/E$3,F6/F$3)*G$3 -> -16638973 | H6: =+AVERAGE(E6/E$3,F6/F$3,G6/G$3)*H$3 -> -17061337 | I6: =+AVERAGE(F6/F$3,G6/G$3,H6/H$3)*I$3 -> -16564457 | J6: =+AVERAGE(G6/G$3,H6/H$3,I6/I$3)*J$3 -> -20000953 | K6: =+AVERAGE(H6/H$3,I6/I$3,J6/J$3)*K$3 -> -24720094 | L6: =+AVERAGE(I6/I$3,J6/J$3,K6/K$3)*L$3 -> -31069988 | M6: =+AVERAGE(J6/J$3,K6/K$3,L6/L$3)*M$3 -> -38842331 | O6: =+AVERAGE(B6:M6) -> -20458890 | P6: =+O6/$O$3 -> -0.11485285
A7: DPTO MKT & DIEÑO | B7: -11687856 | C7: -11046231 | D7: -7163713.5 | E7: =+AVERAGE(B7/B$3,C7/C$3,D7/D$3)*E$3 -> -5750044.4 | F7: =+AVERAGE(C7/C$3,D7/D$3,E7/E$3)*F$3 -> -7241649.6 | G7: =+AVERAGE(D7/D$3,E7/E$3,F7/F$3)*G$3 -> -7864519.9 | H7: =+AVERAGE(E7/E$3,F7/F$3,G7/G$3)*H$3 -> -8509409.5 | I7: =+AVERAGE(F7/F$3,G7/G$3,H7/H$3)*I$3 -> -8158750.1 | J7: =+AVERAGE(G7/G$3,H7/H$3,I7/I$3)*J$3 -> -9754559.8 | K7: =+AVERAGE(H7/H$3,I7/I$3,J7/J$3)*K$3 -> -12185745 | L7: =+AVERAGE(I7/I$3,J7/J$3,K7/K$3)*L$3 -> -15257112 | M7: =+AVERAGE(J7/J$3,K7/K$3,L7/L$3)*M$3 -> -19054497 | O7: =+AVERAGE(B7:M7) -> -10306174 | P7: =+O7/$O$3 -> -0.057857168
A8: GASTOS DE ESTRUCTURA | B8: -6529634.6 | C8: -6100997.5 | D8: -6181121.3 | E8: =+D8 -> -6181121.3 | F8: =+E8 -> -6181121.3 | G8: =+F8 -> -6181121.3 | H8: =+G8 -> -6181121.3 | I8: =+H8 -> -6181121.3 | J8: =+I8 -> -6181121.3 | K8: =+J8 -> -6181121.3 | L8: =+K8 -> -6181121.3 | M8: =+L8 -> -6181121.3 | O8: =+AVERAGE(B8:M8) -> -6203487.1 | P8: =+O8/$O$3 -> -0.034825358
A9: INFRAESTRUCTURA TOL | B9: -5196671.6 | C9: -5695813.6 | D9: -5549771.6 | E9: =+D9 -> -5549771.6 | F9: =+E9 -> -5549771.6 | G9: =+F9 -> -5549771.6 | H9: =+G9 -> -5549771.6 | I9: =+H9 -> -5549771.6 | J9: =+I9 -> -5549771.6 | K9: =+J9 -> -5549771.6 | L9: =+K9 -> -5549771.6 | M9: =+L9 -> -5549771.6 | O9: =+AVERAGE(B9:M9) -> -5532516.8 | P9: =+O9/$O$3 -> -0.031058641
A10: INDEMINIZACIONES | B10: 0 | C10: -4299000 | D10: -4500000 | E10: =+D10 -> -4500000 | F10: =+E10 -> -4500000 | G10: =+F10 -> -4500000 | H10: =+G10 -> -4500000 | I10: =+H10 -> -4500000 | J10: =+I10 -> -4500000 | K10: =+J10 -> -4500000 | L10: =+K10 -> -4500000 | M10: =+L10 -> -4500000 | O10: =+AVERAGE(B10:M10) -> -4108250 | P10: =+O10/$O$3 -> -0.023063041
A11: DPTO ATENCION AL CLIENTE | B11: -2643593.5 | C11: -3442047.2 | D11: -2429543.5 | E11: =+AVERAGE(B11/B$3,C11/C$3,D11/D$3)*E$3 -> -1708229.8 | F11: =+AVERAGE(C11/C$3,D11/D$3,E11/E$3)*F$3 -> -2290206.2 | G11: =+AVERAGE(D11/D$3,E11/E$3,F11/F$3)*G$3 -> -2500012.7 | H11: =+AVERAGE(E11/E$3,F11/F$3,G11/G$3)*H$3 -> -2642924 | I11: =+AVERAGE(F11/F$3,G11/G$3,H11/H$3)*I$3 -> -2569400.1 | J11: =+AVERAGE(G11/G$3,H11/H$3,I11/I$3)*J$3 -> -3067576.4 | K11: =+AVERAGE(H11/H$3,I11/I$3,J11/J$3)*K$3 -> -3818245.8 | L11: =+AVERAGE(I11/I$3,J11/J$3,K11/K$3)*L$3 -> -4794506.9 | M11: =+AVERAGE(J11/J$3,K11/K$3,L11/L$3)*M$3 -> -5983501 | O11: =+AVERAGE(B11:M11) -> -3157482.3 | P11: =+O11/$O$3 -> -0.017725587
A12: DPTO CONTROL DE FRAUDE | B12: -659694.66 | C12: -7035894.7 | D12: -2398303.8 | E12: =+AVERAGE(B12/B$3,C12/C$3,D12/D$3)*E$3 -> -2101782.2 | F12: =+AVERAGE(C12/C$3,D12/D$3,E12/E$3)*F$3 -> -3252312.9 | G12: =+AVERAGE(D12/D$3,E12/E$3,F12/F$3)*G$3 -> -3014264.6 | H12: =+AVERAGE(E12/E$3,F12/F$3,G12/G$3)*H$3 -> -3403038.6 | I12: =+AVERAGE(F12/F$3,G12/G$3,H12/H$3)*I$3 -> -3352901.6 | J12: =+AVERAGE(G12/G$3,H12/H$3,I12/I$3)*J$3 -> -3882823.7 | K12: =+AVERAGE(H12/H$3,I12/I$3,J12/J$3)*K$3 -> -4910737.3 | L12: =+AVERAGE(I12/I$3,J12/J$3,K12/K$3)*L$3 -> -6164008 | M12: =+AVERAGE(J12/J$3,K12/K$3,L12/L$3)*M$3 -> -7653892.4 | O12: =+AVERAGE(B12:M12) -> -3985804.5 | P12: =+O12/$O$3 -> -0.022375652
A13: DPTO ADMINISTRACION | B13: -1940956.9 | C13: -2126277.8 | D13: -1901486.4 | E13: =+AVERAGE(B13/B$3,C13/C$3,D13/D$3)*E$3 -> -1211753.6 | F13: =+AVERAGE(C13/C$3,D13/D$3,E13/E$3)*F$3 -> -1613578.3 | G13: =+AVERAGE(D13/D$3,E13/E$3,F13/F$3)*G$3 -> -1835972.9 | H13: =+AVERAGE(E13/E$3,F13/F$3,G13/G$3)*H$3 -> -1893120.7 | I13: =+AVERAGE(F13/F$3,G13/G$3,H13/H$3)*I$3 -> -1845853.6 | J13: =+AVERAGE(G13/G$3,H13/H$3,I13/I$3)*J$3 -> -2218187.3 | K13: =+AVERAGE(H13/H$3,I13/I$3,J13/J$3)*K$3 -> -2746403.8 | L13: =+AVERAGE(I13/I$3,J13/J$3,K13/K$3)*L$3 -> -3453299.3 | M13: =+AVERAGE(J13/J$3,K13/K$3,L13/L$3)*M$3 -> -4313425.7 | O13: =+AVERAGE(B13:M13) -> -2258359.7 | P13: =+O13/$O$3 -> -0.01267806
A14: DPTO RRHH | B14: -1518752 | C14: -780200 | D14: -1836180 | E14: =+AVERAGE(B14/B$3,C14/C$3,D14/D$3)*E$3 -> -879817.93 | F14: =+AVERAGE(C14/C$3,D14/D$3,E14/E$3)*F$3 -> -1153226.1 | G14: =+AVERAGE(D14/D$3,E14/E$3,F14/F$3)*G$3 -> -1496700.8 | H14: =+AVERAGE(E14/E$3,F14/F$3,G14/G$3)*H$3 -> -1426668 | I14: =+AVERAGE(F14/F$3,G14/G$3,H14/H$3)*I$3 -> -1406250.1 | J14: =+AVERAGE(G14/G$3,H14/H$3,I14/I$3)*J$3 -> -1724567.3 | K14: =+AVERAGE(H14/H$3,I14/I$3,J14/J$3)*K$3 -> -2099362.1 | L14: =+AVERAGE(I14/I$3,J14/J$3,K14/K$3)*L$3 -> -2651852.7 | M14: =+AVERAGE(J14/J$3,K14/K$3,L14/L$3)*M$3 -> -3321121.6 | O14: =+AVERAGE(B14:M14) -> -1691224.9 | P14: =+O14/$O$3 -> -0.0094942587
A15: DPTO IT | B15: -5950313.4 | C15: -2750418.7 | D15: -1072773.5 | E15: =+AVERAGE(B15/B$3,C15/C$3,D15/D$3)*E$3 -> -1654787.5 | F15: =+AVERAGE(C15/C$3,D15/D$3,E15/E$3)*F$3 -> -1650623.3 | G15: =+AVERAGE(D15/D$3,E15/E$3,F15/F$3)*G$3 -> -1734552.3 | H15: =+AVERAGE(E15/E$3,F15/F$3,G15/G$3)*H$3 -> -2083555.9 | I15: =+AVERAGE(F15/F$3,G15/G$3,H15/H$3)*I$3 -> -1885216.5 | J15: =+AVERAGE(G15/G$3,H15/H$3,I15/I$3)*J$3 -> -2264289.4 | K15: =+AVERAGE(H15/H$3,I15/I$3,J15/J$3)*K$3 -> -2875751.2 | L15: =+AVERAGE(I15/I$3,J15/J$3,K15/K$3)*L$3 -> -3555807.4 | M15: =+AVERAGE(J15/J$3,K15/K$3,L15/L$3)*M$3 -> -4453520.2 | O15: =+AVERAGE(B15:M15) -> -2660967.4 | P15: =+O15/$O$3 -> -0.014938234
A16: DPTO COMERCIAL | B16: -968138.29 | C16: -2376307.3 | D16: -1011157.1 | E16: =+AVERAGE(B16/B$3,C16/C$3,D16/D$3)*E$3 -> -870923.93 | F16: =+AVERAGE(C16/C$3,D16/D$3,E16/E$3)*F$3 -> -1231256.7 | G16: =+AVERAGE(D16/D$3,E16/E$3,F16/F$3)*G$3 -> -1212840.1 | H16: =+AVERAGE(E16/E$3,F16/F$3,G16/G$3)*H$3 -> -1350452.6 | I16: =+AVERAGE(F16/F$3,G16/G$3,H16/H$3)*I$3 -> -1313762.9 | J16: =+AVERAGE(G16/G$3,H16/H$3,I16/I$3)*J$3 -> -1541035.5 | K16: =+AVERAGE(H16/H$3,I16/I$3,J16/J$3)*K$3 -> -1940444.6 | L16: =+AVERAGE(I16/I$3,J16/J$3,K16/K$3)*L$3 -> -2432243.1 | M16: =+AVERAGE(J16/J$3,K16/K$3,L16/L$3)*M$3 -> -3027361.2 | O16: =+AVERAGE(B16:M16) -> -1606326.9 | P16: =+O16/$O$3 -> -0.0090176557
A17: AGENTE WEB | B17: -1782607.4 | C17: -707110.08 | D17: -550940.25 | E17: =+AVERAGE(B17/B$3,C17/C$3,D17/D$3)*E$3 -> -538692 | F17: =+AVERAGE(C17/C$3,D17/D$3,E17/E$3)*F$3 -> -563212.85 | G17: =+AVERAGE(D17/D$3,E17/E$3,F17/F$3)*G$3 -> -649587.51 | H17: =+AVERAGE(E17/E$3,F17/F$3,G17/G$3)*H$3 -> -719470.88 | I17: =+AVERAGE(F17/F$3,G17/G$3,H17/H$3)*I$3 -> -665890.93 | J17: =+AVERAGE(G17/G$3,H17/H$3,I17/I$3)*J$3 -> -808814.45 | K17: =+AVERAGE(H17/H$3,I17/I$3,J17/J$3)*K$3 -> -1011700.2 | L17: =+AVERAGE(I17/I$3,J17/J$3,K17/K$3)*L$3 -> -1258981.1 | M17: =+AVERAGE(J17/J$3,K17/K$3,L17/L$3)*M$3 -> -1578074.5 | O17: =+AVERAGE(B17:M17) -> -902923.51 | P17: =+O17/$O$3 -> -0.0050688643
A18: DPTO BI | B18: -373576.14 | C18: -284764.21 | D18: -356936.31 | E18: =+AVERAGE(B18/B$3,C18/C$3,D18/D$3)*E$3 -> -207130.88 | F18: =+AVERAGE(C18/C$3,D18/D$3,E18/E$3)*F$3 -> -268812.86 | G18: =+AVERAGE(D18/D$3,E18/E$3,F18/F$3)*G$3 -> -323196.48 | H18: =+AVERAGE(E18/E$3,F18/F$3,G18/G$3)*H$3 -> -324203.57 | I18: =+AVERAGE(F18/F$3,G18/G$3,H18/H$3)*I$3 -> -316284.88 | J18: =+AVERAGE(G18/G$3,H18/H$3,I18/I$3)*J$3 -> -383579.29 | K18: =+AVERAGE(H18/H$3,I18/I$3,J18/J$3)*K$3 -> -471963.84 | L18: =+AVERAGE(I18/I$3,J18/J$3,K18/K$3)*L$3 -> -594110.53 | M18: =+AVERAGE(J18/J$3,K18/K$3,L18/L$3)*M$3 -> -743086.65 | O18: =+AVERAGE(B18:M18) -> -387303.8 | P18: =+O18/$O$3 -> -0.0021742599
A19: OPERACIONES FINANCIERAS | B19: -327873.2 | C19: -757610.17 | D19: -338809.49 | E19: =+AVERAGE(B19/B$3,C19/C$3,D19/D$3)*E$3 -> -285005.58 | F19: =+AVERAGE(C19/C$3,D19/D$3,E19/E$3)*F$3 -> -401070.37 | G19: =+AVERAGE(D19/D$3,E19/E$3,F19/F$3)*G$3 -> -399176.34 | H19: =+AVERAGE(E19/E$3,F19/F$3,G19/G$3)*H$3 -> -442017.2 | I19: =+AVERAGE(F19/F$3,G19/G$3,H19/H$3)*I$3 -> -430034.21 | J19: =+AVERAGE(G19/G$3,H19/H$3,I19/I$3)*J$3 -> -505319.06 | K19: =+AVERAGE(H19/H$3,I19/I$3,J19/J$3)*K$3 -> -635524.89 | L19: =+AVERAGE(I19/I$3,J19/J$3,K19/K$3)*L$3 -> -796760.43 | M19: =+AVERAGE(J19/J$3,K19/K$3,L19/L$3)*M$3 -> -991969.82 | O19: =+AVERAGE(B19:M19) -> -525930.9 | P19: =+O19/$O$3 -> -0.0029524897
A20: PAGINAS VEB | B20: -142238 | C20: -373746 | D20: -108580 | E20: =+AVERAGE(B20/B$3,C20/C$3,D20/D$3)*E$3 -> -121282.83 | F20: =+AVERAGE(C20/C$3,D20/D$3,E20/E$3)*F$3 -> -170219.07 | G20: =+AVERAGE(D20/D$3,E20/E$3,F20/F$3)*G$3 -> -156387.02 | H20: =+AVERAGE(E20/E$3,F20/F$3,G20/G$3)*H$3 -> -183018.75 | I20: =+AVERAGE(F20/F$3,G20/G$3,H20/H$3)*I$3 -> -176564.87 | J20: =+AVERAGE(G20/G$3,H20/H$3,I20/I$3)*J$3 -> -204948.58 | K20: =+AVERAGE(H20/H$3,I20/I$3,J20/J$3)*K$3 -> -260611.58 | L20: =+AVERAGE(I20/I$3,J20/J$3,K20/K$3)*L$3 -> -325685.26 | M20: =+AVERAGE(J20/J$3,K20/K$3,L20/L$3)*M$3 -> -404867.45 | O20: =+AVERAGE(B20:M20) -> -219012.45 | P20: =+O20/$O$3 -> -0.0012294999
A21: PAGINAS AND | B21: 0 | C21: -52216 | D21: -10539.5 | E21: =+AVERAGE(B21/B$3,C21/C$3,D21/D$3)*E$3 -> -12857.711 | F21: =+AVERAGE(C21/C$3,D21/D$3,E21/E$3)*F$3 -> -20572.337 | G21: =+AVERAGE(D21/D$3,E21/E$3,F21/F$3)*G$3 -> -17142.356 | H21: =+AVERAGE(E21/E$3,F21/F$3,G21/G$3)*H$3 -> -20617.025 | I21: =+AVERAGE(F21/F$3,G21/G$3,H21/H$3)*I$3 -> -20256.668 | J21: =+AVERAGE(G21/G$3,H21/H$3,I21/I$3)*J$3 -> -23037.501 | K21: =+AVERAGE(H21/H$3,I21/I$3,J21/J$3)*K$3 -> -29520.379 | L21: =+AVERAGE(I21/I$3,J21/J$3,K21/K$3)*L$3 -> -36959.274 | M21: =+AVERAGE(J21/J$3,K21/K$3,L21/L$3)*M$3 -> -45773.268 | O21: =+AVERAGE(B21:M21) -> -24124.335 | P21: =+O21/$O$3 -> -0.00013543005
A22: TOL-CTAS CTES | B22: 0 | C22: 0 | D22: -6033.06 | E22: =+AVERAGE(B22/B$3,C22/C$3,D22/D$3)*E$3 -> -1709.367 | F22: =+AVERAGE(C22/C$3,D22/D$3,E22/E$3)*F$3 -> -2734.9872 | G22: =+AVERAGE(D22/D$3,E22/E$3,F22/F$3)*G$3 -> -4011.3146 | H22: =+AVERAGE(E22/E$3,F22/F$3,G22/G$3)*H$3 -> -3370.3399 | I22: =+AVERAGE(F22/F$3,G22/G$3,H22/H$3)*I$3 -> -3490.2754 | J22: =+AVERAGE(G22/G$3,H22/H$3,I22/I$3)*J$3 -> -4338.3258 | K22: =+AVERAGE(H22/H$3,I22/I$3,J22/J$3)*K$3 -> -5153.6849 | L22: =+AVERAGE(I22/I$3,J22/J$3,K22/K$3)*L$3 -> -6588.3356 | M22: =+AVERAGE(J22/J$3,K22/K$3,L22/L$3)*M$3 -> -8253.7816 | O22: =+AVERAGE(B22:M22) -> -3806.956 | P22: =+O22/$O$3 -> -2.1371626e-05
A23: INVERSION IT - INVESTIG & DESA | B23: -237128.53 | C23: -241247.02 | D23: 0 | E23: =+AVERAGE(B23/B$3,C23/C$3,D23/D$3)*E$3 -> -78719.258 | F23: =+AVERAGE(C23/C$3,D23/D$3,E23/E$3)*F$3 -> -86217.469 | G23: =+AVERAGE(D23/D$3,E23/E$3,F23/F$3)*G$3 -> -66249.545 | H23: =+AVERAGE(E23/E$3,F23/F$3,G23/G$3)*H$3 -> -96282.673 | I23: =+AVERAGE(F23/F$3,G23/G$3,H23/H$3)*I$3 -> -86091.984 | J23: =+AVERAGE(G23/G$3,H23/H$3,I23/I$3)*J$3 -> -98464.771 | K23: =+AVERAGE(H23/H$3,I23/I$3,J23/J$3)*K$3 -> -129807.25 | L23: =+AVERAGE(I23/I$3,J23/J$3,K23/K$3)*L$3 -> -159177.58 | M23: =+AVERAGE(J23/J$3,K23/K$3,L23/L$3)*M$3 -> -198036.6 | O23: =+AVERAGE(B23:M23) -> -123118.56 | P23: =+O23/$O$3 -> -0.00069116736
A24: GASTOS EN RRHH | B24: =+SUM(B25:B30) -> -57487011 | C24: =+SUM(C25:C30) -> -57474484 | D24: =+SUM(D25:D30) -> -56333777 | E24: =+SUM(E25:E30) -> -57098424 | F24: =+SUM(F25:F30) -> -56968895 | G24: =+SUM(G25:G30) -> -85200549 | H24: =+SUM(H25:H30) -> -66422623 | I24: =+SUM(I25:I30) -> -69530689 | ... M24: =+SUM(M25:M30) -> -71551577
A25: DPTO IT | B25: -24682861 | C25: -24550185 | D25: -23758217 | E25: =+AVERAGE(B25:D25) -> -24330421 | F25: =+AVERAGE(C25:E25) -> -24212941 | G25: =+AVERAGE(D25:F25)*1.5 -> -36150789 | H25: =+AVERAGE(E25:G25) -> -28231384 | I25: =+AVERAGE(F25:H25) -> -29531705 | J25: =+AVERAGE(G25:I25) -> -31304626 | K25: =+AVERAGE(H25:J25) -> -29689238 | L25: =+AVERAGE(I25:K25) -> -30175189 | M25: =+AVERAGE(J25:L25) -> -30389684 | O25: =+AVERAGE(B25:M25) -> -28083937 | P25: =+O25/$O$3 -> -0.15765861
A26: DPTO ATENCION AL CLIENTE | B26: -10570030 | C26: -11160003 | D26: -11758779 | E26: =+AVERAGE(B26:D26) -> -11162937 | F26: =+AVERAGE(C26:E26) -> -11360573 | G26: =+AVERAGE(D26:F26)*1.5 -> -17141145 | H26: =+AVERAGE(E26:G26) -> -13221552 | I26: =+AVERAGE(F26:H26) -> -13907757 | J26: =+AVERAGE(G26:I26) -> -14756818 | K26: =+AVERAGE(H26:J26) -> -13962042 | L26: =+AVERAGE(I26:K26) -> -14208872 | M26: =+AVERAGE(J26:L26) -> -14309244 | O26: =+AVERAGE(B26:M26) -> -13126646 | P26: =+O26/$O$3 -> -0.073690835
A27: DPTO ADMINISTRACION | B27: -9317433.8 | C27: -8927869.2 | D27: -9000105 | E27: =+AVERAGE(B27:D27) -> -9081802.7 | F27: =+AVERAGE(C27:E27) -> -9003259 | G27: =+AVERAGE(D27:F27)*1.5 -> -13542583 | H27: =+AVERAGE(E27:G27) -> -10542548 | I27: =+AVERAGE(F27:H27) -> -11029464 | J27: =+AVERAGE(G27:I27) -> -11704865 | K27: =+AVERAGE(H27:J27) -> -11092292 | L27: =+AVERAGE(I27:K27) -> -11275540 | M27: =+AVERAGE(J27:L27) -> -11357566 | O27: =+AVERAGE(B27:M27) -> -10489611 | P27: =+O27/$O$3 -> -0.058886952
A28: DPTO BI | B28: -6314338.4 | C28: -5844726.6 | D28: -6042990.3 | E28: =+AVERAGE(B28:D28) -> -6067351.8 | F28: =+AVERAGE(C28:E28) -> -5985022.9 | G28: =+AVERAGE(D28:F28)*1.5 -> -9047682.5 | H28: =+AVERAGE(E28:G28) -> -7033352.4 | I28: =+AVERAGE(F28:H28) -> -7355352.6 | J28: =+AVERAGE(G28:I28) -> -7812129.1 | K28: =+AVERAGE(H28:J28) -> -7400278 | L28: =+AVERAGE(I28:K28) -> -7522586.6 | M28: =+AVERAGE(J28:L28) -> -7578331.3 | O28: =+AVERAGE(B28:M28) -> -7000345.2 | P28: =+O28/$O$3 -> -0.039298788
A29: DPTO MKT & DIEÑO | B29: -3788760.7 | C29: -4080128.2 | D29: -3006010.2 | E29: =+AVERAGE(B29:D29) -> -3624966.4 | F29: =+AVERAGE(C29:E29) -> -3570368.2 | G29: =+AVERAGE(D29:F29)*1.5 -> -5100672.4 | H29: =+AVERAGE(E29:G29) -> -4098669 | I29: =+AVERAGE(F29:H29) -> -4256569.9 | J29: =+AVERAGE(G29:I29) -> -4485303.8 | K29: =+AVERAGE(H29:J29) -> -4280180.9 | L29: =+AVERAGE(I29:K29) -> -4340684.8 | M29: =+AVERAGE(J29:L29) -> -4368723.2 | O29: =+AVERAGE(B29:M29) -> -4083419.8 | P29: =+O29/$O$3 -> -0.022923648
A30: DPTO COMERCIAL | B30: -2813587.2 | C30: -2911572.4 | D30: -2767676.2 | E30: =+AVERAGE(B30:D30) -> -2830945.3 | F30: =+AVERAGE(C30:E30) -> -2836731.3 | G30: =+AVERAGE(D30:F30)*1.5 -> -4217676.4 | H30: =+AVERAGE(E30:G30) -> -3295117.7 | I30: =+AVERAGE(F30:H30) -> -3449841.8 | J30: =+AVERAGE(G30:I30) -> -3654212 | K30: =+AVERAGE(H30:J30) -> -3466390.5 | L30: =+AVERAGE(I30:K30) -> -3523481.4 | M30: =+AVERAGE(J30:L30) -> -3548027.9 | O30: =+AVERAGE(B30:M30) -> -3276271.7 | P30: =+O30/$O$3 -> -0.018392451
A31: COSTOS DE VENTA A DISTRIBUIR | B31: 1044355 | C31: 1095277.9 | D31: 1069735.6 | E31: =+AVERAGE(B31:D31) -> 1069789.5 | F31: =+AVERAGE(C31:E31) -> 1078267.7 | G31: =+AVERAGE(D31:F31)*1.5 -> 1608896.4 | H31: =+AVERAGE(E31:G31) -> 1252317.9 | I31: =+AVERAGE(F31:H31) -> 1313160.7 | J31: =+AVERAGE(G31:I31) -> 1391458.3 | K31: =+AVERAGE(H31:J31) -> 1318979 | L31: =+AVERAGE(I31:K31) -> 1341199.3 | M31: =+AVERAGE(J31:L31) -> 1350545.5 | O31: =+AVERAGE(B31:M31) -> 1244498.6 | P31: =+O31/$O$3 -> 0.0069864106
A32: GANANCIA | B32: =SUM(B3:B31) -> 26664709 | C32: =SUM(C3:C31) -> -34741009 | D32: =SUM(D3:D31) -> -79546003 | E32: =SUM(E3:E31) -> -76409441 | F32: =SUM(F3:F31) -> -69895707 | G32: =SUM(G3:G31) -> -1.2196329e+08 | H32: =SUM(H3:H31) -> -75859834 | I32: =SUM(I3:I31) -> -86949127 | ... M32: =SUM(M3:M31) -> -601375.42 | O32: =+AVERAGE(B32:M32) -> -57164784 | P32: =+O32/$O$3 -> -0.32091371

Sheet 2024
B1: 2024 | C1: 2024 | D1: 2024 | E1: 2024 | F1: 2024 | G1: 2024 | H1: 2024 | I1: 2024 | J1: 2024 | K1: 2024 | L1: 2024 | M1: 2024
B2: 0.033628754 | C2: 0.017511072 | D2: 0.014272701 | E2: -0.0076195206 | F2: -0.0050787205 | G2: -0.0046534094 | H2: 0.0094810878 | I2: -0.0084668681 | J2: 0.0061080789 | K2: 0.018908852 | L2: 0.020338533 | M2: 0.026965297 | N2: 0.014151142
A3: RESULTADO VEB 2024 | B3: ENERO | C3: FEBRERO | D3: MARZO | E3: ABRIL | F3: MAYO | G3: JUNIO | H3: JULIO | I3: AGOSTO | J3: SEPTIEMBRE | K3: OCTUBRE | L3: NOVIEMBRE | M3: DICIEMBRE | N3: 2024 | Q3: INTERANUAL | S3: COMENTARIOS RODRIGO
A4: VENTA COMISIONABLE | B4: 2.2696654e+09 | C4: 1.7520975e+09 | D4: 1.6126006e+09 | E4: 1.1348092e+09 | F4: 1.2330754e+09 | G4: 1.4957877e+09 | H4: 1.9206542e+09 | I4: 1.5704689e+09 | J4: 1.8922874e+09 | K4: 2.2829359e+09 | L4: 3.0566906e+09 | M4: 4.3850078e+09 | N4: 2.4606081e+10 | Q4: 1.7093349 | R4: VENTA COMISIONABLE | S4: BAJA PAGINAS VEB
A5: TOTAL INGRESOS | B5: 1.3352809e+08 | C5: 97324729 | D5: 86992578 | E5: 56571477 | F5: 58501406 | G5: 77816766 | H5: 95987874 | I5: 78591406 | J5: 1.0327646e+08 | K5: 1.2668149e+08 | L5: 1.7189494e+08 | M5: 2.6132399e+08 | N5: 1.3484912e+09 | Q5: 1.6186259 | R5: TOTAL INGRESOS | S5: BAJA PAGINAS VEB
A6: INGRESOS SOBRE VENTA COMISIONABLE | B6: 0.05883162 | C6: 0.055547552 | D6: 0.053945521 | E6: 0.049851092 | F6: 0.047443493 | G6: 0.052023939 | H6: 0.049976656 | I6: 0.050043275 | J6: 0.054577576 | K6: 0.055490603 | L6: 0.056235635 | M6: 0.059594875 | N6: 0.05480317 | Q6: -0.033480173 | R6: INGRESOS SOBRE VENTA COMISIONABLE
A7: EGRESOS OPERATIVOS | O7: sobre ing | P7: sobre gtos | R7: EGRESOS OPERATIVOS
A8: RRHH | B8: -24291492 | C8: -30217543 | D8: -31171174 | E8: -31083737 | F8: -32687555 | G8: -51388071 | H8: -38539960 | I8: -39418181 | J8: -40190764 | K8: -43108886 | L8: -47717062 | M8: -74375564 | N8: -4.8418999e+08 | O8: -0.35906055 | P8: 0.42890847 | Q8: 1.8880015 | R8: RRHH | S8: POSICIONES NUEVAS DE TERESA Y AGUSTINA
A9: DIRECTORIO | B9: -8471794.9 | C9: -8701517.8 | D9: -8808647.6 | E9: -8797658.5 | F9: -10573683 | G9: -9646721.5 | H9: -5440810 | I9: -16310249 | J9: -20536980 | K9: -4614577.8 | L9: -21899742 | M9: -22678566 | N9: -1.4648095e+08 | O9: -0.10862581 | P9: 0.12975675 | Q9: 1.2539 | R9: DIRECTORIO
A10: COSTOS DE VENTA A DISTRIBUIR | B10: -11540611 | C10: -13593392 | D10: -8418260.6 | E10: -7484380.5 | F10: -6965215.1 | G10: -6228872.6 | H10: -10544287 | I10: -8286177.3 | J10: -9812841.2 | K10: -13330008 | L10: -15302258 | M10: -21366066 | N10: -1.3287237e+08 | O10: -0.098534101 | P10: 0.11770191 | Q10: 2.0742294 | R10: COSTOS DE VENTA A DISTRIBUIR
A11: INFRAESTRUCTURA TOL | B11: -3441130.2 | C11: -3972352.3 | D11: -3777237.1 | E11: -3598087.2 | F11: -3661852.5 | G11: -4377757.3 | H11: -5637599.2 | I11: -5233140.8 | J11: -5046540.3 | K11: -4467666.5 | L11: -5853092.7 | M11: -4656623.2 | N11: -53723079 | O11: -0.039839399 | P11: 0.047589343 | Q11: 2.0783726 | R11: INFRAESTRUCTURA TOL | S11: INCREMENTO COSTOS EN DOLARES
A12: GASTOS DE ESTRUCTURA | B12: -3740040.6 | C12: -2799135.1 | D12: -3204134.4 | E12: -4409076.8 | F12: -3262054.8 | G12: -3746792.3 | H12: -8853475 | I12: -13125997 | J12: -6554856 | K12: -6320237.7 | L12: -10507316 | M12: -7973720.1 | N12: -74496836 | O12: -0.055244584 | P12: 0.065991294 | Q12: 3.5357828 | R12: GASTOS DE ESTRUCTURA | S12: INCREMENTO ALQUILER Y MEJORAS OFICINAS
A13: DPTO MKT & DIEÑO | B13: -431011.75 | C13: -885299.54 | D13: -701579.53 | E13: -1302063.8 | F13: -599506.85 | G13: -977447.55 | H13: -795896.61 | I13: -973466.69 | J13: -522018.22 | K13: -528142.78 | L13: -661486.52 | M13: -652466.03 | N13: -9030385.8 | O13: -0.0066966591 | P13: 0.0079993578 | Q13: 10.614443 | R13: DPTO MKT & DIEÑO | S13: INVERSIONES MKT UNIBUS
A14: DPTO ATENCION AL CLIENTE/FRAUDE | B14: -1443327.1 | C14: -1220377.9 | D14: -1602507.2 | E14: -1576449.4 | F14: -794659.05 | G14: -2258687 | H14: -2144726.7 | I14: -1852751.1 | J14: -2045617.1 | K14: -2110835.1 | L14: -2033936 | M14: -2040360.8 | N14: -21124234 | O14: -0.015665089 | P14: 0.018712413 | Q14: 3.1400062 | R14: DPTO ATENCION AL CLIENTE/FRAUDE | S14: ZENDESK
A15: DPTO ADMINISTRACION | B15: -763879.26 | C15: -1011702.8 | D15: -1302825.5 | E15: -1359719.2 | F15: -1364305.2 | G15: -1377759 | H15: -1541980.7 | I15: -1620976.7 | J15: -1735646.7 | K15: -1920911.4 | L15: -1944676.4 | M15: -2030847.1 | N15: -17975230 | O15: -0.013329883 | P15: 0.01592294 | Q15: 2.130537 | R15: DPTO ADMINISTRACION
A16: CONTRACARGOS POR FRAUDE | B16: -892298.03 | C16: -1031809.7 | D16: -1485703.5 | E16: -785158.85 | F16: -1276341.6 | G16: -410577.34 | H16: -1661181.9 | I16: -1494518.6 | J16: -902669 | K16: -1443021.4 | L16: -913089.4 | M16: -526849.81 | N16: -12823219 | O16: -0.0095093087 | P16: 0.011359151 | Q16: 1.1194304 | R16: CONTRACARGOS POR FRAUDE
A17: DPTO IT | B17: -424010.41 | C17: -568019.88 | D17: -455385.53 | E17: -1300261.2 | F17: -1454453 | G17: -1494752.1 | H17: -721171.49 | I17: -543103.78 | J17: -1230381.6 | K17: -3390669 | L17: -1248848.3 | M17: -2850681.7 | N17: -15681738 | O17: -0.011629099 | P17: 0.013891304 | Q17: 3.9427761 | R17: DPTO IT | S17: INCREMENTO COSTOS EN DOLARES
A18: PAGINAS VEB | B18: -444896.33 | C18: -738065.46 | D18: -210388.34 | E18: -101619.24 | F18: -298390.22 | G18: -101689.16 | H18: -98637.97 | I18: -135880.21 | J18: 0 | K18: 0 | L18: 0 | M18: -77329 | N18: -2206895.9 | O18: -0.0016365668 | P18: 0.0019549276 | Q18: 0.54077704 | R18: PAGINAS VEB
A19: DPTO BI | B19: -125767.76 | C19: -164508.58 | D19: -1075244.8 | E19: -1392460.8 | F19: 129681.12 | G19: -219751.91 | H19: -279866.79 | I19: -226965.37 | J19: -751603.42 | K19: -459349.78 | L19: -348613.24 | M19: -363037.8 | N19: -5277489.1 | O19: -0.0039136252 | P19: 0.0046749413 | Q19: 1.1126081 | R19: DPTO BI
A20: DPTO RRHH | B20: -35801.47 | C20: -380961.77 | D20: -439400 | E20: -510000 | F20: -529800 | G20: -550800 | H20: -590000 | I20: -620500 | J20: -1350446.3 | K20: -706000 | L20: 0 | M20: -917983.91 | N20: -6631693.4 | O20: -0.0049178618 | P20: 0.0058745318 | Q20: 0.98820611 | R20: DPTO RRHH
A21: AGENTE WEB | B21: -171502.48 | C21: -261608.43 | D21: -186606.45 | E21: -432468.53 | F21: -134590.74 | G21: -182734.55 | H21: -44479.5 | I21: -399035.37 | J21: -147704.71 | K21: -237687.36 | L21: -298685.37 | M21: -437171.49 | N21: -2934275 | O21: -0.0021759689 | P21: 0.0025992594 | Q21: -0.42928803 | R21: AGENTE WEB
A22: DPTO COMERCIAL | B22: -870371.11 | C22: -979352.41 | D22: -1103814.6 | E22: -1042400.1 | F22: -1159602.1 | G22: -715657.31 | H22: -883910.24 | I22: -1358076.2 | J22: -824933.97 | K22: -806675.79 | L22: -925651.41 | M22: -1151389.3 | N22: -11821835 | O22: -0.0087667124 | P22: 0.010472098 | Q22: 1.300269 | R22: DPTO COMERCIAL
A23: OTROS CC | B23: -114139.77 | C23: -117975.74 | D23: -33503.44 | E23: -42637.77 | F23: -131523.78 | G23: -53812.04 | H23: 0 | I23: -289338.74 | J23: -65215.26 | K23: -69122.44 | L23: -71877.11 | M23: -74938.75 | N23: -1064084.8 | O23: -0.0007890929 | P23: 0.00094259487 | Q23: 0.031553941 | R23: OTROS CC
A24: SABRE | B24: 0 | C24: 0 | D24: 0 | E24: 0 | F24: 0 | G24: -1045395.5 | H24: 0 | I24: 0 | J24: 0 | K24: 0 | L24: 0 | M24: -907357.89 | N24: -1952753.4 | O24: -0.0014481024 | P24: 0.0017298013 | R24: SABRE
A25: TOTAL EGRESOS | B25: -57202073 | C25: -66643622 | D25: -63976412 | E25: -65218178 | F25: -64763852 | G25: -84777279 | H25: -77777983 | I25: -91888359 | J25: -91718218 | K25: -83513792 | L25: -1.0972634e+08 | M25: -1.4308095e+08 | N25: -1.0002871e+09 | Q25: 1.8647879 | R25: TOTAL EGRESOS OPERATIVOS
A26: EGRESOS SOBRE INGRESOS | B26: -0.42838981 | C26: -0.68475528 | D26: -0.7354238 | E26: -1.1528456 | F26: -1.1070478 | G26: -1.0894475 | H26: -0.81028967 | I26: -1.1691909 | J26: -0.88808446 | K26: -0.65924226 | L26: -0.63833372 | M26: -0.54752322 | N26: -0.74178241 | Q26: 0.094004267 | R26: EGRESOS SOBRE INGRESOS
A27: RESULTADO OPERATIVO SIN GTOS EXTRAORDINARIOS | B27: 76326019 | C27: 30681107 | D27: 23016166 | E27: -8646702 | F27: -6262445.5 | G27: -6960512.4 | H27: 18209891 | I27: -13296953 | J27: 11558241 | K27: 43167698 | L27: 62168602 | M27: 1.1824304e+08 | N27: 3.4820415e+08 | O27: 0.25821759 | P27: RENTABILIDAD ANTES DE GASTOS EXTRAORDINARIOS | Q27: 1.1002065 | R27: RESULTADO OPERATIVO SIN GTOS EXTRAORDINARIOS
A28: INVERSION_PUBLICIDAD | B28: -5376837 | C28: -7501135.3 | D28: -3715295.6 | E28: -3725672.2 | F28: -4450068.1 | G28: -6962577.1 | H28: -6394916.7 | I28: -6002642.5 | J28: -5243982.3 | K28: -6372827.8 | L28: -8761148.7 | M28: -9138704.4 | N28: -73645808 | O28: -0.054613488 | P28: 0.06523743 | Q28: 2.5485363 | R28: INVERSION_PUBLICIDAD | S28: GOOGLE
A29: BONOS RRHH | B29: 0 | C29: 0 | D29: -2626000 | E29: 0 | F29: 0 | G29: -24264000 | H29: 0 | I29: 0 | J29: 0 | K29: 0 | L29: 0 | M29: 0 | N29: -26890000 | O29: -0.019940805 | P29: 0.023819883 | R29: BONOS RRHH | S29: BONOS 2023
A30: PERDIDA DIPUTADOS | B30: 0 | C30: 0 | D30: 0 | E30: 0 | F30: 0 | G30: 0 | H30: -1082990 | I30: 0 | J30: 0 | K30: 0 | L30: 0 | M30: 0 | N30: -1082990 | O30: -0.00080311239 | P30: 0.00095934157 | R30: PERDIDA DIPUTADOS
A31: INVERSION_EQUIPOS | B31: -710226.24 | C31: -77685.95 | D31: 0 | E31: -961486.98 | F31: -404437.98 | G31: -696832.58 | H31: -820521.68 | I31: -19421.49 | J31: -1763060.4 | K31: -3011587.3 | L31: -1059994.4 | M31: -791179.11 | N31: -10316434 | O31: -0.0076503533 | P31: 0.0091385738 | Q31: 2.317037 | R31: INVERSION_EQUIPOS
A32: INVERSION_MEJORAS_TOL | B32: -17878.5 | C32: 0 | D32: 0 | E32: -2661304.1 | F32: -452250 | G32: 0 | H32: -945037.01 | I32: 0 | J32: 0 | K32: -777253.32 | L32: -69642.44 | M32: -6133198.6 | N32: -11056564 | O32: -0.008199211 | P32: 0.0097942007 | Q32: 3.3049121 | R32: INVERSION_TOLPOS
A33: INDEMNIZACIONES | B33: -600000 | C33: -600000 | D33: -600000 | E33: -600000 | F33: -600000 | G33: 0 | H33: 0 | I33: 0 | J33: 0 | K33: 0 | L33: 0 | M33: -2610000 | N33: -5610000 | O33: -0.0041602051 | P33: 0.0049694884 | Q33: 1.6080783 | R33: INDEMNIZACIONES
A34: RESULTADO OPERATIVO TOTAL | B34: 69621077 | C34: 22502285 | D34: 16074871 | E34: -16595165 | F34: -12169202 | G34: -38883922 | H34: 8966425.8 | I34: -19319017 | J34: 4551198 | K34: 33006029 | L34: 52277816 | M34: 99569958 | N34: 2.1960235e+08 | O34: 0.16285042 | P34: RENTABILIDAD ANTES DE INGRESOS FINANCIEROS | Q34: 0.77596234 | R34: RESULTADO OPERATIVO TOTAL
A35: GANANCIAS FINANCIERAS | B35: 6563302.9 | C35: 5535124.3 | D35: 4808362.1 | E35: 5760722.7 | F35: 4197081.6 | G35: 2638454.8 | H35: 2763735.5 | I35: 6569873.8 | J35: 9961312.6 | K35: 3497798.6 | L35: 6192350.3 | M35: 4807252.7 | N35: 63295372 | Q35: -0.13003504 | R35: GANANCIAS FINANCIERAS | S35: FIMAS + LEY ECONOMIA DEL CONOCIMIENTO
A36: RESULTADO ANTES DE IMPUESTOS | B36: 76184380 | C36: 28037410 | D36: 20883233 | E36: -10834443 | F36: -7972120 | G36: -36245467 | H36: 11730161 | I36: -12749143 | J36: 14512511 | K36: 36503828 | L36: 58470166 | M36: 1.0437721e+08 | N36: 2.8289773e+08 | Q36: 0.44035138 | R36: RESULTADO ANTES DE IMPUESTOS
B38: CUENTA FINANCIERA | M38: 4070000000
B39: RDO | C39: 2.8289773e+08 | E39: 244600000 | F39: BANCOS | M39: 1276366000 | N39: 84869318
B40: ENE | C40: 1.8861601e+08 | E40: 78200000 | F40: TRANSPORTISTAS A COBRAR | M40: 5346366000 | N40: 33947727
E41: 290000000 | F41: FIMAS | M41: 3.1861601e+08 | N41: 50921591
E42: 67700000 | F42: NARANJA | M42: -120000000
E43: 80000000 | F43: CTAS CTES A COBRAR | M43: -15000000
E44: -315500000 | F44: TRANSPORTISTAS A PAGAR | M44: 5000000
E45: 91986000 | F45: BOFA + cajas | M45: 1.8861601e+08
E46: -62000000 | F46: IVA POSTDATADO
C47: 4.7151374e+08 | E47: 474986000
B52: ENERO | C52: FEBRERO | D52: MARZO | E52: ABRIL | F52: MAYO | G52: JUNIO | H52: JULIO | I52: AGOSTO | J52: SEPTIEMBRE | K52: OCTUBRE | L52: NOVIEMBRE | M52: DICIEMBRE | N52: 2024
A53: RRHH | B53: -0.18192046 | C53: -0.31048166 | D53: -0.35831992 | E53: -0.54945953 | F53: -0.5587482 | G53: -0.66037274 | H53: -0.40150863 | I53: -0.50155842 | J53: -0.38915707 | K53: -0.34029349 | L53: -0.27759434 | M53: -0.28461054 | N53: -0.35906055 | O53: #DIV/0!
A54: DIRECTORIO | B54: -0.063445787 | C54: -0.089407059 | D54: -0.10125746 | E54: -0.15551403 | F54: -0.18074237 | G54: -0.12396713 | H54: -0.056682264 | I54: -0.20753223 | J54: -0.19885442 | K54: -0.036426614 | L54: -0.1274019 | M54: -0.086783329 | N54: -0.10862581 | O54: #DIV/0!
A55: COSTOS DE VENTA A DISTRIBUIR | B55: -0.086428334 | C55: -0.13967048 | D55: -0.096769871 | E55: -0.13229954 | F55: -0.11906064 | G55: -0.080045379 | H55: -0.10985019 | I55: -0.10543363 | J55: -0.095015276 | K55: -0.1052246 | L55: -0.089020995 | M55: -0.081760828 | N55: -0.098534101 | O55: #DIV/0!
A56: INFRAESTRUCTURA TOL | B56: -0.025770833 | C56: -0.040815447 | D56: -0.043420222 | E56: -0.063602497 | F56: -0.062594264 | G56: -0.05625725 | H56: -0.05873241 | I56: -0.06658668 | J56: -0.048864382 | K56: -0.035266924 | L56: -0.034050407 | M56: -0.017819348 | N56: -0.039839399 | O56: #DIV/0!
A57: GASTOS DE ESTRUCTURA | B57: -0.028009391 | C57: -0.028760779 | D57: -0.036832273 | E57: -0.07793816 | F57: -0.05576028 | G57: -0.048148907 | H57: -0.092235348 | I57: -0.16701568 | J57: -0.063469024 | K57: -0.049890775 | L57: -0.061126385 | M57: -0.030512775 | N57: -0.055244584 | O57: #DIV/0!
A58: DPTO MKT & DIEÑO | B58: -0.0032278732 | C58: -0.0090963474 | D58: -0.0080648205 | E58: -0.023016259 | F58: -0.010247734 | G58: -0.012560886 | H58: -0.008291637 | I58: -0.012386427 | J58: -0.0050545713 | K58: -0.0041690604 | L58: -0.0038482025 | M58: -0.0024967705 | N58: -0.0066966591 | O58: #DIV/0!
A59: DPTO ATENCION AL CLIENTE/FRAUDE | B59: -0.010809164 | C59: -0.012539238 | D59: -0.018421195 | E59: -0.027866506 | F59: -0.013583589 | G59: -0.029025712 | H59: -0.022343725 | I59: -0.023574474 | J59: -0.019807197 | K59: -0.016662538 | L59: -0.011832437 | M59: -0.0078077821 | N59: -0.015665089 | O59: #DIV/0!
A60: DPTO ADMINISTRACION | B60: -0.0057207382 | C60: -0.010395126 | D60: -0.014976284 | E60: -0.02403542 | F60: -0.023320896 | G60: -0.017705169 | H60: -0.016064328 | I60: -0.020625368 | J60: -0.016805831 | K60: -0.015163315 | L60: -0.011313169 | M60: -0.0077713762 | N60: -0.013329883 | O60: #DIV/0!
A61: CONTRACARGOS POR FRAUDE | B61: -0.0066824742 | C61: -0.010601722 | D61: -0.017078509 | E61: -0.013879059 | F61: -0.021817281 | G61: -0.0052762067 | H61: -0.017306164 | I61: -0.01901631 | J61: -0.0087403171 | K61: -0.011390941 | L61: -0.005311904 | M61: -0.002016079 | N61: -0.0095093087 | O61: #DIV/0!
A62: DPTO IT | B62: -0.0031754397 | C62: -0.0058363366 | D62: -0.005234763 | E62: -0.022984395 | F62: -0.024861846 | G62: -0.019208613 | H62: -0.007513152 | I62: -0.0069104729 | J62: -0.011913476 | K62: -0.026765308 | L62: -0.0072651835 | M62: -0.010908611 | N62: -0.011629099 | O62: #DIV/0!
A63: PAGINAS VEB | B63: -0.0033318557 | C63: -0.0075835347 | D63: -0.0024184631 | E63: -0.0017962982 | F63: -0.0051005649 | G63: -0.001306777 | H63: -0.0010276087 | I63: -0.0017289449 | J63: 0 | K63: 0 | L63: 0 | M63: -0.00029591236 | N63: -0.0016365668 | O63: #DIV/0!
A64: DPTO BI | B64: -0.0009418824 | C64: -0.0016903061 | D64: -0.01236019 | E64: -0.024614185 | F64: 0.002216718 | G64: -0.0028239661 | H64: -0.0029156473 | I64: -0.0028879159 | J64: -0.0072775871 | K64: -0.0036260213 | L64: -0.00202806 | M64: -0.0013892249 | N64: -0.0039136252 | O64: #DIV/0!
... A81: RESULTADO ANTES DE IMPUESTOS | B81: 0.57054945 | C81: 0.28808105 | D81: 0.24005764 | E81: -0.19151776 | F81: -0.13627228 | G81: -0.46577966 | H81: 0.12220462 | I81: -0.16222057 | J81: 0.14052099 | K81: 0.2881544 | L81: 0.3401506 | M81: 0.39941687 | N81: 0.20978834 | O81: #DIV/0!

Sheet 2023
B1: 2023 | C1: 2023 | D1: 2023 | E1: 2023 | F1: 2023 | G1: 2023 | H1: 2023 | I1: 2023 | J1: 2023 | K1: 2023 | L1: 2023 | M1: 2023
B2: 0.038287782 | C2: 0.029275303 | D2: 0.0090115482 | E2: -0.0042891987 | F2: -0.004276564 | G2: -0.019476806 | H2: 0.0086495466 | I2: 0.0087516483 | J2: 0.0061501168 | K2: 0.017891887 | L2: 0.028874759 | M2: 0.028228485 | N2: 0.018255435
A3: RESULTADO VEB 2023 | B3: ENERO | C3: FEBRERO | D3: MARZO | E3: ABRIL | F3: MAYO | G3: JUNIO | H3: JULIO | I3: AGOSTO | J3: SEPTIEMBRE | K3: OCTUBRE | L3: NOVIEMBRE | M3: DICIEMBRE | N3: 2023
A4: VENTA COMISIONABLE | B4: 8.0862269e+08 | C4: 5.9183437e+08 | D4: 4.6811106e+08 | E4: 4.0395367e+08 | F4: 3.6632394e+08 | G4: 4.0817186e+08 | H4: 6.0546418e+08 | I4: 5.3007803e+08 | J4: 7.0862721e+08 | K4: 8.5043284e+08 | L4: 1.2325181e+09 | M4: 2.1078257e+09 | N4: 9.0819636e+09 | Q4: VENTA COMISIONABLE
A5: TOTAL INGRESOS | B5: 54560186 | C5: 34553608 | D5: 25697481 | E5: 22895767 | F5: 20849071 | G5: 20489493 | H5: 32534603 | I5: 27637017 | J5: 38102149 | K5: 48483408 | L5: 70037900 | M5: 1.1912071e+08 | N5: 5.1496139e+08 | Q5: TOTAL INGRESOS
A6: INGRESOS SOBRE VENTA COMISIONABLE | B6: 0.067472985 | C6: 0.058383915 | D6: 0.05489612 | E6: 0.05667919 | F6: 0.056914303 | G6: 0.050198201 | H6: 0.053734975 | I6: 0.052137639 | J6: 0.053768961 | K6: 0.057010273 | L6: 0.056825047 | M6: 0.056513548 | N6: 0.056701547 | Q6: INGRESOS SOBRE VENTA COMISIONABLE
A7: EGRESOS OPERATIVOS | O7: sobre ing | P7: sobre gtos | Q7: EGRESOS OPERATIVOS
A8: RRHH | B8: -8027076.9 | C8: -7716335.5 | D8: -9026108 | E8: -9780915.1 | F8: -10858336 | G8: -15900313 | H8: -11742946 | I8: -12932031 | J8: -14072616 | K8: -17233021 | L8: -20329003 | M8: -30037027 | N8: -1.6765573e+08 | O8: -0.32556951 | P8: 0.42844866 | Q8: RRHH
A9: DIRECTORIO | B9: -8282156.5 | C9: -914534.64 | D9: -4800945.3 | E9: -8735953.3 | F9: -4693732.9 | G9: -5319344.2 | H9: -5105457 | I9: -800204.37 | J9: -9659288.3 | K9: -5157864.5 | L9: -779782.96 | M9: -10740732 | N9: -64989996 | O9: -0.12620363 | P9: 0.16608366 | Q9: DIRECTORIO
A10: COSTOS DE VENTA A DISTRIBUIR | B10: -4097525.5 | C10: -4048759.2 | D10: -2941526.9 | E10: -1903394.3 | F10: -2099788.4 | G10: -2084209.3 | H10: -4102386.5 | I10: -2782687.6 | J10: -2649201 | K10: -3613944.9 | L10: -4774818.5 | M10: -8123116.5 | N10: -43221358 | O10: -0.08393126 | P10: 0.11045333 | Q10: COSTOS DE VENTA A DISTRIBUIR
A11: INFRAESTRUCTURA TOL | B11: -816118.65 | C11: -829417.52 | D11: -1003894 | E11: -1123250.4 | F11: -995174.34 | G11: -1331957.6 | H11: -2107383.8 | I11: -1350656.3 | J11: -1552646.7 | K11: -1949876 | L11: -1562211.6 | M11: -2829192.1 | N11: -17451779 | O11: -0.03388949 | P11: 0.044598484 | Q11: INFRAESTRUCTURA TOL
A12: GASTOS DE ESTRUCTURA | B12: -658569.32 | C12: -810189.37 | D12: -879103.33 | E12: -1037258.3 | F12: -809335.31 | G12: -1122721.1 | H12: -1502467.9 | I12: -1755985.6 | J12: -1947130.5 | K12: -1603902.3 | L12: -2335761.6 | M12: -1961826.5 | N12: -16424251 | O12: -0.031894141 | P12: 0.04197261 | Q12: GASTOS DE ESTRUCTURA
A13: DPTO MKT & DIEÑO | B13: -8097.96 | C13: -8097.96 | D13: -12021.41 | E13: -18327.96 | F13: -129868.52 | G13: -66928.61 | H13: -94747.08 | I13: -150536.44 | J13: -60045.61 | K13: -52781.07 | L13: -106215.78 | M13: -69845.08 | N13: -777513.48 | O13: -0.0015098481 | P13: 0.0019869563 | Q13: DPTO MKT & DIEÑO
A14: DPTO ATENCION AL CLIENTE/FRAUDE | B14: -120762.99 | C14: -113956.2 | D14: -169630.38 | E14: -120473.87 | F14: -153067.88 | G14: -151243.34 | H14: -429079.74 | I14: -541163.06 | J14: -596602.89 | K14: -571376.38 | L14: -730366.54 | M14: -1404741.1 | N14: -5102464.4 | O14: -0.0099084407 | P14: 0.013039483 | Q14: DPTO ATENCION AL CLIENTE/FRAUDE
A15: DPTO ADMINISTRACION | B15: -332207.99 | C15: -314227.69 | D15: -378360.01 | E15: -381569.84 | F15: -436467.58 | G15: -442675.03 | H15: -475456.92 | I15: -446433.64 | J15: -527923.57 | K15: -577014.67 | L15: -671553.17 | M15: -758009.72 | N15: -5741899.8 | O15: -0.011150156 | P15: 0.014673577 | Q15: DPTO ADMINISTRACION
A16: CONTRACARGOS POR FRAUDE | B16: -401684.07 | C16: -1198909.5 | D16: -881148.34 | E16: -288758.64 | F16: -539977.7 | G16: -349701.08 | H16: -375157.03 | I16: -174734.6 | J16: -283040.08 | K16: -320307.96 | L16: -525867.58 | M16: -711027.2 | N16: -6050313.8 | O16: -0.011749063 | P16: 0.015461737 | Q16: CONTRACARGOS POR FRAUDE
A17: DPTO IT | B17: -100027.86 | C17: -266025.8 | D17: -78521.81 | E17: -90958 | F17: -314590.95 | G17: -586332.04 | H17: -165738.78 | I17: -122444.93 | J17: -143070.63 | K17: -590856.97 | L17: -248251.16 | M17: -465839.03 | N17: -3172658 | O17: -0.0061609628 | P17: 0.0081078116 | Q17: DPTO IT
A18: PAGINAS VEB | B18: -112992.6 | C18: -42278.11 | D18: -118686.06 | E18: -20567.12 | F18: -94091.37 | G18: -29228 | H18: -146354.88 | I18: -24243.47 | J18: -67069.02 | K18: -265005.76 | L18: -283014.81 | M18: -228795.39 | N18: -1432326.6 | O18: -0.0027814252 | P18: 0.0036603486 | Q18: PAGINAS VEB
A19: DPTO BI | B19: -55824.51 | C19: -113574.22 | D19: -453220.46 | E19: -158926.6 | F19: -94984.88 | G19: -129291.95 | H19: -318612.82 | I19: -63626.98 | J19: -1079756.9 | K19: 153664.94 | L19: -83685.9 | M19: -100251.48 | N19: -2498091.8 | O19: -0.0048510274 | P19: 0.0063839399 | Q19: DPTO BI
... A23: OTROS CC | B23: -17060.81 | C23: -98725.38 | D23: -25680.22 | E23: -141983.81 | F23: -63513.1 | G23: -233332.68 | H23: -25650.73 | I23: -150817.57 | J23: -128446.23 | K23: -74594.01 | L23: -48888.09 | M23: -22843.19 | N23: -1031535.8 | O23: -0.0020031324 | P23: 0.0026361171 | Q23: OTROS CC
A25: TOTAL EGRESOS | B25: -23599817 | C25: -17227477 | D25: -21479075 | E25: -24628404 | F25: -22415679 | G25: -28439377 | H25: -27297612 | I25: -22997961 | J25: -33744008 | K25: -33267560 | L25: -34449236 | M25: -59619982 | N25: -3.4916619e+08 | Q25: TOTAL EGRESOS
A26: EGRESOS SOBRE INGRESOS | B26: -0.43254648 | C26: -0.49857246 | D26: -0.83584362 | E26: -1.075675 | F26: -1.0751404 | G26: -1.3879981 | H26: -0.83903321 | I26: -0.83214337 | J26: -0.88561957 | K26: -0.68616381 | L26: -0.49186563 | M26: -0.50050057 | N26: -0.67804343 | Q26: EGRESOS SOBRE INGRESOS
A27: RESULTADO OPERATIVO SIN GTOS EXTRAORDINARIOS | B27: 30960370 | C27: 17326131 | D27: 4218405.4 | E27: -1732637.5 | F27: -1566607.8 | G27: -7949884.1 | H27: 5236990.7 | I27: 4639056.5 | J27: 4358140.1 | K27: 15215848 | L27: 35588664 | M27: 59500725 | N27: 1.657952e+08 | O27: 0.32195657 | P27: RENTABILIDAD ANTES DE GASTOS EXTRAORDINARIOS | Q27: RESULTADO OPERATIVO SIN GTOS EXTRAORDINARIOS
A28: INVERSION_PUBLICIDAD | B28: -544879.84 | C28: -368610.97 | D28: -538565.32 | E28: -378859.84 | F28: -496569.13 | G28: -463502.78 | H28: -551335.08 | I28: -1573087.2 | J28: -183347.64 | K28: -3607006.2 | L28: -5990258.8 | M28: -6057832.3 | N28: -20753855 | O28: -0.040301769 | P28: 0.053037027 | Q28: INVERSION_PUBLICIDAD
A31: INVERSION_EQUIPOS | B31: -266161.99 | C31: 0 | D31: -30036.2 | E31: -379366.09 | F31: -52026.66 | G31: 0 | H31: -777478.89 | I31: -1055334.9 | J31: 0 | K31: -82642.83 | L31: -340481.45 | M31: -126606.34 | N31: -3110135.4 | O31: -0.0060395506 | P31: 0.0079480334 | Q31: INVERSION_EQUIPOS
A32: INVERSION_TOLPOS | B32: -1009800 | C32: 0 | D32: -1558560 | E32: 0 | F32: 0 | G32: 0 | H32: 0 | I32: 0 | J32: 0 | K32: 0 | L32: 0 | M32: 0 | N32: -2568360 | O32: -0.0049874807 | P32: 0.0065635121 | Q32: INVERSION_TOLPOS
A33: INDEMNIZACIONES | B33: 0 | C33: 0 | D33: 0 | E33: 0 | F33: 0 | G33: -265288 | H33: -500000 | I33: 0 | J33: 0 | K33: 0 | L33: -360000 | M33: -1025721 | N33: -2151009 | O33: -0.0041770297 | P33: 0.0054969606 | Q33: INDEMNIZACIONES
A34: INVERSION_CRM | B34: 0 | C34: 0 | D34: 0 | E34: 0 | F34: -1227817.5 | G34: 0 | H34: 0 | I34: 0 | J34: 0 | K34: -2171872.5 | L34: 0 | M34: 0 | N34: -3399690 | O34: -0.0066018348 | P34: 0.008687998 | Q34: INVERSION_CRM
A35: INVERSION_APP | B35: 0 | C35: 0 | D35: 0 | E35: 0 | F35: 0 | G35: 0 | H35: 0 | I35: 0 | J35: 0 | K35: 0 | L35: 0 | M35: -2465000 | N35: -2465000 | O35: -0.0047867666 | P35: 0.0062993729 | Q35: INVERSION_APP
A36: INVERSION_UNIBUS | B36: 0 | C36: 0 | D36: 0 | E36: 0 | F36: 0 | G36: 0 | H36: -200000 | I36: -700000 | J36: -400000 | K36: -499995.6 | L36: -450000 | M36: 0 | N36: -2249995.6 | O36: -0.0043692511 | P36: 0.0057499234 | Q36: INVERSION_UNIBUS
A37: INVERSION_CALIDAD | B37: 0 | C37: 0 | D37: 0 | E37: 0 | F37: -62500 | G37: -428400 | H37: -325000 | I37: -485000 | J37: 0 | K37: 0 | L37: -194648 | M37: -467148 | N37: -1962696 | O37: -0.0038113459 | P37: 0.0050157217 | Q37: INVERSION_CALIDAD
A38: PERDIDA EXTRAORDINARIA | I38: 739022.41 | J38: -2608113.7 | N38: -1869091.3 | O38: -0.0036295756 | P38: 0.0047765124 | Q38: PERDIDA EXTRAORDINARIA
A39: INVERSION_LEY_CONOCIMIENTO | B39: 0 | C39: 0 | D39: 0 | E39: 0 | F39: 0 | G39: -321000 | H39: 0 | I39: -145000 | J39: -552876 | K39: -176131 | L39: -176131 | M39: -241634 | N39: -1612772 | O39: -0.0031318309 | P39: 0.0041214816 | Q39: INVERSION_LEY_CONOCIMIENTO
A40: RESULTADO OPERATIVO TOTAL | B40: 29139528 | C40: 16957520 | D40: 2091243.9 | E40: -2490863.5 | F40: -3405521.1 | G40: -9428074.8 | H40: 2883176.7 | I40: 1419656.8 | J40: 613802.76 | K40: 8678200.1 | L40: 28077145 | M40: 49116783 | N40: 1.236526e+08 | O40: 0.24012013 | P40: RENTABILIDAD ANTES DE INGRESOS FINANCIERAS | Q40: RESULTADO OPERATIVO TOTAL
A41: GANANCIAS FINANCIERAS | B41: 3387599.6 | C41: 3352253.3 | D41: 1671668.4 | E41: 4353459.8 | F41: 1582504.7 | G41: 1689629.6 | H41: 1929570.5 | I41: 16591257 | J41: 4863797.6 | K41: 16845472 | L41: -789655.68 | M41: 17278674 | N41: 72756231 | Q41: GANANCIAS FINANCIERAS
A42: RESULTADO ANTES DE IMPUESTOS | B42: 32527127 | C42: 20309773 | D42: 3762912.3 | E42: 1862596.3 | F42: -1823016.3 | G42: -7738445.3 | H42: 4812747.2 | I42: 18010914 | J42: 5477600.4 | K42: 25523672 | L42: 27287489 | M42: 66395457 | N42: 1.9640883e+08 | Q42: RESULTADO ANTES DE IMPUESTOS
B43: 0.53408043 | C43: 0.49075974 | N43: 48900947
B44: 0.56745352 | C44: 0.50142754

Sheet Project
B1: 44957 | C1: =+EOMONTH(B1,1) -> 44985 | D1: =+EOMONTH(C1,1) -> 45016 | E1: =+EOMONTH(D1,1) -> 45046 | F1: =+EOMONTH(E1,1) -> 45077 | G1: =+EOMONTH(F1,1) -> 45107 | H1: =+EOMONTH(G1,1) -> 45138 | I1: =+EOMONTH(H1,1) -> 45169 | J1: =+EOMONTH(I1,1) -> 45199 | ... AK1: =+EOMONTH(AJ1,1) -> 46022
A2: RESULTADO VEB | B2: ENERO | C2: FEBRERO | D2: MARZO | E2: ABRIL | F2: MAYO | G2: JUNIO | H2: JULIO | I2: AGOSTO | J2: SEPTIEMBRE | K2: OCTUBRE | L2: NOVIEMBRE | M2: DICIEMBRE | N2: ENERO | O2: FEBRERO | P2: MARZO | Q2: ABRIL | R2: MAYO | S2: JUNIO | T2: JULIO | U2: AGOSTO | V2: SEPTIEMBRE | W2: OCTUBRE | X2: NOVIEMBRE | Y2: DICIEMBRE | Z2: ENERO | AA2: FEBRERO | AB2: MARZO | AC2: ABRIL | AD2: MAYO | AE2: JUNIO | AF2: JULIO | AG2: AGOSTO | AH2: SEPTIEMBRE | AI2: OCTUBRE | AJ2: NOVIEMBRE | AK2: DICIEMBRE
A3: VENTA COMISIONABLE | B3: =+'2023'!B4 -> 8.0862269e+08 | C3: =+'2023'!C4 -> 5.9183437e+08 | D3: =+'2023'!D4 -> 4.6811106e+08 | E3: =+'2023'!E4 -> 4.0395367e+08 | F3: =+'2023'!F4 -> 3.6632394e+08 | G3: =+'2023'!G4 -> 4.0817186e+08 | H3: =+'2023'!H4 -> 6.0546418e+08 | I3: =+'2023'!I4 -> 5.3007803e+08 | ... M3: =+'2023'!M4 -> 2.1078257e+09 | N3: =+'2024'!B4 -> 2.2696654e+09 | O3: =+'2024'!C4 -> 1.7520975e+09 | P3: =+'2024'!D4 -> 1.6126006e+09 | Q3: =+'2024'!E4 -> 1.1348092e+09 | R3: =+'2024'!F4 -> 1.2330754e+09 | S3: =+'2024'!G4 -> 1.4957877e+09 | T3: =+'2024'!H4 -> 1.9206542e+09 | U3: =+'2024'!I4 -> 1.5704689e+09 | ... Y3: =+'2024'!M4 -> 4.3850078e+09 | Z3: =+Z4/Z5 -> 4.2329495e+09 | AA3: =+AA4/AA5 -> 3.0830942e+09 | AB3: =+AB4/AB5 -> 2.1145657e+09 | AC3: =+AC4/AC5 -> 1.736546e+09 | AD3: =+AD4/AD5 -> 2.0558465e+09 | AE3: =+AE4/AE5 -> 2.269063e+09 | AF3: =+AF4/AF5 -> 2.5028841e+09 | AG3: =+AG4/AG5 -> 2.4063053e+09 | ... AK3: =+AK4/AK5 -> 5.8089429e+09
A4: TOTAL INGRESOS | B4: =+'2023'!B5 -> 54560186 | C4: =+'2023'!C5 -> 34553608 | D4: =+'2023'!D5 -> 25697481 | E4: =+'2023'!E5 -> 22895767 | F4: =+'2023'!F5 -> 20849071 | G4: =+'2023'!G5 -> 20489493 | H4: =+'2023'!H5 -> 32534603 | I4: =+'2023'!I5 -> 27637017 | ... M4: =+'2023'!M5 -> 1.1912071e+08 | N4: =+'2024'!B5 -> 1.3352809e+08 | O4: =+'2024'!C5 -> 97324729 | P4: =+'2024'!D5 -> 86992578 | Q4: =+'2024'!E5 -> 56571477 | R4: =+'2024'!F5 -> 58501406 | S4: =+'2024'!G5 -> 77816766 | T4: =+'2024'!H5 -> 95987874 | U4: =+'2024'!I5 -> 78591406 | ... Y4: =+'2024'!M5 -> 2.6132399e+08 | Z4: =+RESULTADO_CON_AND!B3 -> 2.417312e+08 | AA4: =+RESULTADO_CON_AND!C3 -> 1.7854281e+08 | AB4: =+RESULTADO_CON_AND!D3 -> 1.1913108e+08 | AC4: =+RESULTADO_CON_AND!E3 -> 1.0126142e+08 | AD4: =+RESULTADO_CON_AND!F3 -> 1.215137e+08 | AE4: =+RESULTADO_CON_AND!G3 -> 1.3366508e+08 | AF4: =+RESULTADO_CON_AND!H3 -> 1.4569493e+08 | AG4: =+RESULTADO_CON_AND!I3 -> 1.3841019e+08 | ... AK4: =+RESULTADO_CON_AND!M3 -> 3.2439887e+08
A5: INGRESOS SOBRE VENTA COMISIONABLE | B5: =+B4/B3 -> 0.067472985 | C5: =+C4/C3 -> 0.058383915 | D5: =+D4/D3 -> 0.05489612 | E5: =+E4/E3 -> 0.05667919 | F5: =+F4/F3 -> 0.056914303 | G5: =+G4/G3 -> 0.050198201 | H5: =+H4/H3 -> 0.053734975 | I5: =+I4/I3 -> 0.052137639 | ... Y5: =+Y4/Y3 -> 0.059594875 | Z5: =+AVERAGE(W5:Y5) -> 0.057107038 | AA5: =RAND()*(AVERAGE(X5:Z5)+0.002-(AVERAGE(X5:Z5)-0.002))+(AVERAGE(X5:Z5)-0.002) -> 0.057910268 | AB5: =RAND()*(AVERAGE(Y5:AA5)+0.002-(AVERAGE(Y5:AA5)-0.002))+(AVERAGE(Y5:AA5)-0.002) -> 0.056338322 | AC5: =RAND()*(AVERAGE(Z5:AB5)+0.002-(AVERAGE(Z5:AB5)-0.002))+(AVERAGE(Z5:AB5)-0.002) -> 0.058311971 | AD5: =RAND()*(AVERAGE(AA5:AC5)+0.002-(AVERAGE(AA5:AC5)-0.002))+(AVERAGE(AA5:AC5)-0.002) -> 0.059106408 | AE5: =RAND()*(AVERAGE(AB5:AD5)+0.002-(AVERAGE(AB5:AD5)-0.002))+(AVERAGE(AB5:AD5)-0.002) -> 0.058907609 | AF5: =RAND()*(AVERAGE(AC5:AE5)+0.002-(AVERAGE(AC5:AE5)-0.002))+(AVERAGE(AC5:AE5)-0.002) -> 0.058210818 | AG5: =RAND()*(AVERAGE(AD5:AF5)+0.002-(AVERAGE(AD5:AF5)-0.002))+(AVERAGE(AD5:AF5)-0.002) -> 0.057519795 | AH5: =RAND()*(AVERAGE(AE5:AG5)+0.002-(AVERAGE(AE5:AG5)-0.002))+(AVERAGE(AE5:AG5)-0.002) -> 0.058540546 | ... AJ5: =RAND()*(AVERAGE(AG5:AI5)+0.002-(AVERAGE(AG5:AI5)-0.002))+(AVERAGE(AG5:AI5)-0.002) -> 0.056689331 | AK5: =RAND()*(AVERAGE(AH5:AJ5)+0.004-(AVERAGE(AH5:AJ5)-0.002))+(AVERAGE(AH5:AJ5)-0.002) -> 0.055844734
A6: EGRESOS OPERATIVOS
A7: RRHH | B7: =+'2023'!B8 -> -8027076.9 | C7: =+'2023'!C8 -> -7716335.5 | D7: =+'2023'!D8 -> -9026108 | E7: =+'2023'!E8 -> -9780915.1 | F7: =+'2023'!F8 -> -10858336 | G7: =+'2023'!G8 -> -15900313 | H7: =+'2023'!H8 -> -11742946 | I7: =+'2023'!I8 -> -12932031 | ... M7: =+'2023'!M8 -> -30037027 | N7: =+'2024'!B8 -> -24291492 | O7: =+'2024'!C8 -> -30217543 | P7: =+'2024'!D8 -> -31171174 | Q7: =+'2024'!E8 -> -31083737 | R7: =+'2024'!F8 -> -32687555 | S7: =+'2024'!G8 -> -51388071 | T7: =+'2024'!H8 -> -38539960 | U7: =+'2024'!I8 -> -39418181 | ... Y7: =+'2024'!M8 -> -74375564 | Z7: =+RESULTADO_CON_AND!B24 -> -57487011 | AA7: =+RESULTADO_CON_AND!C24 -> -57474484 | AB7: =+RESULTADO_CON_AND!D24 -> -56333777 | AC7: =+RESULTADO_CON_AND!E24 -> -57098424 | AD7: =+RESULTADO_CON_AND!F24 -> -56968895 | AE7: =+RESULTADO_CON_AND!G24 -> -85200549 | AF7: =+RESULTADO_CON_AND!H24 -> -66422623 | AG7: =+RESULTADO_CON_AND!I24 -> -69530689 | ... AK7: =+RESULTADO_CON_AND!M24 -> -71551577
